Workbook

Sheet READ ME FIRST
A1: Remax Forge & Fittings - city pages for Andhra Pradesh and Arunachal Pradesh: strategy and developer build pack
A2: remaxforge.com · prepared by errorr.in · research 27 Sep 2026 · workbook 28 Sep 2026
A4: STANDING RULE - FORMS ONLY: no visible phone number, no tel: link, no WhatsApp link or widget, and no telephone property in schema - on any page, image, video or email signature. Every lead comes through a form.
A6: Where things stand (live formulas)
B7: Impressions, all 10 URLs (GSC, about 5.5 months) | C7: ='1. Decision Summary'!$G$18 -> 175 | D7: Tab 1. City pages are a small lever.
B8: Clicks, same period | C8: ='1. Decision Summary'!$J$18 -> 5 | D8: Tab 1.
B9: Impressions per month | C9: ='1. Decision Summary'!$G$19 -> 31.818182 | D9: Tab 1.
B10: Decision for Naharlagun, Pasighat, Tawang, Ziro | C10: ='1. Decision Summary'!$C$5 -> Option A (recommended) | D10: Change it in tab 1, cell C5.
B11: Pages READY to publish | C11: =COUNTIF('6. On-Page Specs'!$Z$5:$Z$13,"READY")&" of "&ROWS('6. On-Page Specs'!$Z$5:$Z$13) -> 0 of 9 | D11: Tab 6 column Z. A page goes live only when it says READY.
B12: Page sections still holding a [CLIENT], [CONFIRM] or [DEV] marker | C12: =SUM('6. On-Page Specs'!$Q$5:$Q$13) -> 118 | D12: Counted per page in tab 6 column Q - they clear as tab 15 is filled.
B13: Client inputs still missing | C13: ='15. Client Inputs'!$C$4 -> 40 of 40 | D13: Tab 15.
B14: ...of which block publishing | C14: ='15. Client Inputs'!$C$5 -> 28 | D14: Tab 15.
B15: Tickets done | C15: ='16. Tests & Rollout'!$C$25 -> 0 of 19 | D15: Tab 16.
B16: P0 tickets still open | C16: ='16. Tests & Rollout'!$C$26 -> 4 | D16: Tab 16 - nothing new publishes while C-01 and C-02 are open.
B17: Photos live | C17: ='13. Media Plan'!$I$21 -> 0 of 15 | D17: Tab 13.
B18: Claims verified | C18: ='17. Sources'!$C$68 -> 0 of 20 | D18: Tab 17 section D.
A20: What this workbook decides
A21: 1 | B21: Rebuild 6 city pages on one template with genuinely local content: Visakhapatnam, Vijayawada, Guntur, Nellore, Kurnool, and Itanagar & Naharlagun.
A22: 2 | B22: Merge the 4 smallest towns (Option A): Naharlagun into /itanagar/; Pasighat, Tawang and Ziro into the Arunachal Pradesh hub - their keywords stay covered.
A23: 3 | B23: Add /market-area/ plus two state hubs, so state-level searches land on a hub and every city page has a parent.
A24: 4 | B24: Capture leads through forms only: a 2-step quote form in the hero, a full RFQ at #rfq, a gated chart, and hidden fields that tag each lead with its city.
A25: 5 | B25: ="Keep perspective: the 10 URLs earned "&TEXT('1. Decision Summary'!$G$18,"0")&" impressions and "&TEXT('1. Decision Summary'!$J$18,"0")&" clicks in about "&TEXT('1. Decision Summary'!$C$4,"0.0")&" months. The biggest lead lever is still the 53 flange product pages, only 2 of them indexed (daily log A-64) - ship C-01 and C-02 first." -> Keep perspective: the 10 URLs earned 175 impressions and 5 clicks in about 5.5 months. The biggest lead lever is still the 53 flange product pages, only 2 of them indexed (daily log A-64) - ship C-01 and C-02 first.
A27: Order of work
A28: 1 | B28: Client: choose Option A or B (tab 1, cell C5) and fill the yellow cells in tab 15 - blocking ones first.
A29: 2 | B29: Developer: ship DL, C-00, C-01 and C-02 in tab 16 before touching any city page.
A30: 3 | B30: Client: one factory shoot and five short videos (tab 13).
A31: 4 | B31: Developer: build the template once (tab 7), then /market-area/ and the hubs, then the P1 city pages - copy from tabs 8, 8b and 9, forms from tab 10, schema from tab 11, links, 301s and sitemap from tab 12.
A32: 5 | B32: Publish a page only when tab 6 column Z says READY; run the QA script (tab 16 section B) after every deploy.
A33: 6 | B33: Request indexing in the tab 12 order; review at W6 and W10 against the KPIs in tab 16.
A35: Tab guide (click a tab name to jump to it)
B36: Tab | C36: What is in it | E36: Who uses it
B37: 1. Decision Summary | C37: GSC data for the 10 URLs, the decision per URL, and the Option A / B switch | E37: Akshat, client
B38: 2. SERP Benchmark | C38: The 20 searches: who ranks, why, and how Remax outranks them | E38: Akshat
B39: 3. Competitor Patterns | C39: The page patterns that rank and their weaknesses | E39: Akshat
B40: 4. Viraj & Sagar Benchmark | C40: What to copy from the two benchmark sites - and what not to | E40: Akshat, writer
B41: 5. Keyword Map | C41: Every keyword mapped to one URL and one place on the page | E41: Akshat, writer
B42: 6. On-Page Specs | C42: Titles, metas, H1s, word floors, links, schema - and the READY gate | E42: Developer, Akshat
B43: 7. Page Template (Dev) | C43: The 14-section template, built once | E43: Developer
B44: 8. City Content (Paste) | C44: Paste-ready copy per section | E44: Developer
B45: 8b. Page Tables (Paste) | C45: Local-demand and product-range tables | E45: Developer
B46: 9. FAQs (Paste) | C46: FAQ copy - also feeds the FAQ schema | E46: Developer
B47: 10. Lead Capture Forms | C47: Forms A, B, C; hidden fields; attribution script; emails | E47: Developer
... B54: 17. Sources | C54: Every source, and the claims still to verify | E54: Akshat
A56: Colour key
B57: Sample | C57: Yellow fill = choose or fill in (client, Akshat, developer status cells)
B58: Sample | C58: Light-yellow fill = the cell still contains a [CLIENT ...], [CONFIRM] or [DEV] marker - never publish it
B59: Sample | C59: Blue text = hardcoded number or assumption - change it if wrong and dependent cells recalculate
B60: Sample | C60: Green text = pulled from another tab by formula - edit the source tab, not this cell
B61: Sample | C61: Green fill = check passes (OK / READY / PASS / Done)
B62: Sample | C62: Red fill = check fails or is blocked
B63: P0 · P1 · P2 · P3 | C63: Priority chips: P0 = blocks everything, P1 = first wave, P2 = second wave, P3 = Arunachal wave
A65: Rules for every page
A66: • | B66: Never publish a [CLIENT], [CONFIRM] or [DEV] marker. Replace it with the client's real answer or the real link, or delete the sentence.
A67: • | B67: Never invent capabilities, prices, approvals, customers or transit times. A capability goes on a page only after tab 15 says yes.
A68: • | B68: One URL per city. State-level searches go to the hub. No separate manufacturer / supplier / material pages per city.
A69: • | B69: No Product, Offer or LocalBusiness schema on city pages - the business has one location, in Mumbai, and the pages say so honestly.
A70: • | B70: The same template extends to the next industrial cities later; small towns merge into their state hub.

Sheet 1. Decision Summary
A1: 1. Decision summary - what happens to each of the 10 URLs
A2: GSC pages export, 20 Feb - 6 Aug 2026 (master plan, sheet '12. GSC Raw Data - Pages'). Each URL shows up twice in GSC - with and without the trailing slash - which is the duplicate-URL fault C-01 fixes.
B4: GSC period covered (months): 20 Feb - 6 Aug 2026 | C4: 5.5 | D4: Blue = hardcoded assumption. Change it if the export covers a different period; the per-month figures below recalculate.
B5: Decision for Naharlagun, Pasighat, Tawang and Ziro | C5: Option A (recommended) | D5: Yellow = choose. Option A: 301 each town to the combined page. Option B: keep as mini-pages - only if the keep-if condition in tab 6 (Option B block) is true. Tabs 2, 5, 6 and 12 follow this cell.
A7: # | B7: City | C7: State | D7: Current URL | E7: Impr. (no slash) | F7: Impr. (slash) | G7: Impr. total | H7: Clicks (no slash) | I7: Clicks (slash) | J7: Clicks total | K7: Avg pos. (no slash) | L7: Avg pos. (slash) | M7: Weighted avg position | N7: Share of impressions | O7: Tier | P7: Decision | Q7: Target URL | R7: Priority | S7: Why
A8: 1 | B8: Visakhapatnam | C8: Andhra Pradesh | D8: /visakhapatnam/ | E8: 25 | F8: 30 | G8: =SUM(E8:F8) -> 55 | H8: 2 | I8: 0 | J8: =SUM(H8:I8) -> 2 | K8: 4.16 | L8: 6.37 | M8: =IFERROR((N(E8)*N(K8)+N(F8)*N(L8))/(N(E8)+N(F8)),"") -> 5.3654545 | N8: =IF($G$18=0,0,G8/$G$18) -> 0.31428571 | O8: A | P8: Rebuild | Q8: /visakhapatnam/ | R8: P1 | S8: The only contested SERP of the ten (4 templated competitor pages + directories). Biggest demand base: RINL, HPCL, ports, Pharma City, and AM/NS India's 8.2 MTPA plant at Anakapalli. Most impressions of the ten.
A9: 2 | B9: Vijayawada | C9: Andhra Pradesh | D9: /vijayawada/ | E9: 13 | F9: 4 | G9: =SUM(E9:F9) -> 17 | H9: 1 | I9: 0 | J9: =SUM(H9:I9) -> 1 | K9: 5 | L9: 6 | M9: =IFERROR((N(E9)*N(K9)+N(F9)*N(L9))/(N(E9)+N(F9)),"") -> 5.2352941 | N9: =IF($G$18=0,0,G9/$G$18) -> 0.097142857 | O9: B | P9: Rebuild | Q9: /vijayawada/ | R9: P1 | S9: Kalikund material-by-city pages and Justdial rank; no strong local page. Real demand: thermal power at Ibrahimpatnam and Amaravati capital works (World Bank + ADB US$1.6 bn committed).
A10: 3 | B10: Guntur | C10: Andhra Pradesh | D10: /guntur/ | E10: 16 | F10: 5 | G10: =SUM(E10:F10) -> 21 | H10: 0 | I10: 0 | J10: =SUM(H10:I10) -> 0 | K10: 3.75 | L10: 6.4 | M10: =IFERROR((N(E10)*N(K10)+N(F10)*N(L10))/(N(E10)+N(F10)),"") -> 4.3809524 | N10: =IF($G$18=0,0,G10/$G$18) -> 0.12 | O10: B | P10: Rebuild | Q10: /guntur/ | R10: P2 | S10: No dedicated competitor page ranks. Cold-chain ammonia plant rooms and mill boilers give a distinct, genuinely useful angle.
A11: 4 | B11: Nellore | C11: Andhra Pradesh | D11: /nellore/ | E11: 15 | F11: 6 | G11: =SUM(E11:F11) -> 21 | H11: 1 | I11: 0 | J11: =SUM(H11:I11) -> 1 | K11: 2.6 | L11: 4.83 | M11: =IFERROR((N(E11)*N(K11)+N(F11)*N(L11))/(N(E11)+N(F11)),"") -> 3.2371429 | N11: =IF($G$18=0,0,G11/$G$18) -> 0.12 | O11: B | P11: Rebuild | Q11: /nellore/ | R11: P1 | S11: BPCL's 9-12 MMTPA refinery near Ramayapatnam (6,000 acres allotted Oct 2025) will pull EPC flange demand; no dedicated supplier page ranks.
A12: 5 | B12: Kurnool | C12: Andhra Pradesh | D12: /kurnool/ | E12: 4 | F12: 4 | G12: =SUM(E12:F12) -> 8 | H12: 0 | I12: 0 | J12: =SUM(H12:I12) -> 0 | K12: 2.25 | L12: 9.75 | M12: =IFERROR((N(E12)*N(K12)+N(F12)*N(L12))/(N(E12)+N(F12)),"") -> 6 | N12: =IF($G$18=0,0,G12/$G$18) -> 0.045714286 | O12: B | P12: Rebuild | Q12: /kurnool/ | R12: P2 | S12: No dedicated competitor page (an Ahmedabad firm's Andhra Pradesh state page ranks). Greenko Pinnapuram pumped storage + lift irrigation = large-bore demand.
A13: 6 | B13: Itanagar | C13: Arunachal Pradesh | D13: /itanagar/ | E13: 8 | F13: 16 | G13: =SUM(E13:F13) -> 24 | H13: 1 | I13: 0 | J13: =SUM(H13:I13) -> 1 | K13: 2.75 | L13: 8.44 | M13: =IFERROR((N(E13)*N(K13)+N(F13)*N(L13))/(N(E13)+N(F13)),"") -> 6.5433333 | N13: =IF($G$18=0,0,G13/$G$18) -> 0.13714286 | O13: C | P13: Rebuild as 'Itanagar & Naharlagun' | Q13: /itanagar/ | R13: P3 | S13: Near-zero competition and small demand. One honest page for the Itanagar-Naharlagun capital region beats two thin ones.
A14: 7 | B14: Naharlagun | C14: Arunachal Pradesh | D14: /naharlagun/ | E14: 6 | F14: 1 | G14: =SUM(E14:F14) -> 7 | H14: 0 | I14: 0 | J14: =SUM(H14:I14) -> 0 | K14: 4.17 | L14: 4 | M14: =IFERROR((N(E14)*N(K14)+N(F14)*N(L14))/(N(E14)+N(F14)),"") -> 4.1457143 | N14: =IF($G$18=0,0,G14/$G$18) -> 0.04 | O14: D (merge) | P14: =IF(LEFT('1. Decision Summary'!$C$5,8)="Option A","301 redirect to "&Q14,"Keep as mini-page (Option B)") -> 301 redirect to /itanagar/ | Q14: =IF(LEFT('1. Decision Summary'!$C$5,8)="Option A","/itanagar/","/naharlagun/ (kept)") -> /itanagar/ | R14: P3 | S14: Twin town of Itanagar in one capital region; one page covers both honestly.
A15: 8 | B15: Pasighat | C15: Arunachal Pradesh | D15: /pasighat/ | F15: 5 | G15: =SUM(E15:F15) -> 5 | I15: 0 | J15: =SUM(H15:I15) -> 0 | L15: 8 | M15: =IFERROR((N(E15)*N(K15)+N(F15)*N(L15))/(N(E15)+N(F15)),"") -> 8 | N15: =IF($G$18=0,0,G15/$G$18) -> 0.028571429 | O15: D (merge) | P15: =IF(LEFT('1. Decision Summary'!$C$5,8)="Option A","301 redirect to "&Q15,"Keep as mini-page (Option B)") -> 301 redirect to /market-area/arunachal-pradesh/ | Q15: =IF(LEFT('1. Decision Summary'!$C$5,8)="Option A","/market-area/arunachal-pradesh/","/pasighat/ (kept)") -> /market-area/arunachal-pradesh/ | R15: P3 | S15: No buyer base to write about; SERP holds only spam pages for other places.
A16: 9 | B16: Tawang | C16: Arunachal Pradesh | D16: /tawang/ | E16: 9 | G16: =SUM(E16:F16) -> 9 | H16: 0 | J16: =SUM(H16:I16) -> 0 | K16: 5.67 | M16: =IFERROR((N(E16)*N(K16)+N(F16)*N(L16))/(N(E16)+N(F16)),"") -> 5.67 | N16: =IF($G$18=0,0,G16/$G$18) -> 0.051428571 | O16: D (merge) | P16: =IF(LEFT('1. Decision Summary'!$C$5,8)="Option A","301 redirect to "&Q16,"Keep as mini-page (Option B)") -> 301 redirect to /market-area/arunachal-pradesh/ | Q16: =IF(LEFT('1. Decision Summary'!$C$5,8)="Option A","/market-area/arunachal-pradesh/","/tawang/ (kept)") -> /market-area/arunachal-pradesh/ | R16: P3 | S16: Negligible flange demand; only one programmatic competitor page exists.
A17: 10 | B17: Ziro | C17: Arunachal Pradesh | D17: /ziro/ | E17: 8 | G17: =SUM(E17:F17) -> 8 | H17: 0 | J17: =SUM(H17:I17) -> 0 | K17: 16.5 | M17: =IFERROR((N(E17)*N(K17)+N(F17)*N(L17))/(N(E17)+N(F17)),"") -> 16.5 | N17: =IF($G$18=0,0,G17/$G$18) -> 0.045714286 | O17: D (merge) | P17: =IF(LEFT('1. Decision Summary'!$C$5,8)="Option A","301 redirect to "&Q17,"Keep as mini-page (Option B)") -> 301 redirect to /market-area/arunachal-pradesh/ | Q17: =IF(LEFT('1. Decision Summary'!$C$5,8)="Option A","/market-area/arunachal-pradesh/","/ziro/ (kept)") -> /market-area/arunachal-pradesh/ | R17: P3 | S17: Negligible demand; worst position of the ten (16.5).
B18: All 10 URLs | E18: =SUM(E8:E17) -> 104 | F18: =SUM(F8:F17) -> 71 | G18: =SUM(G8:G17) -> 175 | H18: =SUM(H8:H17) -> 5 | I18: =SUM(I8:I17) -> 0 | J18: =SUM(J8:J17) -> 5 | M18: =IFERROR((SUMPRODUCT(E8:E17,K8:K17)+SUMPRODUCT(F8:F17,L8:L17))/G18,"") -> 5.7209714 | N18: =SUM(N8:N17) -> 1
B19: Per month | G19: =G18/$C$4 -> 31.818182 | J19: =J18/$C$4 -> 0.90909091
B20: Click-through rate | J20: =IF(G18=0,0,J18/G18) -> 0.028571429
A22: What this means
B23: ="All 10 URLs together earned "&TEXT(G18,"0")&" impressions and "&TEXT(J18,"0")&" clicks in about "&TEXT(C4,"0.0")&" months - roughly "&TEXT(G19,"0")&" impressions a month. City pages are a small lever." -> All 10 URLs together earned 175 impressions and 5 clicks in about 5.5 months - roughly 32 impressions a month. City pages are a small lever.
B24: The biggest lead lever is still the flange product estate: 53 finished product pages, 2 indexed (daily log A-64). Ship C-01 (trailingSlash: true) and C-02 (strip tel:/WhatsApp) before any rebuilt city page goes live - otherwise the new pages inherit the same link fault.
B25: Outside Visakhapatnam the SERPs are weak: no dedicated competitor page ranks for Guntur, Kurnool or Itanagar, and Nellore has one product-by-city page. Page-one positions are realistic once the pages are indexed and linked - not guaranteed (tab 2).
B26: Rebuild 6 pages on one template (tab 7) with genuinely local content (tabs 8-9). Merge the 4 smallest towns (Option A) - their keywords stay covered on the target pages (tab 5).
B27: Nothing publishes while tab 6 says NOT READY: every [CLIENT] and [CONFIRM] marker must be replaced with real data from tab 15, or the sentence deleted. Never guess capabilities, prices or approvals.

Sheet 2. SERP Benchmark
A1: 2. SERP benchmark - 'flanges manufacturer in {city}' and 'flange supplier in {city}' (20 searches)
A2: Checked 27 Sep 2026 with a web-search API, not geo-located Google India - positions shift by location and device. Re-check in an incognito window set to the city, or with a rank tracker, before reporting. No Remax page appeared in any result set.
A4: # | B4: City | C4: Keyword | D4: Results seen (in order) | E4: Dedicated local competitor page? | F4: Why they rank | G4: Their weaknesses | H4: How Remax outranks them | I4: Difficulty (1 easy - 5 hard) | J4: Remax target URL
A5: 1 | B5: Visakhapatnam | C5: flanges manufacturer in Visakhapatnam | D5: 1 TradeIndia - blind flanges, Visakhapatnam category page | 2 TradeIndia - SS flanges, Visakhapatnam | 3 IndiaMART - local retailer listing | 4 Nitech Stainless - templated city page | 5 Justdial - 47 flange manufacturers | 6 Justdial - MS flange manufacturers | 7 Workwise vendor page | 8 Kalikund Steel - alloy steel flanges city page | 9 Rudra Impex - templated city page | E5: Yes (4 templated competitor pages) | F5: Directories: domain authority, huge category-by-city page grids, local listings with prices and reviews. Competitor pages: exact-match URL/title/H1, thousands of internally linked city pages, aged domains. | G5: Templated copy with city-swap errors: Nitech's Vizag page says it made its name 'in the Hyderabad market'; Rudra Impex lists carbide cutters and conveyor belts as flange types and mentions Hubli, Dhar and Chennai. No local industry, no delivery facts, no prices; phone/WhatsApp-first CTAs. | H5: Get indexed and linked first (C-01, C-03 to C-05). Then out-content them on local substance: AM/NS Anakapalli, HPCL, ports, Pharma City; coastal/sour/oxygen material guidance; delivery and document facts; price guidance; GSTIN and real factory media. Realistic target: first page below the directories. | I5: 4 | J5: /visakhapatnam/
A6: 2 | B6: Visakhapatnam | C6: flange supplier in Visakhapatnam | D6: 1 TradeIndia - SS flanges | 2 Riddhi Siddhi Metal Impex - templated city page | 3 Dolphin Rubber - flange gaskets | 4 stainlesssteelscrews.in - flange bolts | 5 Nitech Stainless | 6 Kanakbhuvan - pipe fittings city page | 7 Justdial | 8 Kalikund Steel | 9 Rudra Impex | E6: Yes (templated) | F6: Same as above; two results are intent mismatches (gaskets, bolts), a sign Google lacks good matches. | G6: Riddhi Siddhi claims EIL/IBR/ARAMCO approvals with no evidence on the page and says it covers 'more than 55 cities in Visakhapatnam'. | H6: Same page as the manufacturer query (one URL per city). Answer supplier-intent questions directly in FAQs (local stock? delivery time? documents?). | I6: 3 | J6: /visakhapatnam/
A7: 3 | B7: Vijayawada | C7: flanges manufacturer in Vijayawada | D7: 1 Nova Steel - India page listing Vijayawada | 2 Justdial - flange dealers (Mumbai sellers 'also serve Vijayawada', from Rs 110/kg) | 3-6 Kalikund Steel - SS, super duplex, Monel, Incoloy city pages | 7 AISI 4130 city page (Kalikund) | 8 Steel Pipe Sourcing (astmsteelpipes.com) city page | 9 Diamond Flanges - Kolkata homepage | E7: Yes (Kalikund material-by-city matrix) | F7: Kalikund's material x city matrix (hundreds of pages) plus locality stuffing: Kondapalli, Auto Nagar, Mangalagiri, Mallavalli, Gannavaram, Ibrahimpatnam. | G7: Unreadable keyword lists dated 2021; nothing a buyer can use. Justdial shows Mumbai sellers and a per-kg price anchor - price transparency is expected. | H7: One strong page with material H2s (MS/SS/alloy) to capture 'ss flanges vijayawada' variants, Amaravati and NTTPS content, the Class 150 vs PN16 drilling guide, and a price section. | I7: 3 | J7: /vijayawada/
A8: 4 | B8: Vijayawada | C8: flange supplier in Vijayawada | D8: 1 TradeIndia - local distributor (India Pipe & Fitting Store, Tarapet) | 2 Kiran Industries - flange bolts | 3 stainlesssteelscrews.in - flange bolts | 4 OD Engineers - puddle flange (spun template) | 5-8 Justdial - flange / blind / puddle / split flange dealers | 9 Kalikund Steel | E8: Partial | F8: Directory authority and a genuine local distributor listing; the rest fill gaps. | G8: Three intent mismatches (bolts, puddle flange spam). | H8: Same URL as above; supplier FAQ answers the 'local dealer?' question honestly. | I8: 3 | J8: /vijayawada/
A9: 5 | B9: Guntur | C9: flanges manufacturer in Guntur | D9: 1 IndiaMART - pipe fittings in Guntur | 2 Justdial - aluminium flange distributors (non-local listings) | 3 Snomi (Kolkata) - Guntur in a service list | 4-9 national 'flanges manufacturer in India' pages (Vishal Steel, Petromet, Mesta, Excel Metal, flanges.co, Diamond) | E9: No | F9: No dedicated page exists, so Google falls back to national pages and directories. | G9: Nothing Guntur-specific anywhere on page one. | H9: First indexed, well-linked Guntur page with real local substance (cold chain, agro-processing, IBR, capital region) should reach the top 3. | I9: 2 | J9: /guntur/
A10: 6 | B10: Guntur | C10: flange supplier in Guntur | D10: 1 aajjo - flange spreader tool | 2 IndiaMART directory | 3 Justdial - aluminium flange distributors | 4 Digvijay Metals - city list | 5 Justdial - CS flange dealers, Ashok Nagar (Mumbai firms listed) | 6 TradeIndia seller list | 7 Sagar Steel India page | 8 IndiaMART category | 9 Skyland Metal | E10: No | F10: Directory grids and city-name lists. | G10: Intent mismatch at #1 (a tool). | H10: Same page; answer the 'local supplier?' question in FAQ 1. | I10: 2 | J10: /guntur/
A11: 7 | B11: Nellore | C11: flanges manufacturer in Nellore | D11: 1 Nascent Fittings - blind flange, Nellore (hierarchical /city/india/andhra-pradesh/nellore/... URL) | 2-9 national pages (Bhansali Techno, Sagar Steel, Marcel Piping, Vishal Steel, Rajtilak, Excel Metal, flanges.co, Diamond) | E11: Partial (one product-by-city page) | F11: Clean hierarchical URL on Nascent; otherwise national fallbacks. | G11: Nascent's page is generic blind-flange text with the city name. | H11: Refinery-EPC angle (BPCL Ramayapatnam) plus power and port content; EPC checklist is unique on this SERP. | I11: 2 | J11: /nellore/
A12: 8 | B12: Nellore | C12: flange supplier in Nellore | D12: 1 aajjo - display flange | 2 Justdial - tank flange | 3 Justdial - ASA flange exporters | 4 Marcel Piping - city list | 5 Sagar Steel | 6 Wikipedia - Transport in Nellore | 7-8 Snomi GI/MS flange pages | 9 Vishal Steel | E12: No | F12: Nothing relevant exists; a Wikipedia transport page ranks. | G12: Page one is almost entirely off-intent. | H12: Same page; very achievable top 3 once indexed. | I12: 1 | J12: /nellore/
A13: 9 | B13: Kurnool | C13: flanges manufacturer in Kurnool | D13: 1 MH Infra Project (Ahmedabad) - 'Stainless Steel Flanges in Andhra Pradesh' state page listing districts | 2 Ambica Group - city list | 3 TradeIndia | 4-9 national pages | E13: No (a state page ranks) | F13: A STATE-level page captures the city query - evidence that a good Andhra Pradesh hub helps every AP city. | G13: MH Infra's page is a district list with generic copy. | H13: Kurnool page (pumped storage, irrigation, plate vs forged) plus the AP hub. | I13: 2 | J13: /kurnool/
A14: 10 | B14: Kurnool | C14: flange supplier in Kurnool | D14: 1 Digvijay Metals - city list | 2 Kanakbhuvan - India page | 3 TradeIndia | 4 Kanakbhuvan - Chennai page (wrong city) | 5 IndiaMART | 6 Petromet | 7 Vishal Steel | 8 stackshare 'flange supplier in dubai' (junk) | E14: No | F14: Pure fallback. | G14: A Chennai page and a junk page rank for Kurnool. | H14: Same page; top 3 achievable. | I14: 1 | J14: /kurnool/
A15: 11 | B15: Itanagar | C15: flanges manufacturer in Itanagar | D15: 1-9 national 'flanges manufacturer in India' pages only (Metalica Forging, Marcel, Vishal, Sagar, Metal Forge India, Excel Metal, flanges.co, Induskart, Diamond) | E15: No | F15: No competitor has an Itanagar page. | G15: - | H15: Remax already shows at ~2.8 in GSC; a better page keeps it there. Demand is tiny. | I15: 1 | J15: /itanagar/
A16: 12 | B16: Itanagar | C16: flange supplier in Itanagar | D16: 1 aajjo - refractory anchor | 2 Ananka | 3 TradeIndia | 4 Metalica | 5 IndiaMART | 6 Sagar Steel | 7 Timex Metals | 8 Metal Forge India | 9 Vishal Steel | E16: No | F16: Fallback only. | G16: - | H16: Same page. | I16: 1 | J16: /itanagar/
A17: 13 | B17: Naharlagun | C17: flanges manufacturer in Naharlagun | D17: 1 Meghmani Metal - 'Naharlagun' tag archive, page 6 | 2-9 national pages | E17: No | F17: Tag-archive spam. | G17: - | H17: Covered by the Itanagar & Naharlagun page (Option A). | I17: 1 | J17: =IF(LEFT('1. Decision Summary'!$C$5,8)="Option A","/itanagar/","/naharlagun/ (Option B)") -> /itanagar/
A18: 14 | B18: Naharlagun | C18: flange supplier in Naharlagun | D18: Only rfpindia.com programmatic pages for other places: Nagaon (Assam), Naha (Okinawa), Dadra & Nagar Haveli, Tiha Bargaului (Romania), Ikerasassuaq (Greenland), Susa (Nagorno-Karabakh) ... | E18: No | F18: No page exists for the town at all. | G18: The only 'competitor' is a site generating pages for every place on Earth - the pattern Google's scaled-content policy targets. | H18: Do not compete with a standalone page; Itanagar page covers it. | I18: 1 | J18: =IF(LEFT('1. Decision Summary'!$C$5,8)="Option A","/itanagar/","/naharlagun/ (Option B)") -> /itanagar/
A19: 15 | B19: Pasighat | C19: flanges manufacturer in Pasighat | D19: Noise: a 2022 Debian mailing-list spam email, an enggpro directory entry, a Korean flange maker, rfpindia pages for Passy (France), Cerro de Pasco (Peru), Pasadena (US), Pauri ... | E19: No | F19: No relevant results exist. | G19: - | H19: Arunachal hub section (Option A). | I19: 1 | J19: =IF(LEFT('1. Decision Summary'!$C$5,8)="Option A","/market-area/arunachal-pradesh/","/pasighat/ (Option B)") -> /market-area/arunachal-pradesh/
A20: 16 | B20: Pasighat | C20: flange supplier in Pasighat | D20: rfpindia pages for Panipat, Passy, Cerro de Pasco, Pauri, Pasadena (MD and TX), Pachmarhi, Paucarpata, Passirana di Rho | E20: No | F20: No relevant results exist. | G20: - | H20: Arunachal hub section. | I20: 1 | J20: =IF(LEFT('1. Decision Summary'!$C$5,8)="Option A","/market-area/arunachal-pradesh/","/pasighat/ (Option B)") -> /market-area/arunachal-pradesh/
A21: 17 | B21: Tawang | C21: flanges manufacturer in Tawang | D21: enggpro directory, Debian spam email, Product Hunt profile, rfpindia 'Pipe Fittings Supplier in Tawang' (the only Tawang-named page), enggpro blog, rfpindia pages for Tungkang, Taywarah, Taungdwingyi, Tavush, Plateaux (Togo) | E21: One programmatic page (rfpindia) | F21: No relevant results exist. | G21: - | H21: Arunachal hub section with the cold-service and winter-logistics angle. | I21: 1 | J21: =IF(LEFT('1. Decision Summary'!$C$5,8)="Option A","/market-area/arunachal-pradesh/","/tawang/ (Option B)") -> /market-area/arunachal-pradesh/
A22: 18 | B22: Tawang | C22: flange supplier in Tawang | D22: 1 rfpindia - Pipe Fittings Supplier in Tawang | 2-10 rfpindia pages for Titwan, Tungkang, Keelung, Taywarah, Tutume, Tov (Mongolia), Takaev, Tabora ... | E22: One programmatic page | F22: - | G22: - | H22: Arunachal hub section. | I22: 1 | J22: =IF(LEFT('1. Decision Summary'!$C$5,8)="Option A","/market-area/arunachal-pradesh/","/tawang/ (Option B)") -> /market-area/arunachal-pradesh/
A23: 19 | B23: Ziro | C23: flanges manufacturer in Ziro | D23: Debian spam email, enggpro directory, a Chinese flange maker (Jiangyin Zeli), rfpindia pages for Ozoir-la-Ferriere, Mashonaland East, Kushiro, Zaranj, Isiro, Zareh Sharan, a Viraj listing on expometals | E23: No | F23: - | G23: - | H23: Arunachal hub section. | I23: 1 | J23: =IF(LEFT('1. Decision Summary'!$C$5,8)="Option A","/market-area/arunachal-pradesh/","/ziro/ (Option B)") -> /market-area/arunachal-pradesh/
A24: 20 | B24: Ziro | C24: flange supplier in Ziro | D24: rfpindia pages only: Ozoir-la-Ferriere, Mashonaland East, Risch-Rotkreuz, Matabeleland North, Zarqa, Isiro, Zadar, Kushiro, Zaranj, Zareh Sharan | E24: No | F24: - | G24: - | H24: Arunachal hub section. | I24: 1 | J24: =IF(LEFT('1. Decision Summary'!$C$5,8)="Option A","/market-area/arunachal-pradesh/","/ziro/ (Option B)") -> /market-area/arunachal-pradesh/
B26: Keywords at difficulty 1-2 | C26: =COUNTIF(I5:I24,"<=2")&" of "&COUNT(I5:I24) -> 16 of 20
B27: Average difficulty | C27: =AVERAGE(I5:I24) -> 1.65
B28: Difficulty scale | C28: 1 = no relevant competitor page; 3 = templated/national pages only; 5 = strong dedicated local pages + directories. Judged from the result sets above, not from a tool score.

Sheet 3. Competitor Patterns
A1: 3. Competitor patterns - who ranks for these city keywords, why, and how Remax beats each pattern
A2: Patterns seen across the 20 result sets in tab 2. The lesson: every ranking page wins on exact-match structure and internal linking, not on content quality - Remax can match the structure and beat the content.
A4: # | B4: Competitor / pattern | C4: Page type | D4: Why it ranks | E4: Weakness | F4: How Remax beats it
A5: 1 | B5: IndiaMART / TradeIndia / Justdial / aajjo / Workwise | C5: Directory / marketplace | D5: Domain authority; category x city page grids; local listings with prices, ratings and reviews. | E5: Generic; the buyer must call several sellers; many listings are Mumbai firms 'also serving' the city. Listings expose phone numbers. | F5: Do not fight on authority. Win the dedicated-page slot beneath them and convert better (written quotes, prices, documents). Listing there conflicts with the forms-only rule - client's call.
A6: 2 | B6: Kalikund Steel (kalikundsteel.com/city/...) | C6: Material x city matrix (2021) | D6: Hundreds of exact-match pages, heavy internal linking, locality names stuffed into keyword lists. | E6: Unreadable keyword strings; no buyer information; old. | F6: Capture material variants with H2 sections on ONE city page (never separate city x material pages - avoids the thin-page trap).
A7: 3 | B7: Nitech Stainless | C7: Templated city pages | D7: Exact-match title and URL; site-wide city links. | E7: Template leak: the Visakhapatnam page says the firm made its name 'in the Hyderabad market'. | F7: Local facts only a real supplier would know (sites, routes, documents).
A8: 4 | B8: Rudra Impex | C8: Spun template | D8: Exact-match URLs by city and product. | E8: Lists carbide cutters, conveyor belts and felt sheets as 'types of flange'; names Hubli, Dhar and Chennai on the Vizag page; claims to be the 'largest flange manufacturer in Visakhapatnam'. | F8: Accuracy and plain honesty (we ship from Mumbai).
A9: 5 | B9: Riddhi Siddhi Metal Impex | C9: Templated city pages | D9: Approval claims (EIL, IBR, ARAMCO) and exact-match titles. | E9: No evidence of approvals on the page; 'more than 55 cities in Visakhapatnam'. | F9: State only verifiable credentials: GSTIN with portal link, real certificates, real photos.
A10: 6 | B10: Kanakbhuvan Industries | C10: City pages (pipe fittings / flanges) | D10: Volume of city pages. | E10: Its Chennai page ranks for a Kurnool query - the SERP is that thin. | F10: Dedicated Kurnool page wins by default once indexed.
A11: 7 | B11: Steel Pipe Sourcing (astmsteelpipes.com) | C11: City directory pages | D11: Exact-match URL /vijayawada/flanges.htm. | E11: Generic 'stainless steel products in Vijayawada' copy. | F11: Specific Vijayawada content (NTTPS, Kondapalli, Amaravati drilling standards).
A12: 8 | B12: Nascent Fittings | C12: Hierarchical product x city pages | D12: Clean URL tree /city/india/{state}/{city}/{category}/{product}. | E12: Thin generic text per product with a city name. | F12: Copy the hierarchy idea (state hub -> city), not the thin product x city pages.
A13: 9 | B13: MH Infra Project (Ahmedabad) | C13: State-level page | D13: One Andhra Pradesh page listing all districts ranks for 'flanges manufacturer in Kurnool'. | E13: Generic. | F13: Proof that a strong state hub earns city long-tail: build /market-area/andhra-pradesh/.
A14: 10 | B14: rfpindia.com | C14: Programmatic pages for every place on Earth | D14: Sheer volume; the only results for Naharlagun, Pasighat, Tawang and Ziro queries. | E14: Pages for Greenland, Okinawa and Nagorno-Karabakh villages - textbook scaled-content abuse. | F14: Cautionary example: do not keep near-empty town pages; consolidate them.
A15: 11 | B15: National 'flanges manufacturer in India' pages (Vishal Steel, Marcel Piping, Sagar Steel, Metalica, Excel Metal ...) | C15: Fallback national pages | D15: Rank for small-city queries only because no city page exists; long city-name lists in the copy. | E15: Nothing city-specific. | F15: A genuine city page beats them on relevance once it is indexed.

Sheet 4. Viraj & Sagar Benchmark
A1: 4. Viraj & Sagar Steel benchmark - what to copy, what to skip
A2: Viraj = content depth (capability disclosure). Sagar = educational tables. Remax adopts the depth and the education, fixes the errors, and keeps forms-only lead capture.
A4: # | B4: Element | C4: Viraj (viraj.com/stainless-steel-flanges/) | D4: Sagar Steel (sagarsteel.net/flanges-manufacturer-india/) | E4: What Remax should publish | F4: Where | G4: Adopt?
A5: 1 | B5: Capability disclosure | C5: Integrated forge shop: cutting, forging, ring rolling, CNC lathes, CNC drilling, high-capacity forging press, mobile manipulator; in-house heat treatment and laboratory. | D5: Generic claims ('best state of technology'). | E5: Machine list with photos: forging press or hammer (tonnage), CNC lathes (count, max swing), drilling/VMC, heat-treatment furnace, testing equipment - only what exists. | F5: /manufacturing/ page (new or existing) + 120-word summary on city pages | G5: YES
A6: 2 | B6: Capacity & size range | C6: 18,000 MT per annum; stainless flanges from 1/2" to 40". | D6: 1/2" (15 NB) to 48" (1200 NB), DN10-DN5000. | E6: Monthly capacity and size range per flange type and standard. | F6: Spec tables on product pages; one line on city pages | G6: YES
A7: 3 | B7: Testing list | C7: PMI spectrometer, ultrasonic, tensile, impact (room temp and sub-zero), hardness, microscopy, IGC, dye penetrant. | D7: 'Strict quality testing'. | E7: Honest split between in-house tests and outsourced/TPI tests; certificate type (EN 10204 3.1/3.2). | F7: Quality module (shared) + FAQ | G7: YES
A8: 4 | B8: Approvals & certificates | C8: More than 100 approvals and certifications. | D8: ISO 9001:2008 (a withdrawn edition). | E8: Only real, current certificates. If there are none yet, show GSTIN + portal link and real factory media instead of invented badges. | F8: Trust strip | G8: YES
A9: 5 | B9: Product-type explanations | C9: Accurate engineering descriptions of each flange type. | D9: Short, generic. | E9: Already done: Remax product pages run 6,500-7,800 words. Link to them; do not repeat on city pages. | F9: Product pages | G9: no
A10: 6 | B10: Specification table | C10: - | D10: Types, classes, sizes, facings, grades in one table. | E10: Same format, correct data, on product/material pages; a short filtered version on each city page (tab 8b). | F10: Product pages / city pages | G10: verify
A11: 7 | B11: Chemistry & mechanical tables | C11: - | D11: Present but wrong: tensile and yield columns are swapped on all 7 rows (e.g. F11 shown as tensile 205 / yield 415; ASTM A182 F11 Class 1 is tensile >= 415 MPa, yield >= 205 MPa); F12 and F22 chromium shown as 4-6% (F12 is 0.80-1.25%, F22 is 2.00-2.50%); pipe specs A335, A691 and SA 790 listed as flange grades. | E11: Use tab 14 values, cite the ASTM edition, never copy competitor tables. | F11: Material pages | G11: verify
A12: 8 | B12: Commercial terms | C12: - | D12: Payment modes (LC, TT, cheque), packaging, port of dispatch (Mumbai / Kalamboli), GST rate. | E12: Payment terms, packaging, documents, dispatch point and per-city transit time. | F12: City pages - delivery section | G12: YES
A13: 9 | B13: Supply record by city | C13: - | D13: 'Product supplied x city' table. | E13: Only real past supplies, anonymised (e.g. 'Class 300 weld neck flanges for a Vizag refinery contractor, 2025'). Never invent. | F13: City pages (optional block) | G13: YES (real only)
A14: 10 | B14: FAQs | C14: 4 generic FAQs with brand plugs. | D14: None on the flange page. | E14: 6-8 city-specific FAQs that answer buyer questions (tab 9). | F14: City pages | G14: no
A15: 11 | B15: Catalogue / gated download | C15: PDF catalogues plus a 'Download PDF' form modal that captures details. | D15: Size-chart page. | E15: Gated flange weight & dimension chart PDF (email capture) and catalogue. | F15: Tab 10 (Form C) | G15: YES (PDF)
A16: 12 | B16: Real imagery | C16: Red-hot forging shots, product galleries. | D16: Warehouse stock photos. | E16: Factory photos and videos (incoming) - different ones per city page. | F16: Tab 13 | G16: YES
... A18: 14 | B18: Location pages | C18: None. | D18: 'Cities we supply' lists and many thin city pages. | E18: Fewer, deeper city pages + state hubs; merge towns with no buyers. | F18: Tabs 1 and 12 | G18: no
A20: Do not copy
A21: 1 | B21: WhatsApp and tel: CTAs (Sagar) - conflicts with the forms-only rule.
A22: 2 | B22: Math captcha on the form (Sagar) - adds friction; use an invisible check (Turnstile or reCAPTCHA v3) plus a honeypot (tab 10).
A23: 3 | B23: Sagar's mechanical and chemical tables - they contain errors (tensile and yield swapped, wrong chromium for F12/F22, pipe specs listed as flange grades). See tab 14 before publishing any table.
A24: 4 | B24: Outdated certification claims - Sagar still cites ISO 9001:2008, an edition replaced by ISO 9001:2015 (2008 certificates lapsed in September 2018). Remax shows only current, real certificates.
A25: 5 | B25: Unverifiable scale claims ('largest', 'more than 55 cities in Visakhapatnam') seen on competitor pages - state facts the client can prove.

Sheet 5. Keyword Map
A1: 5. Keyword map - every keyword points to ONE URL per city (no separate manufacturer / supplier / material pages)
A2: No volume column on purpose: the GSC export shows zero city-level queries for these pages in about 5.5 months, and third-party volume estimates at city level are unreliable. Treat every row as low-volume, high-intent.
A4: # | B4: Page | C4: Keyword | D4: Type | E4: Intent | F4: Target URL | G4: Where it goes on the page | H4: Priority | I4: Note
A5: 1 | B5: Visakhapatnam | C5: flange supplier in visakhapatnam | D5: Primary | E5: Commercial - find a supplier | F5: /visakhapatnam/ | G5: Title (front), H1, FAQ 1 | H5: P1
A6: 2 | B6: Visakhapatnam | C6: flanges manufacturer in visakhapatnam | D6: Primary | E6: Commercial - find a maker | F6: /visakhapatnam/ | G6: Title (after the |), subline under H1 ('flanges manufacturer in Mumbai supplying ...'), meta description | H6: P1 | I6: Honest framing: manufacturer in Mumbai, supplier to the city.
A7: 3 | B7: Visakhapatnam | C7: flange manufacturer in visakhapatnam | D7: Variant | E7: Commercial | F7: /visakhapatnam/ | G7: Covered by the two primary placements | H7: P1 | I7: No separate URL.
A8: 4 | B8: Visakhapatnam | C8: flanges dealer in visakhapatnam | D8: Variant (dealer / stockist) | E8: Commercial - local stock | F8: /visakhapatnam/ | G8: FAQ 1 answers it honestly: shipped direct from Mumbai, no local dealer | H8: P1 | I8: Do not claim a local stockist.
A9: 5 | B9: Visakhapatnam | C9: ms flanges visakhapatnam | D9: Material | E9: Commercial | F9: /visakhapatnam/ | G9: Range intro ('Carbon-steel (MS) flanges in ASTM A105') + demand table | H9: P1
A10: 6 | B10: Visakhapatnam | C10: ss flanges visakhapatnam | D10: Material | E10: Commercial | F10: /visakhapatnam/ | G10: Range intro (SS 304/304L, 316/316L) + materials section | H10: P1
A11: 7 | B11: Visakhapatnam | C11: flange price visakhapatnam | D11: Price | E11: Commercial - price check | F11: /visakhapatnam/ | G11: Section 'Flange prices for Visakhapatnam delivery' | H11: P1 | I11: Needs the client's dated Rs/kg bands (tab 15) to compete with directory prices.
A12: 8 | B12: Visakhapatnam | C12: duplex flanges visakhapatnam | D12: Material (niche) | E12: Commercial | F12: /visakhapatnam/ | G12: Materials section (seawater: super duplex F53/F55 or 6Mo F44; duplex F51/F60 for splash zones) + FAQ 4 | H12: P1
A13: 9 | B13: Visakhapatnam | C13: nace flanges visakhapatnam | D13: Spec | E13: Commercial | F13: /visakhapatnam/ | G13: Materials section (sour service) + FAQ 5 + link to the sour-service product page | H13: P1
A14: 10 | B14: Visakhapatnam | C14: flanges for steel plant visakhapatnam | D14: Industry | E14: Commercial | F14: /visakhapatnam/ | G14: Demand table row 1 + FAQ 3 | H14: P1
A15: 11 | B15: Visakhapatnam | C15: flange supplier gajuwaka | D15: Local area | E15: Commercial | F15: /visakhapatnam/ | G15: Section 'Areas we deliver in and around Visakhapatnam' + demand table | H15: P1 | I15: Mention in text only - no locality pages.
A16: 12 | B16: Visakhapatnam | C16: flange supplier autonagar visakhapatnam | D16: Local area | E16: Commercial | F16: /visakhapatnam/ | G16: Section 'Areas we deliver in and around Visakhapatnam' + demand table | H16: P1 | I16: Mention in text only - no locality pages.
A17: 13 | B17: Visakhapatnam | C17: flange supplier duvvada | D17: Local area | E17: Commercial | F17: /visakhapatnam/ | G17: Section 'Areas we deliver in and around Visakhapatnam' + demand table | H17: P1 | I17: Mention in text only - no locality pages.
A18: 14 | B18: Visakhapatnam | C18: flange supplier parawada | D18: Local area | E18: Commercial | F18: /visakhapatnam/ | G18: Section 'Areas we deliver in and around Visakhapatnam' + demand table | H18: P1 | I18: Mention in text only - no locality pages.
A19: 15 | B19: Visakhapatnam | C19: flange supplier anakapalli | D19: Local area | E19: Commercial | F19: /visakhapatnam/ | G19: Section 'Areas we deliver in and around Visakhapatnam' + demand table | H19: P1 | I19: Mention in text only - no locality pages.
A20: 16 | B20: Visakhapatnam | C20: flange supplier in vizag | D20: Alt city name | E20: Commercial | F20: /visakhapatnam/ | G20: H1 '(Vizag)' + meta description | H20: P1
A21: 17 | B21: Vijayawada | C21: flange supplier in vijayawada | D21: Primary | E21: Commercial - find a supplier | F21: /vijayawada/ | G21: Title (front), H1, FAQ 1 | H21: P1
A22: 18 | B22: Vijayawada | C22: flanges manufacturer in vijayawada | D22: Primary | E22: Commercial - find a maker | F22: /vijayawada/ | G22: Title (after the |), subline under H1 ('flanges manufacturer in Mumbai supplying ...'), meta description | H22: P1 | I22: Honest framing: manufacturer in Mumbai, supplier to the city.
A23: 19 | B23: Vijayawada | C23: flange manufacturer in vijayawada | D23: Variant | E23: Commercial | F23: /vijayawada/ | G23: Covered by the two primary placements | H23: P1 | I23: No separate URL.
A24: 20 | B24: Vijayawada | C24: flanges dealer in vijayawada | D24: Variant (dealer / stockist) | E24: Commercial - local stock | F24: /vijayawada/ | G24: FAQ 1 answers it honestly: shipped direct from Mumbai, no local dealer | H24: P1 | I24: Do not claim a local stockist.
A25: 21 | B25: Vijayawada | C25: ms flanges vijayawada | D25: Material | E25: Commercial | F25: /vijayawada/ | G25: Range intro ('Carbon-steel (MS) flanges in ASTM A105') + demand table | H25: P1
A26: 22 | B26: Vijayawada | C26: ss flanges vijayawada | D26: Material | E26: Commercial | F26: /vijayawada/ | G26: Range intro (SS 304/304L, 316/316L) + materials section | H26: P1
A27: 23 | B27: Vijayawada | C27: flange price vijayawada | D27: Price | E27: Commercial - price check | F27: /vijayawada/ | G27: Section 'Pricing water-project and power-plant flanges' | H27: P1 | I27: Needs the client's dated Rs/kg bands (tab 15) to compete with directory prices.
A28: 24 | B28: Vijayawada | C28: pn16 flanges vijayawada | D28: Spec | E28: Commercial | F28: /vijayawada/ | G28: Materials section 'Class 150 or PN16?' + FAQ 3 | H28: P1
A29: 25 | B29: Vijayawada | C29: flanges for amaravati projects | D29: Industry / project | E29: Commercial | F29: /vijayawada/ | G29: Demand table (capital city construction) + FAQ 2 | H29: P1
A30: 26 | B30: Vijayawada | C30: f22 flanges vijayawada | D30: Material (niche) | E30: Commercial | F30: /vijayawada/ | G30: Materials section (power-plant steam) + FAQ 4 | H30: P1
A31: 27 | B31: Vijayawada | C31: flange supplier kondapalli | D31: Local area | E31: Commercial | F31: /vijayawada/ | G31: Section 'Areas we deliver around Vijayawada' + demand table | H31: P1 | I31: Mention in text only - no locality pages.
A32: 28 | B32: Vijayawada | C32: flange supplier ibrahimpatnam | D32: Local area | E32: Commercial | F32: /vijayawada/ | G32: Section 'Areas we deliver around Vijayawada' + demand table | H32: P1 | I32: Mention in text only - no locality pages.
A33: 29 | B33: Vijayawada | C33: flange supplier autonagar vijayawada | D33: Local area | E33: Commercial | F33: /vijayawada/ | G33: Section 'Areas we deliver around Vijayawada' + demand table | H33: P1 | I33: Mention in text only - no locality pages.
A34: 30 | B34: Vijayawada | C34: flange supplier amaravati | D34: Local area | E34: Commercial | F34: /vijayawada/ | G34: Section 'Areas we deliver around Vijayawada' + demand table | H34: P1 | I34: Mention in text only - no locality pages.
A35: 31 | B35: Vijayawada | C35: flange supplier gannavaram | D35: Local area | E35: Commercial | F35: /vijayawada/ | G35: Section 'Areas we deliver around Vijayawada' + demand table | H35: P1 | I35: Mention in text only - no locality pages.
A36: 32 | B36: Guntur | C36: flange supplier in guntur | D36: Primary | E36: Commercial - find a supplier | F36: /guntur/ | G36: Title (front), H1, FAQ 1 | H36: P2
A37: 33 | B37: Guntur | C37: flanges manufacturer in guntur | D37: Primary | E37: Commercial - find a maker | F37: /guntur/ | G37: Title (after the |), subline under H1 ('flanges manufacturer in Mumbai supplying ...'), meta description | H37: P2 | I37: Honest framing: manufacturer in Mumbai, supplier to the city.
A38: 34 | B38: Guntur | C38: flange manufacturer in guntur | D38: Variant | E38: Commercial | F38: /guntur/ | G38: Covered by the two primary placements | H38: P2 | I38: No separate URL.
A39: 35 | B39: Guntur | C39: flanges dealer in guntur | D39: Variant (dealer / stockist) | E39: Commercial - local stock | F39: /guntur/ | G39: FAQ 1 answers it honestly: shipped direct from Mumbai, no local dealer | H39: P2 | I39: Do not claim a local stockist.
A40: 36 | B40: Guntur | C40: ms flanges guntur | D40: Material | E40: Commercial | F40: /guntur/ | G40: Range intro ('Carbon-steel (MS) flanges in ASTM A105') + demand table | H40: P2
A41: 37 | B41: Guntur | C41: ss flanges guntur | D41: Material | E41: Commercial | F41: /guntur/ | G41: Range intro (SS 304/304L, 316/316L) + materials section | H41: P2
A42: 38 | B42: Guntur | C42: flange price guntur | D42: Price | E42: Commercial - price check | F42: /guntur/ | G42: Section 'What drives the price of refrigeration and boiler flanges' | H42: P2 | I42: Needs the client's dated Rs/kg bands (tab 15) to compete with directory prices.
A43: 39 | B43: Guntur | C43: ammonia refrigeration flanges guntur | D43: Industry | E43: Commercial | F43: /guntur/ | G43: Materials section + demand table (cold chain) | H43: P2
A44: 40 | B44: Guntur | C44: ibr flanges guntur | D44: Spec | E44: Commercial | F44: /guntur/ | G44: Materials section (IBR paragraph) - only if IBR supply is confirmed | H44: P2
A45: 41 | B45: Guntur | C45: lf2 flanges guntur | D45: Material (niche) | E45: Commercial | F45: /guntur/ | G45: Materials section (below -29 °C) | H45: P2
A46: 42 | B46: Guntur | C46: flange supplier mangalagiri | D46: Local area | E46: Commercial | F46: /guntur/ | G46: Section 'Areas we deliver around Guntur' + demand table | H46: P2 | I46: Mention in text only - no locality pages.
A47: 43 | B47: Guntur | C47: flange supplier tadepalli | D47: Local area | E47: Commercial | F47: /guntur/ | G47: Section 'Areas we deliver around Guntur' + demand table | H47: P2 | I47: Mention in text only - no locality pages.
A48: 44 | B48: Guntur | C48: flange supplier tenali | D48: Local area | E48: Commercial | F48: /guntur/ | G48: Section 'Areas we deliver around Guntur' + demand table | H48: P2 | I48: Mention in text only - no locality pages.
A49: 45 | B49: Nellore | C49: flange supplier in nellore | D49: Primary | E49: Commercial - find a supplier | F49: /nellore/ | G49: Title (front), H1, FAQ 1 | H49: P1
A50: 46 | B50: Nellore | C50: flanges manufacturer in nellore | D50: Primary | E50: Commercial - find a maker | F50: /nellore/ | G50: Title (after the |), subline under H1 ('flanges manufacturer in Mumbai supplying ...'), meta description | H50: P1 | I50: Honest framing: manufacturer in Mumbai, supplier to the city.
A51: 47 | B51: Nellore | C51: flange manufacturer in nellore | D51: Variant | E51: Commercial | F51: /nellore/ | G51: Covered by the two primary placements | H51: P1 | I51: No separate URL.
A52: 48 | B52: Nellore | C52: flanges dealer in nellore | D52: Variant (dealer / stockist) | E52: Commercial - local stock | F52: /nellore/ | G52: FAQ 1 answers it honestly: shipped direct from Mumbai, no local dealer | H52: P1 | I52: Do not claim a local stockist.
A53: 49 | B53: Nellore | C53: ms flanges nellore | D53: Material | E53: Commercial | F53: /nellore/ | G53: Range intro ('Carbon-steel (MS) flanges in ASTM A105') + demand table | H53: P1
A54: 50 | B54: Nellore | C54: ss flanges nellore | D54: Material | E54: Commercial | F54: /nellore/ | G54: Range intro (SS 304/304L, 316/316L) + materials section | H54: P1
A55: 51 | B55: Nellore | C55: flange price nellore | D55: Price | E55: Commercial - price check | F55: /nellore/ | G55: Section 'How project flange packages are priced' | H55: P1 | I55: Needs the client's dated Rs/kg bands (tab 15) to compete with directory prices.
A56: 52 | B56: Nellore | C56: flange supplier for bpcl ramayapatnam refinery | D56: Project | E56: Commercial | F56: /nellore/ | G56: Demand table row 1 + FAQ 2 + materials checklist | H56: P1
A57: 53 | B57: Nellore | C57: rtj flanges nellore | D57: Spec | E57: Commercial | F57: /nellore/ | G57: FAQ 4 - only if RTJ machining is confirmed | H57: P1
A58: 54 | B58: Nellore | C58: lf2 flanges nellore | D58: Material (niche) | E58: Commercial | F58: /nellore/ | G58: Materials checklist item 3 + FAQ 3 | H58: P1
A59: 55 | B59: Nellore | C59: flange supplier krishnapatnam | D59: Local area | E59: Commercial | F59: /nellore/ | G59: Section 'Areas we deliver around Nellore' + demand table | H59: P1 | I59: Mention in text only - no locality pages.
A60: 56 | B60: Nellore | C60: flange supplier ramayapatnam | D60: Local area | E60: Commercial | F60: /nellore/ | G60: Section 'Areas we deliver around Nellore' + demand table | H60: P1 | I60: Mention in text only - no locality pages.
A61: 57 | B61: Nellore | C61: flange supplier kavali | D61: Local area | E61: Commercial | F61: /nellore/ | G61: Section 'Areas we deliver around Nellore' + demand table | H61: P1 | I61: Mention in text only - no locality pages.
A62: 58 | B62: Nellore | C62: flange supplier muthukur | D62: Local area | E62: Commercial | F62: /nellore/ | G62: Section 'Areas we deliver around Nellore' + demand table | H62: P1 | I62: Mention in text only - no locality pages.
A63: 59 | B63: Kurnool | C63: flange supplier in kurnool | D63: Primary | E63: Commercial - find a supplier | F63: /kurnool/ | G63: Title (front), H1, FAQ 1 | H63: P2
A64: 60 | B64: Kurnool | C64: flanges manufacturer in kurnool | D64: Primary | E64: Commercial - find a maker | F64: /kurnool/ | G64: Title (after the |), subline under H1 ('flanges manufacturer in Mumbai supplying ...'), meta description | H64: P2 | I64: Honest framing: manufacturer in Mumbai, supplier to the city.
A65: 61 | B65: Kurnool | C65: flange manufacturer in kurnool | D65: Variant | E65: Commercial | F65: /kurnool/ | G65: Covered by the two primary placements | H65: P2 | I65: No separate URL.
A66: 62 | B66: Kurnool | C66: flanges dealer in kurnool | D66: Variant (dealer / stockist) | E66: Commercial - local stock | F66: /kurnool/ | G66: FAQ 1 answers it honestly: shipped direct from Mumbai, no local dealer | H66: P2 | I66: Do not claim a local stockist.
A67: 63 | B67: Kurnool | C67: ms flanges kurnool | D67: Material | E67: Commercial | F67: /kurnool/ | G67: Range intro ('Carbon-steel (MS) flanges in ASTM A105') + demand table | H67: P2
A68: 64 | B68: Kurnool | C68: ss flanges kurnool | D68: Material | E68: Commercial | F68: /kurnool/ | G68: Range intro (SS 304/304L, 316/316L) + materials section | H68: P2
A69: 65 | B69: Kurnool | C69: flange price kurnool | D69: Price | E69: Commercial - price check | F69: /kurnool/ | G69: Section 'How large-bore water flanges are priced' | H69: P2 | I69: Needs the client's dated Rs/kg bands (tab 15) to compete with directory prices.
A70: 66 | B70: Kurnool | C70: large diameter flanges kurnool | D70: Spec | E70: Commercial | F70: /kurnool/ | G70: FAQ 2 + materials section | H70: P2
A71: 67 | B71: Kurnool | C71: plate flanges kurnool | D71: Spec | E71: Commercial | F71: /kurnool/ | G71: Materials section 'Plate flange or forged flange?' + FAQ 4 | H71: P2
A72: 68 | B72: Kurnool | C72: awwa c207 flanges | D72: Spec (informational) | E72: Commercial | F72: /kurnool/ | G72: FAQ 3 | H72: P2
A73: 69 | B73: Kurnool | C73: flange supplier orvakal | D73: Local area | E73: Commercial | F73: /kurnool/ | G73: Section 'Areas we deliver around Kurnool' + demand table | H73: P2 | I73: Mention in text only - no locality pages.
A74: 70 | B74: Kurnool | C74: flange supplier nandyal | D74: Local area | E74: Commercial | F74: /kurnool/ | G74: Section 'Areas we deliver around Kurnool' + demand table | H74: P2 | I74: Mention in text only - no locality pages.
A75: 71 | B75: Kurnool | C75: flange supplier panyam | D75: Local area | E75: Commercial | F75: /kurnool/ | G75: Section 'Areas we deliver around Kurnool' + demand table | H75: P2 | I75: Mention in text only - no locality pages.
A76: 72 | B76: Itanagar & Naharlagun | C76: flange supplier in itanagar | D76: Primary | E76: Commercial - find a supplier | F76: /itanagar/ | G76: Title (front), H1, FAQ 1 | H76: P3
A77: 73 | B77: Itanagar & Naharlagun | C77: flanges manufacturer in itanagar | D77: Primary | E77: Commercial - find a maker | F77: /itanagar/ | G77: Title (after the |), subline under H1 ('flanges manufacturer in Mumbai supplying ...'), meta description | H77: P3 | I77: Honest framing: manufacturer in Mumbai, supplier to the city.
A78: 74 | B78: Itanagar & Naharlagun | C78: flange manufacturer in itanagar | D78: Variant | E78: Commercial | F78: /itanagar/ | G78: Covered by the two primary placements | H78: P3 | I78: No separate URL.
A79: 75 | B79: Itanagar & Naharlagun | C79: flanges dealer in itanagar | D79: Variant (dealer / stockist) | E79: Commercial - local stock | F79: /itanagar/ | G79: FAQ 1 answers it honestly: shipped direct from Mumbai, no local dealer | H79: P3 | I79: Do not claim a local stockist.
A80: 76 | B80: Itanagar & Naharlagun | C80: ms flanges itanagar | D80: Material | E80: Commercial | F80: /itanagar/ | G80: Range intro ('Carbon-steel (MS) flanges in ASTM A105') + demand table | H80: P3
A81: 77 | B81: Itanagar & Naharlagun | C81: ss flanges itanagar | D81: Material | E81: Commercial | F81: /itanagar/ | G81: Range intro (SS 304/304L, 316/316L) + materials section | H81: P3
A82: 78 | B82: Itanagar & Naharlagun | C82: flange price itanagar | D82: Price | E82: Commercial - price check | F82: /itanagar/ | G82: Section 'Freight and pricing for small Northeast orders' | H82: P3 | I82: Needs the client's dated Rs/kg bands (tab 15) to compete with directory prices.
A83: 79 | B83: Itanagar & Naharlagun | C83: flange delivery arunachal pradesh | D83: Logistics | E83: Commercial | F83: /itanagar/ | G83: Section 'Planning a flange delivery to Arunachal Pradesh' + FAQ 2-4 | H83: P3
A84: 80 | B84: Itanagar & Naharlagun | C84: flanges for water supply schemes itanagar | D84: Industry | E84: Commercial | F84: /itanagar/ | G84: Demand table (water supply) + FAQ 5 | H84: P3
A85: 81 | B85: Itanagar & Naharlagun | C85: flange supplier nirjuli | D85: Local area | E85: Commercial | F85: /itanagar/ | G85: Section 'Areas we deliver in the capital region' + demand table | H85: P3 | I85: Mention in text only - no locality pages.
A86: 82 | B86: Itanagar & Naharlagun | C86: flange supplier doimukh | D86: Local area | E86: Commercial | F86: /itanagar/ | G86: Section 'Areas we deliver in the capital region' + demand table | H86: P3 | I86: Mention in text only - no locality pages.
A87: 83 | B87: Itanagar & Naharlagun | C87: flange supplier banderdewa | D87: Local area | E87: Commercial | F87: /itanagar/ | G87: Section 'Areas we deliver in the capital region' + demand table | H87: P3 | I87: Mention in text only - no locality pages.
A88: 84 | B88: Andhra Pradesh hub | C88: flange supplier in andhra pradesh | D88: Primary | E88: Commercial | F88: /market-area/andhra-pradesh/ | G88: Title (front), H1 | H88: P1 | I88: State-level queries go to the hub, never to a city page.
A89: 85 | B89: Andhra Pradesh hub | C89: flanges manufacturer in andhra pradesh | D89: Primary | E89: Commercial | F89: /market-area/andhra-pradesh/ | G89: Subline under H1 + meta description | H89: P1 | I89: State-level queries go to the hub, never to a city page.
A90: 86 | B90: Arunachal Pradesh hub | C90: flange supplier in arunachal pradesh | D90: Primary | E90: Commercial | F90: /market-area/arunachal-pradesh/ | G90: Title (front), H1 | H90: P3 | I90: State-level queries go to the hub, never to a city page.
A91: 87 | B91: Arunachal Pradesh hub | C91: flanges manufacturer in arunachal pradesh | D91: Primary | E91: Commercial | F91: /market-area/arunachal-pradesh/ | G91: Subline under H1 + meta description | H91: P3 | I91: State-level queries go to the hub, never to a city page.
A92: 88 | B92: Naharlagun (merged) | C92: flange supplier in naharlagun | D92: Primary (merged town) | E92: Commercial | F92: =IF(LEFT('1. Decision Summary'!$C$5,8)="Option A","/itanagar/","/naharlagun/") -> /itanagar/ | G92: Title + H1 of /itanagar/ (both towns named) + FAQ 1 | H92: P3 | I92: Follows the Option A/B choice in tab 1.
A93: 89 | B93: Naharlagun (merged) | C93: flanges manufacturer in naharlagun | D93: Primary (merged town) | E93: Commercial | F93: =IF(LEFT('1. Decision Summary'!$C$5,8)="Option A","/itanagar/","/naharlagun/") -> /itanagar/ | G93: Title + H1 of /itanagar/ (both towns named) + FAQ 1 | H93: P3 | I93: Follows the Option A/B choice in tab 1.
A94: 90 | B94: Pasighat (merged) | C94: flange supplier in pasighat | D94: Primary (merged town) | E94: Commercial | F94: =IF(LEFT('1. Decision Summary'!$C$5,8)="Option A","/market-area/arunachal-pradesh/","/pasighat/") -> /market-area/arunachal-pradesh/ | G94: Hub section headed 'Pasighat' (H2) on /market-area/arunachal-pradesh/ | H94: P3 | I94: Follows the Option A/B choice in tab 1.
A95: 91 | B95: Pasighat (merged) | C95: flanges manufacturer in pasighat | D95: Primary (merged town) | E95: Commercial | F95: =IF(LEFT('1. Decision Summary'!$C$5,8)="Option A","/market-area/arunachal-pradesh/","/pasighat/") -> /market-area/arunachal-pradesh/ | G95: Hub section headed 'Pasighat' (H2) on /market-area/arunachal-pradesh/ | H95: P3 | I95: Follows the Option A/B choice in tab 1.
A96: 92 | B96: Tawang (merged) | C96: flange supplier in tawang | D96: Primary (merged town) | E96: Commercial | F96: =IF(LEFT('1. Decision Summary'!$C$5,8)="Option A","/market-area/arunachal-pradesh/","/tawang/") -> /market-area/arunachal-pradesh/ | G96: Hub section headed 'Tawang' (H2) on /market-area/arunachal-pradesh/ | H96: P3 | I96: Follows the Option A/B choice in tab 1.
A97: 93 | B97: Tawang (merged) | C97: flanges manufacturer in tawang | D97: Primary (merged town) | E97: Commercial | F97: =IF(LEFT('1. Decision Summary'!$C$5,8)="Option A","/market-area/arunachal-pradesh/","/tawang/") -> /market-area/arunachal-pradesh/ | G97: Hub section headed 'Tawang' (H2) on /market-area/arunachal-pradesh/ | H97: P3 | I97: Follows the Option A/B choice in tab 1.
A98: 94 | B98: Ziro (merged) | C98: flange supplier in ziro | D98: Primary (merged town) | E98: Commercial | F98: =IF(LEFT('1. Decision Summary'!$C$5,8)="Option A","/market-area/arunachal-pradesh/","/ziro/") -> /market-area/arunachal-pradesh/ | G98: Hub section headed 'Ziro' (H2) on /market-area/arunachal-pradesh/ | H98: P3 | I98: Follows the Option A/B choice in tab 1.
A99: 95 | B99: Ziro (merged) | C99: flanges manufacturer in ziro | D99: Primary (merged town) | E99: Commercial | F99: =IF(LEFT('1. Decision Summary'!$C$5,8)="Option A","/market-area/arunachal-pradesh/","/ziro/") -> /market-area/arunachal-pradesh/ | G99: Hub section headed 'Ziro' (H2) on /market-area/arunachal-pradesh/ | H99: P3 | I99: Follows the Option A/B choice in tab 1.

Sheet 6. On-Page Specs
A1: 6. On-page specs - one row per URL. A page publishes only when column Z says READY.
A2: Title <= 60 chars, meta 120-160 chars. Word floors stop thin pages - they are not targets, never pad. Word counts and open placeholders are live formulas over tabs 8, 8b and 9.
A4: Page key | B4: Page | C4: Canonical URL (absolute, slash form) | D4: Build status | E4: Priority | F4: Title tag | G4: Title chars | H4: Title check | I4: Meta description | J4: Meta chars | K4: Meta check | L4: H1 | M4: Subline under H1 | N4: Word floor (no padding) | O4: Words drafted (tabs 8+8b+9) | P4: Word check | Q4: Open placeholders | R4: Uniqueness target | S4: Internal links OUT (add these) | T4: Internal links IN (must exist at launch) | U4: Photos (tab 13) | V4: Video (tab 13) | W4: Schema (tab 11) | X4: Breadcrumb | Y4: Meta robots | Z4: Ready to publish?
A5: vizag | B5: Visakhapatnam | C5: https://remaxforge.com/visakhapatnam/ | D5: REBUILD | E5: P1 | F5: Flange Supplier in Visakhapatnam | Flanges Manufacturer | G5: =LEN(F5) -> 55 | H5: =IF(G5=0,"MISSING",IF(G5>60,"TOO LONG",IF(G5<30,"TOO SHORT","OK"))) -> OK | I5: Forged flanges for Vizag and Anakapalli steel plants, the refinery, ports and Pharma City. CS, SS, alloy and NACE grades from Mumbai. Written quotes. | J5: =LEN(I5) -> 149 | K5: =IF(J5=0,"MISSING",IF(J5>160,"TOO LONG",IF(J5<120,"SHORT","OK"))) -> OK | L5: Flange Supplier in Visakhapatnam (Vizag) | M5: Flanges manufacturer in Mumbai supplying Visakhapatnam and Anakapalli steel, refinery, port, power and pharma sites. | N5: 1400 | O5: =SUMIFS('8. City Content (Paste)'!$H$5:$H$400,'8. City Content (Paste)'!$A$5:$A$400,$A5)+SUMIFS('8b. Page Tables (Paste)'!$H$5:$H$300,'8b. Page Tables (Paste)'!$A$5:$A$300,$A5)+SUMIFS('9. FAQs (Paste)'!$F$5:$F$200,'9. FAQs (Paste)'!$A$5:$A$200,$A5) -> 1703 | P5: =IF(O5>=N5,"OK","BELOW FLOOR") -> OK | Q5: =COUNTIFS('8. City Content (Paste)'!$A$5:$A$400,$A5,'8. City Content (Paste)'!$I$5:$I$400,"<>Ready")+COUNTIFS('8b. Page Tables (Paste)'!$A$5:$A$300,$A5,'8b. Page Tables (Paste)'!$I$5:$I$300,"<>Ready")+COUNTIFS('9. FAQs (Paste)'!$A$5:$A$200,$A5,'9. FAQs (Paste)'!$G$5:$G$200,"<>Ready") -> 18 | R5: >= 65% unique 5-word shingles; max similarity to any other city page <= 0.25 | S5: Flange supply across Andhra Pradesh → /market-area/andhra-pradesh/ Nellore (refinery projects) → /nellore/ Sour-service NACE flanges → /products/flanges/sour-service-nace-flange/ Flanges for oil & gas → /industries/oil-and-gas/ Pipe flanges guide → /blogs/pipe-flanges-guide/ + 7 product-type links (tab 8b) | T5: AP hub (city section + list); /nellore/ related links; /industries/oil-and-gas/ 'Where we supply' block (optional) | U5: P03, P07, P09 | V5: V1 | W5: WebPage, BreadcrumbList, Service, FAQPage (+ sitewide Organization, WebSite, Person) | X5: Home › Areas We Supply › Andhra Pradesh › Visakhapatnam | Y5: index, follow | Z5: =IF(AND(H5="OK",K5="OK",P5="OK",Q5=0),"READY","NOT READY") -> NOT READY
A6: vijayawada | B6: Vijayawada | C6: https://remaxforge.com/vijayawada/ | D6: REBUILD | E6: P1 | F6: Flange Supplier in Vijayawada | Flanges Manufacturer | G6: =LEN(F6) -> 52 | H6: =IF(G6=0,"MISSING",IF(G6>60,"TOO LONG",IF(G6<30,"TOO SHORT","OK"))) -> OK | I6: Flanges for Vijayawada power stations, Kondapalli industry and Amaravati water and building works. ASME, EN and IS drilling. Written quotes by email. | J6: =LEN(I6) -> 149 | K6: =IF(J6=0,"MISSING",IF(J6>160,"TOO LONG",IF(J6<120,"SHORT","OK"))) -> OK | L6: Flange Supplier in Vijayawada & the Amaravati Capital Region | M6: Flanges manufacturer in Mumbai supplying power, industrial and capital-region projects around Vijayawada. | N6: 1100 | O6: =SUMIFS('8. City Content (Paste)'!$H$5:$H$400,'8. City Content (Paste)'!$A$5:$A$400,$A6)+SUMIFS('8b. Page Tables (Paste)'!$H$5:$H$300,'8b. Page Tables (Paste)'!$A$5:$A$300,$A6)+SUMIFS('9. FAQs (Paste)'!$F$5:$F$200,'9. FAQs (Paste)'!$A$5:$A$200,$A6) -> 1280 | P6: =IF(O6>=N6,"OK","BELOW FLOOR") -> OK | Q6: =COUNTIFS('8. City Content (Paste)'!$A$5:$A$400,$A6,'8. City Content (Paste)'!$I$5:$I$400,"<>Ready")+COUNTIFS('8b. Page Tables (Paste)'!$A$5:$A$300,$A6,'8b. Page Tables (Paste)'!$I$5:$I$300,"<>Ready")+COUNTIFS('9. FAQs (Paste)'!$A$5:$A$200,$A6,'9. FAQs (Paste)'!$G$5:$G$200,"<>Ready") -> 17 | R6: >= 65% unique 5-word shingles; max similarity to any other city page <= 0.25 | S6: Flange supply across Andhra Pradesh → /market-area/andhra-pradesh/ Guntur → /guntur/ Pipe flanges guide → /blogs/pipe-flanges-guide/ Kurnool (large-bore water projects) → /kurnool/ + 7 product-type links (tab 8b) | T6: AP hub; /guntur/ and /kurnool/ related links | U6: P05, P06, P12 | V6: V2 | W6: WebPage, BreadcrumbList, Service, FAQPage (+ sitewide Organization, WebSite, Person) | X6: Home › Areas We Supply › Andhra Pradesh › Vijayawada | Y6: index, follow | Z6: =IF(AND(H6="OK",K6="OK",P6="OK",Q6=0),"READY","NOT READY") -> NOT READY
A7: guntur | B7: Guntur | C7: https://remaxforge.com/guntur/ | D7: REBUILD | E7: P2 | F7: Flange Supplier in Guntur | Flanges Manufacturer | G7: =LEN(F7) -> 48 | H7: =IF(G7=0,"MISSING",IF(G7>60,"TOO LONG",IF(G7<30,"TOO SHORT","OK"))) -> OK | I7: Steel flanges for Guntur cold storages, ammonia refrigeration, mill boilers and capital-region projects. A105, LF2 and SS grades. Quotes by email. | J7: =LEN(I7) -> 146 | K7: =IF(J7=0,"MISSING",IF(J7>160,"TOO LONG",IF(J7<120,"SHORT","OK"))) -> OK | L7: Flange Supplier in Guntur | M7: Flanges manufacturer in Mumbai supplying cold chain, agro-processing and capital-region projects in Guntur district. | N7: 1050 | O7: =SUMIFS('8. City Content (Paste)'!$H$5:$H$400,'8. City Content (Paste)'!$A$5:$A$400,$A7)+SUMIFS('8b. Page Tables (Paste)'!$H$5:$H$300,'8b. Page Tables (Paste)'!$A$5:$A$300,$A7)+SUMIFS('9. FAQs (Paste)'!$F$5:$F$200,'9. FAQs (Paste)'!$A$5:$A$200,$A7) -> 1217 | P7: =IF(O7>=N7,"OK","BELOW FLOOR") -> OK | Q7: =COUNTIFS('8. City Content (Paste)'!$A$5:$A$400,$A7,'8. City Content (Paste)'!$I$5:$I$400,"<>Ready")+COUNTIFS('8b. Page Tables (Paste)'!$A$5:$A$300,$A7,'8b. Page Tables (Paste)'!$I$5:$I$300,"<>Ready")+COUNTIFS('9. FAQs (Paste)'!$A$5:$A$200,$A7,'9. FAQs (Paste)'!$G$5:$G$200,"<>Ready") -> 17 | R7: >= 65% unique 5-word shingles; max similarity to any other city page <= 0.25 | S7: Flange supply across Andhra Pradesh → /market-area/andhra-pradesh/ Vijayawada & Amaravati → /vijayawada/ Low-temperature flanges → /products/flanges/high-temperature-cryogenic-flange/ + 7 product-type links (tab 8b) | T7: AP hub; /vijayawada/ related links | U7: P01, P08, P11 | V7: V1 (reuse) | W7: WebPage, BreadcrumbList, Service, FAQPage (+ sitewide Organization, WebSite, Person) | X7: Home › Areas We Supply › Andhra Pradesh › Guntur | Y7: index, follow | Z7: =IF(AND(H7="OK",K7="OK",P7="OK",Q7=0),"READY","NOT READY") -> NOT READY
A8: nellore | B8: Nellore | C8: https://remaxforge.com/nellore/ | D8: REBUILD | E8: P1 | F8: Flange Supplier in Nellore | Flanges Manufacturer | G8: =LEN(F8) -> 49 | H8: =IF(G8=0,"MISSING",IF(G8>60,"TOO LONG",IF(G8<30,"TOO SHORT","OK"))) -> OK | I8: Flanges for Nellore power plants, Krishnapatnam port, seafood processors and the Ramayapatnam refinery supply chain. NACE, LF2 and alloy grades. | J8: =LEN(I8) -> 144 | K8: =IF(J8=0,"MISSING",IF(J8>160,"TOO LONG",IF(J8<120,"SHORT","OK"))) -> OK | L8: Flange Supplier in Nellore, Krishnapatnam & Ramayapatnam | M8: Flanges manufacturer in Mumbai supplying Nellore's power, port, seafood and refinery-project buyers. | N8: 1050 | O8: =SUMIFS('8. City Content (Paste)'!$H$5:$H$400,'8. City Content (Paste)'!$A$5:$A$400,$A8)+SUMIFS('8b. Page Tables (Paste)'!$H$5:$H$300,'8b. Page Tables (Paste)'!$A$5:$A$300,$A8)+SUMIFS('9. FAQs (Paste)'!$F$5:$F$200,'9. FAQs (Paste)'!$A$5:$A$200,$A8) -> 1230 | P8: =IF(O8>=N8,"OK","BELOW FLOOR") -> OK | Q8: =COUNTIFS('8. City Content (Paste)'!$A$5:$A$400,$A8,'8. City Content (Paste)'!$I$5:$I$400,"<>Ready")+COUNTIFS('8b. Page Tables (Paste)'!$A$5:$A$300,$A8,'8b. Page Tables (Paste)'!$I$5:$I$300,"<>Ready")+COUNTIFS('9. FAQs (Paste)'!$A$5:$A$200,$A8,'9. FAQs (Paste)'!$G$5:$G$200,"<>Ready") -> 17 | R8: >= 65% unique 5-word shingles; max similarity to any other city page <= 0.25 | S8: Flange supply across Andhra Pradesh → /market-area/andhra-pradesh/ Visakhapatnam → /visakhapatnam/ Sour-service NACE flanges → /products/flanges/sour-service-nace-flange/ Low-temperature flanges → /products/flanges/high-temperature-cryogenic-flange/ Flanges for oil & gas → /industries/oil-and-gas/ + 7 product-type links (tab 8b) | T8: AP hub; /visakhapatnam/ related links; /industries/oil-and-gas/ (optional) | U8: P07, P09, P10 | V8: V3 | W8: WebPage, BreadcrumbList, Service, FAQPage (+ sitewide Organization, WebSite, Person) | X8: Home › Areas We Supply › Andhra Pradesh › Nellore | Y8: index, follow | Z8: =IF(AND(H8="OK",K8="OK",P8="OK",Q8=0),"READY","NOT READY") -> NOT READY
A9: kurnool | B9: Kurnool | C9: https://remaxforge.com/kurnool/ | D9: REBUILD | E9: P2 | F9: Flange Supplier in Kurnool | Flanges Manufacturer | G9: =LEN(F9) -> 49 | H9: =IF(G9=0,"MISSING",IF(G9>60,"TOO LONG",IF(G9<30,"TOO SHORT","OK"))) -> OK | I9: Flanges for Kurnool pumped storage, lift irrigation, solar parks and cement plants. Large-bore, AWWA, EN and IS drilling. Written quotes by email. | J9: =LEN(I9) -> 146 | K9: =IF(J9=0,"MISSING",IF(J9>160,"TOO LONG",IF(J9<120,"SHORT","OK"))) -> OK | L9: Flange Supplier in Kurnool | M9: Flanges manufacturer in Mumbai supplying pumped-storage, irrigation, renewable and industrial projects around Kurnool. | N9: 1000 | O9: =SUMIFS('8. City Content (Paste)'!$H$5:$H$400,'8. City Content (Paste)'!$A$5:$A$400,$A9)+SUMIFS('8b. Page Tables (Paste)'!$H$5:$H$300,'8b. Page Tables (Paste)'!$A$5:$A$300,$A9)+SUMIFS('9. FAQs (Paste)'!$F$5:$F$200,'9. FAQs (Paste)'!$A$5:$A$200,$A9) -> 1196 | P9: =IF(O9>=N9,"OK","BELOW FLOOR") -> OK | Q9: =COUNTIFS('8. City Content (Paste)'!$A$5:$A$400,$A9,'8. City Content (Paste)'!$I$5:$I$400,"<>Ready")+COUNTIFS('8b. Page Tables (Paste)'!$A$5:$A$300,$A9,'8b. Page Tables (Paste)'!$I$5:$I$300,"<>Ready")+COUNTIFS('9. FAQs (Paste)'!$A$5:$A$200,$A9,'9. FAQs (Paste)'!$G$5:$G$200,"<>Ready") -> 17 | R9: >= 65% unique 5-word shingles; max similarity to any other city page <= 0.25 | S9: Flange supply across Andhra Pradesh → /market-area/andhra-pradesh/ Pipe flanges guide → /blogs/pipe-flanges-guide/ Vijayawada (Class 150 vs PN16 drilling) → /vijayawada/ + 7 product-type links (tab 8b) | T9: AP hub; /vijayawada/ related links | U9: P12, P06, P13 | V9: V4 | W9: WebPage, BreadcrumbList, Service, FAQPage (+ sitewide Organization, WebSite, Person) | X9: Home › Areas We Supply › Andhra Pradesh › Kurnool | Y9: index, follow | Z9: =IF(AND(H9="OK",K9="OK",P9="OK",Q9=0),"READY","NOT READY") -> NOT READY
A10: itanagar | B10: Itanagar & Naharlagun | C10: https://remaxforge.com/itanagar/ | D10: REBUILD + ABSORB NAHARLAGUN | E10: P3 | F10: Flange Supplier in Itanagar & Naharlagun | Manufacturer | G10: =LEN(F10) -> 55 | H10: =IF(G10=0,"MISSING",IF(G10>60,"TOO LONG",IF(G10<30,"TOO SHORT","OK"))) -> OK | I10: Flanges for water-supply, hospital, building and hydro projects in Itanagar and Naharlagun. Shipped from Mumbai via Guwahati. Written quotes by email. | J10: =LEN(I10) -> 150 | K10: =IF(J10=0,"MISSING",IF(J10>160,"TOO LONG",IF(J10<120,"SHORT","OK"))) -> OK | L10: Flange Supplier in Itanagar & Naharlagun (Capital Region) | M10: Flanges manufacturer in Mumbai supplying water-supply, building and hydropower work in the Itanagar capital region. | N10: 900 | O10: =SUMIFS('8. City Content (Paste)'!$H$5:$H$400,'8. City Content (Paste)'!$A$5:$A$400,$A10)+SUMIFS('8b. Page Tables (Paste)'!$H$5:$H$300,'8b. Page Tables (Paste)'!$A$5:$A$300,$A10)+SUMIFS('9. FAQs (Paste)'!$F$5:$F$200,'9. FAQs (Paste)'!$A$5:$A$200,$A10) -> 1053 | P10: =IF(O10>=N10,"OK","BELOW FLOOR") -> OK | Q10: =COUNTIFS('8. City Content (Paste)'!$A$5:$A$400,$A10,'8. City Content (Paste)'!$I$5:$I$400,"<>Ready")+COUNTIFS('8b. Page Tables (Paste)'!$A$5:$A$300,$A10,'8b. Page Tables (Paste)'!$I$5:$I$300,"<>Ready")+COUNTIFS('9. FAQs (Paste)'!$A$5:$A$200,$A10,'9. FAQs (Paste)'!$G$5:$G$200,"<>Ready") -> 18 | R10: >= 65% unique 5-word shingles; max similarity to any other city page <= 0.25 | S10: Flange supply across Arunachal Pradesh → /market-area/arunachal-pradesh/ Pipe flanges guide → /blogs/pipe-flanges-guide/ + 7 product-type links (tab 8b) | T10: AR hub (Itanagar section + list) | U10: P13, P14, P11 | V10: V5 | W10: WebPage, BreadcrumbList, Service, FAQPage (+ sitewide Organization, WebSite, Person) | X10: Home › Areas We Supply › Arunachal Pradesh › Itanagar & Naharlagun | Y10: index, follow | Z10: =IF(AND(H10="OK",K10="OK",P10="OK",Q10=0),"READY","NOT READY") -> NOT READY
A11: ap_hub | B11: Andhra Pradesh hub | C11: https://remaxforge.com/market-area/andhra-pradesh/ | D11: NEW | E11: P1 | F11: Flange Supplier in Andhra Pradesh | Flanges Manufacturer | G11: =LEN(F11) -> 56 | H11: =IF(G11=0,"MISSING",IF(G11>60,"TOO LONG",IF(G11<30,"TOO SHORT","OK"))) -> OK | I11: Forged flanges across Andhra Pradesh: Vizag steel and refinery belt, Nellore ports, Amaravati works, Kurnool pumped storage. Written quotes by email. | J11: =LEN(I11) -> 149 | K11: =IF(J11=0,"MISSING",IF(J11>160,"TOO LONG",IF(J11<120,"SHORT","OK"))) -> OK | L11: Flanges Manufacturer & Supplier for Andhra Pradesh | M11: One Mumbai manufacturer supplying Andhra Pradesh's steel, refinery, power, port, water and capital-region projects. | N11: 550 | O11: =SUMIFS('8. City Content (Paste)'!$H$5:$H$400,'8. City Content (Paste)'!$A$5:$A$400,$A11)+SUMIFS('8b. Page Tables (Paste)'!$H$5:$H$300,'8b. Page Tables (Paste)'!$A$5:$A$300,$A11)+SUMIFS('9. FAQs (Paste)'!$F$5:$F$200,'9. FAQs (Paste)'!$A$5:$A$200,$A11) -> 881 | P11: =IF(O11>=N11,"OK","BELOW FLOOR") -> OK | Q11: =COUNTIFS('8. City Content (Paste)'!$A$5:$A$400,$A11,'8. City Content (Paste)'!$I$5:$I$400,"<>Ready")+COUNTIFS('8b. Page Tables (Paste)'!$A$5:$A$300,$A11,'8b. Page Tables (Paste)'!$I$5:$I$300,"<>Ready")+COUNTIFS('9. FAQs (Paste)'!$A$5:$A$200,$A11,'9. FAQs (Paste)'!$G$5:$G$200,"<>Ready") -> 7 | R11: Hub copy unique; city summaries must not repeat city-page sentences | S11: Visakhapatnam → /visakhapatnam/ Vijayawada → /vijayawada/ Guntur → /guntur/ Nellore → /nellore/ Kurnool → /kurnool/ All flange types → /products/flanges/ | T11: /market-area/ index; breadcrumb of all 5 AP city pages; body link from each AP city page | U11: P03, P11 | V11: V1 | W11: CollectionPage, BreadcrumbList, Service, FAQPage (+ sitewide Organization, WebSite, Person) | X11: Home › Areas We Supply › Andhra Pradesh | Y11: index, follow | Z11: =IF(AND(H11="OK",K11="OK",P11="OK",Q11=0),"READY","NOT READY") -> NOT READY
A12: ar_hub | B12: Arunachal Pradesh hub | C12: https://remaxforge.com/market-area/arunachal-pradesh/ | D12: NEW (absorbs Pasighat, Tawang, Ziro under Option A) | E12: P3 | F12: Flange Supplier in Arunachal Pradesh | Itanagar to Tawang | G12: =LEN(F12) -> 57 | H12: =IF(G12=0,"MISSING",IF(G12>60,"TOO LONG",IF(G12<30,"TOO SHORT","OK"))) -> OK | I12: Flanges for hydro, water-supply and building projects in Arunachal Pradesh: Itanagar, Tawang, Ziro, Pasighat. Shipped via Guwahati. Quotes by email. | J12: =LEN(I12) -> 148 | K12: =IF(J12=0,"MISSING",IF(J12>160,"TOO LONG",IF(J12<120,"SHORT","OK"))) -> OK | L12: Flange Supplier for Arunachal Pradesh | M12: Flanges from our Mumbai unit for hydropower, water-supply, building and road projects across the state. | N12: 450 | O12: =SUMIFS('8. City Content (Paste)'!$H$5:$H$400,'8. City Content (Paste)'!$A$5:$A$400,$A12)+SUMIFS('8b. Page Tables (Paste)'!$H$5:$H$300,'8b. Page Tables (Paste)'!$A$5:$A$300,$A12)+SUMIFS('9. FAQs (Paste)'!$F$5:$F$200,'9. FAQs (Paste)'!$A$5:$A$200,$A12) -> 771 | P12: =IF(O12>=N12,"OK","BELOW FLOOR") -> OK | Q12: =COUNTIFS('8. City Content (Paste)'!$A$5:$A$400,$A12,'8. City Content (Paste)'!$I$5:$I$400,"<>Ready")+COUNTIFS('8b. Page Tables (Paste)'!$A$5:$A$300,$A12,'8b. Page Tables (Paste)'!$I$5:$I$300,"<>Ready")+COUNTIFS('9. FAQs (Paste)'!$A$5:$A$200,$A12,'9. FAQs (Paste)'!$G$5:$G$200,"<>Ready") -> 6 | R12: Hub copy unique; city summaries must not repeat city-page sentences | S12: Itanagar & Naharlagun → /itanagar/ All flange types → /products/flanges/ | T12: /market-area/ index; breadcrumb + body link from /itanagar/ | U12: P14, P13 | V12: V5 | W12: CollectionPage, BreadcrumbList, Service, FAQPage (+ sitewide Organization, WebSite, Person) | X12: Home › Areas We Supply › Arunachal Pradesh | Y12: index, follow | Z12: =IF(AND(H12="OK",K12="OK",P12="OK",Q12=0),"READY","NOT READY") -> NOT READY
A13: market_area | B13: Market Area index | C13: https://remaxforge.com/market-area/ | D13: NEW (if it does not exist) | E13: P1 | F13: Flange Supply Areas Across India | Remax Forge & Fittings | G13: =LEN(F13) -> 57 | H13: =IF(G13=0,"MISSING",IF(G13>60,"TOO LONG",IF(G13<30,"TOO SHORT","OK"))) -> OK | I13: See the states and cities we deliver forged flanges to from Mumbai, with local industries, delivery times and documents. Written quotes by email. | J13: =LEN(I13) -> 145 | K13: =IF(J13=0,"MISSING",IF(J13>160,"TOO LONG",IF(J13<120,"SHORT","OK"))) -> OK | L13: Where We Supply Flanges in India | M13: Forged flanges made in Mumbai and delivered by road to plants, EPC contractors and fabricators across India. | N13: 50 | O13: =SUMIFS('8. City Content (Paste)'!$H$5:$H$400,'8. City Content (Paste)'!$A$5:$A$400,$A13)+SUMIFS('8b. Page Tables (Paste)'!$H$5:$H$300,'8b. Page Tables (Paste)'!$A$5:$A$300,$A13)+SUMIFS('9. FAQs (Paste)'!$F$5:$F$200,'9. FAQs (Paste)'!$A$5:$A$200,$A13) -> 180 | P13: =IF(O13>=N13,"OK","BELOW FLOOR") -> OK | Q13: =COUNTIFS('8. City Content (Paste)'!$A$5:$A$400,$A13,'8. City Content (Paste)'!$I$5:$I$400,"<>Ready")+COUNTIFS('8b. Page Tables (Paste)'!$A$5:$A$300,$A13,'8b. Page Tables (Paste)'!$I$5:$I$300,"<>Ready")+COUNTIFS('9. FAQs (Paste)'!$A$5:$A$200,$A13,'9. FAQs (Paste)'!$G$5:$G$200,"<>Ready") -> 1 | R13: Hub copy unique; city summaries must not repeat city-page sentences | S13: Andhra Pradesh → /market-area/andhra-pradesh/ Arunachal Pradesh → /market-area/arunachal-pradesh/ | T13: Sitewide footer link 'Areas we supply'; breadcrumb of every hub and city page | U13: - | V13: - | W13: CollectionPage, BreadcrumbList (+ sitewide Organization, WebSite, Person) | X13: Home › Areas We Supply | Y13: index, follow | Z13: =IF(AND(H13="OK",K13="OK",P13="OK",Q13=0),"READY","NOT READY") -> NOT READY
A15: Option B only - mini-pages for the 4 merged towns (ignored while tab 1 says Option A)
A16: Town | B16: Current URL | C16: Used? | D16: Keep only if (all must be true) | E16: Angle | F16: 4 FAQs to write | G16: Title tag | H16: Title chars | I16: Meta description | J16: Meta chars | K16: H1 | L16: Word floor
A17: Naharlagun | B17: /naharlagun/ | C17: =IF(LEFT('1. Decision Summary'!$C$5,8)="Option A","No - 301 (Option A)","YES - build") -> No - 301 (Option A) | D17: Remax has supplied Naharlagun sites (e.g. hospital or rail-linked projects) or receives Naharlagun-specific RFQs. | E17: Hospital and public-building fire-fighting and HVAC plant rooms; Naharlagun rail head for consolidated freight. | F17: Can you deliver to hospital sites in Naharlagun? Is rail freight to Naharlagun an option? Do you supply fire-fighting flanges? Do you have a stockist in Naharlagun? | G17: Flange Supplier in Naharlagun | Flanges Manufacturer | H17: =LEN(G17) -> 52 | I17: Flanges for Naharlagun hospital, public-building and fire-fighting projects, shipped from Mumbai with heat-traceable certificates. Written quotes. | J17: =LEN(I17) -> 146 | K17: Flange Supplier in Naharlagun | L17: 500
A18: Pasighat | B18: /pasighat/ | C18: =IF(LEFT('1. Decision Summary'!$C$5,8)="Option A","No - 301 (Option A)","YES - build") -> No - 301 (Option A) | D18: Remax has an active East Siang project or repeat Pasighat enquiries. | E18: East Siang water-supply schemes and institutions; delivery via Guwahati and Dibrugarh side routes [CLIENT: route]. | F18: How long does delivery to Pasighat take? Do you supply PN10/PN16 water-scheme flanges? Is there a minimum order? Do you have a stockist in Pasighat? | G18: Flange Supplier in Pasighat | Flanges Manufacturer | H18: =LEN(G18) -> 50 | I18: Flanges for East Siang water-supply schemes and institutions around Pasighat, shipped from Mumbai with certificates. Written quotes by email. | J18: =LEN(I18) -> 141 | K18: Flange Supplier in Pasighat | L18: 500
A19: Tawang | B19: /tawang/ | C19: =IF(LEFT('1. Decision Summary'!$C$5,8)="Option A","No - 301 (Option A)","YES - build") -> No - 301 (Option A) | D19: Remax supplies defence, BRO or hydro contractors in Tawang district. | E19: High-altitude cold service (A105 vs LF2 below -29 °C), winter logistics over the Sela route, defence and border infrastructure contractors. | F19: Do you deliver to Tawang in winter? When is A350 LF2 needed? Can you supply BRO or defence contractors? How is freight priced? | G19: Flange Supplier in Tawang | Flanges Manufacturer | H19: =LEN(G19) -> 48 | I19: Flanges for Tawang defence, road and hydro contractors, including LF2 for sub-zero service. Packed for mountain transit from Mumbai. Written quotes. | J19: =LEN(I19) -> 148 | K19: Flange Supplier in Tawang | L19: 500
A20: Ziro | B20: /ziro/ | C20: =IF(LEFT('1. Decision Summary'!$C$5,8)="Option A","No - 301 (Option A)","YES - build") -> No - 301 (Option A) | D20: Remax supplies Ranganadi / Lower Subansiri hydro maintenance or local water schemes. | E20: Hydro auxiliary spares near the Ranganadi dam at Yazali; Lower Subansiri water-supply schemes. | F20: Do you supply hydro auxiliary spares? How long does delivery to Ziro take? Do you supply water-scheme flanges? Do you have a stockist in Ziro? | G20: Flange Supplier in Ziro | Flanges Manufacturer | H20: =LEN(G20) -> 46 | I20: Flanges for hydro auxiliaries and water-supply schemes around Ziro and Yazali, shipped from Mumbai with heat-traceable certificates. Quotes by email. | J20: =LEN(I20) -> 149 | K20: Flange Supplier in Ziro | L20: 500

Sheet 7. Page Template (Dev)
A1: 7. Page template for the developer - 14 sections, same order on every city page
A2: Build once as a component, fill from tabs 8, 8b and 9. Hubs use sections 1-3, their own sections, then 7, 11-14.
A4: # | B4: Section | C4: What goes in it | D4: Content source | E4: Words | F4: Uniqueness | G4: HTML / component notes | H4: Lead-capture role
A5: 1 | B5: Breadcrumb | C5: Home › Areas We Supply › {State} › {City} | D5: Tab 8 'Breadcrumb' row; BreadcrumbList in tab 11 | E5: 5 | F5: Template | G5: <nav aria-label="Breadcrumb"><ol> … </ol></nav>. Every link in slash form; last item is plain text (the current page). If /market-area/ is not built, drop that level here AND in the JSON-LD. | H5: -
A6: 2 | B6: Hero | C6: H1, subline, hero paragraph + Form A (2-step quick quote) | D6: Tab 8 'H1', 'Subline', 'Hero' rows; tab 10 Form A | E6: 70-100 | F6: Unique | G6: Exactly one <h1>. Desktop: form in the right column, above the fold. Mobile: form directly under the hero paragraph. No phone number, no tel: link, no WhatsApp or 'Call us' button. | H6: Primary conversion point
A7: 3 | B7: Trust strip | C7: GSTIN, GST-registered since 2020, proprietorship led by Vikas Purohit (CEO), Mumbai unit, real certificates only, 'written quotes by email' | D7: Tab 8 SHARED row | E7: 40 | F7: Shared | G7: One band under the hero. GSTIN as text + link 'verify on the GST portal' → https://services.gst.gov.in/services/searchtp (taxpayer search). | H7: Trust
A8: 4 | B8: Local demand | C8: H2 + one-line lead + table: industry | local sites | where flanges are used | what is usually specified | D8: Tab 8 'Local demand' row + tab 8b demand table | E8: 200-380 | F8: Unique | G8: Real <table> with <th scope="col">; horizontal-scroll wrapper on mobile. Name companies in text only - no third-party logos. | H8: Relevance
A9: 5 | B9: Materials guidance | C9: H2 + 2-4 short paragraphs; a different teaching angle per city | D9: Tab 8 'Materials guidance' row | E9: 120-250 | F9: Unique | G9: Line breaks in the cell = paragraph breaks. Lines starting '1.' to '5.' render as an ordered list (Nellore). | H9: Expertise → trust
A10: 6 | B10: Product range | C10: H2 + range intro + 7-row table: flange type (link) | typical use in this city | D10: Tab 8 'Product range' row + tab 8b product table | E10: 90-140 | F10: Semi-unique | G10: Each type links to its product page in slash form. This also feeds the 53-page product estate with correctly formed links (daily log A-64). Confirm the 5 slugs marked [CONFIRM] exist before linking; otherwise link /products/flanges/. | H10: Routes buyers to product pages
A11: 7 | B11: Manufacturing & QA | C11: H2 + 120-word shared summary + 1 photo + the page's video (V1-V5) with transcript | D11: Tab 8 SHARED row; tab 13 | E11: 120 (+ transcript) | F11: Shared | G11: Video behind a click-to-load facade (no player JS until clicked). Transcript in the HTML (details/summary is fine). Link to /manufacturing/ only if that page exists [CONFIRM]. | H11: Trust
A12: 8 | B12: Delivery & documents | C12: H2 + text: transit time, invoice/IGST, e-way bill, certificates, packing | D12: Tab 8 'Delivery' row | E12: 90-130 | F12: Unique | G12: Transit days come from tab 15 - never publish a number the client has not confirmed. | H12: Removes a purchase objection
A13: 9 | B13: Price guidance | C13: H2 + text (+ dated Rs/kg band table once the client supplies it) | D13: Tab 8 'Price' row; tab 15 I-26 | E13: 50-100 | F13: Unique | G13: Show 'Prices as of {month year}' beside any band. No band from the client = keep the text only. Never invent prices; no Product/Offer schema. | H13: Captures price-check searches
A14: 10 | B14: Areas served | C14: H2 + text naming localities and industrial areas | D14: Tab 8 'Areas' row | E14: 50-80 | F14: Unique | G14: Plain text - no links to locality pages (none should exist; one URL per city). | H14: Local relevance
A15: 11 | B15: Request a quote | C15: H2 + shared RFQ checklist + Form B (full RFQ) with id="rfq" | D15: Tab 8 SHARED row; tab 10 Form B | E15: 60 | F15: Shared | G15: id="rfq" is the Service schema's serviceUrl target (tab 11) and the sticky mobile CTA target. | H15: Main conversion point
A16: 12 | B16: FAQs | C16: H2 + 6-7 questions and answers | D16: Tab 8 'FAQs' heading row + tab 9 | E16: 180-350 | F16: Unique | G16: Answers must be in the HTML on page load (accordion OK; answers fetched on click are not). FAQPage JSON-LD must match the visible text word for word - tab 11 builds it from tab 9 automatically. | H16: Objection handling
... A18: 14 | B18: Final CTA band | C18: Shared CTA text + button 'Get a written quote' → #rfq | D18: Tab 8 SHARED row | E18: 40 | F18: Shared | G18: No phone, no WhatsApp, no third-party chat widget. | H18: Last conversion point
A20: Sitewide elements on city and hub pages
A21: • | B21: Sticky mobile CTA | C21: Bottom bar 'Get a written quote' → #rfq. Shows after 30% scroll; hides while a form is on screen. Mobile only. No phone or WhatsApp icon.
A22: • | B22: Exit-intent offer | C22: Desktop only, once per session, not before 20 s on page: offers the flange weight & dimension chart (tab 10 Form C). Never on mobile (Google treats intrusive mobile interstitials as a negative).
A23: • | B23: Header & footer | C23: No phone number, no tel:, no WhatsApp anywhere (daily log T1-e). Footer: add 'Areas we supply' → /market-area/.
A24: • | B24: <main> wrapper | C24: Wrap page content in <main> so the QA script (tab 16) measures page copy, not header/footer boilerplate.
A25: • | B25: Uniqueness rule | C25: Unique sections stay unique per city; shared modules stay under ~20% of words. QA target: >= 65% unique 5-word shingles, pairwise similarity <= 0.25 (fail > 0.35).
A26: • | B26: Images & video | C26: WebP, explicit width/height, lazy-load below the fold, hero image fetchpriority=high. Photo IDs per page in tab 6; specs in tab 13.

Sheet 8. City Content (Paste)
A1: 8. City content (paste-ready) - copy each cell into the matching section of the template (tab 7)
A2: Light-yellow cells still contain [CLIENT ...], [CONFIRM] or [DEV] markers - replace them with real data from tab 15 or delete the sentence. SHARED rows at the top feed every page (edit once; the page rows below update).
A4: Page key | B4: URL | C4: Sec # | D4: Section | E4: Element | F4: Heading (H2) | G4: Copy (paste-ready) | H4: Words | I4: Status | J4: Uniqueness | K4: Dev note
A5: SHARED | B5: all city + hub pages | C5: 3 | D5: Trust strip | E5: Band under the hero (no heading) | G5: GSTIN 27FFLPP0007K1ZA (verify on the GST portal) · GST-registered since 2020 · Proprietorship led by Vikas Purohit, CEO · Manufacturing unit in Mumbai, Maharashtra [CLIENT: locality] · [CLIENT: real certifications only, e.g. ISO 9001:2015 — delete if none] · Written quotes by email, no calls needed | H5: =IF(LEN(TRIM(SUBSTITUTE(F5,CHAR(10)," ")))=0,0,LEN(TRIM(SUBSTITUTE(F5,CHAR(10)," ")))-LEN(SUBSTITUTE(TRIM(SUBSTITUTE(F5,CHAR(10)," "))," ",""))+1)+IF(LEN(TRIM(SUBSTITUTE(G5,CHAR(10)," ")))=0,0,LEN(TRIM(SUBSTITUTE(G5,CHAR(10)," ")))-LEN(SUBSTITUTE(TRIM(SUBSTITUTE(G5,CHAR(10)," "))," ",""))+1) -> 46 | I5: =IF(ISNUMBER(FIND("[CLIENT",F5&G5)),"CLIENT INPUT",IF(ISNUMBER(FIND("[CONFIRM",F5&G5)),"CONFIRM",IF(ISNUMBER(FIND("[DEV",F5&G5)),"DEV NOTE","Ready"))) -> CLIENT INPUT | J5: Shared | K5: Edit here only - page rows reference this row.
A6: SHARED | B6: all city + hub pages | C6: 7 | D6: Manufacturing & QA | E6: H2 + P + photo + video | F6: How every flange is made and checked | G6: Every flange starts as a certified billet or bar whose heat number follows it through cutting, forging, heat treatment where the material specification requires it, CNC machining and drilling, and final marking of grade, class, size and heat number. Before dispatch we check dimensions against the governing standard and [CLIENT: list only tests actually done in-house, e.g. PMI, hardness, ultrasonic], and issue material test certificates that tie each flange back to its heat. Buyer-nominated third-party inspection can witness any stage [CONFIRM]. | H6: =IF(LEN(TRIM(SUBSTITUTE(F6,CHAR(10)," ")))=0,0,LEN(TRIM(SUBSTITUTE(F6,CHAR(10)," ")))-LEN(SUBSTITUTE(TRIM(SUBSTITUTE(F6,CHAR(10)," "))," ",""))+1)+IF(LEN(TRIM(SUBSTITUTE(G6,CHAR(10)," ")))=0,0,LEN(TRIM(SUBSTITUTE(G6,CHAR(10)," ")))-LEN(SUBSTITUTE(TRIM(SUBSTITUTE(G6,CHAR(10)," "))," ",""))+1) -> 88 | I6: =IF(ISNUMBER(FIND("[CLIENT",F6&G6)),"CLIENT INPUT",IF(ISNUMBER(FIND("[CONFIRM",F6&G6)),"CONFIRM",IF(ISNUMBER(FIND("[DEV",F6&G6)),"DEV NOTE","Ready"))) -> CLIENT INPUT | J6: Shared | K6: Edit here only - page rows reference this row.
A7: SHARED | B7: all city + hub pages | C7: 11 | D7: Request a quote | E7: H2 + P + Form B (id="rfq") | F7: Request a written quote | G7: A quote-ready enquiry lists: flange type · nominal size (NPS or DN) · pressure class or PN · facing (RF, FF or RTJ) · material specification and grade · bore or schedule for weld neck flanges · quantity · delivery location · testing and certificate needs (NACE, impact test, EN 10204 3.1/3.2, third-party inspection). Upload a BOQ or drawing and we will read it for you. | H7: =IF(LEN(TRIM(SUBSTITUTE(F7,CHAR(10)," ")))=0,0,LEN(TRIM(SUBSTITUTE(F7,CHAR(10)," ")))-LEN(SUBSTITUTE(TRIM(SUBSTITUTE(F7,CHAR(10)," "))," ",""))+1)+IF(LEN(TRIM(SUBSTITUTE(G7,CHAR(10)," ")))=0,0,LEN(TRIM(SUBSTITUTE(G7,CHAR(10)," ")))-LEN(SUBSTITUTE(TRIM(SUBSTITUTE(G7,CHAR(10)," "))," ",""))+1) -> 70 | I7: =IF(ISNUMBER(FIND("[CLIENT",F7&G7)),"CLIENT INPUT",IF(ISNUMBER(FIND("[CONFIRM",F7&G7)),"CONFIRM",IF(ISNUMBER(FIND("[DEV",F7&G7)),"DEV NOTE","Ready"))) -> Ready | J7: Shared | K7: Edit here only - page rows reference this row.
A8: SHARED | B8: all city + hub pages | C8: 14 | D8: Final CTA | E8: CTA band + button 'Get a written quote' → #rfq | G8: Send your requirement - we reply in writing. Fill the form or upload your BOQ; you get a line-by-line quote by email [CLIENT: reply time, e.g. within one working day]. No phone calls needed - everything is in writing. | H8: =IF(LEN(TRIM(SUBSTITUTE(F8,CHAR(10)," ")))=0,0,LEN(TRIM(SUBSTITUTE(F8,CHAR(10)," ")))-LEN(SUBSTITUTE(TRIM(SUBSTITUTE(F8,CHAR(10)," "))," ",""))+1)+IF(LEN(TRIM(SUBSTITUTE(G8,CHAR(10)," ")))=0,0,LEN(TRIM(SUBSTITUTE(G8,CHAR(10)," ")))-LEN(SUBSTITUTE(TRIM(SUBSTITUTE(G8,CHAR(10)," "))," ",""))+1) -> 39 | I8: =IF(ISNUMBER(FIND("[CLIENT",F8&G8)),"CLIENT INPUT",IF(ISNUMBER(FIND("[CONFIRM",F8&G8)),"CONFIRM",IF(ISNUMBER(FIND("[DEV",F8&G8)),"DEV NOTE","Ready"))) -> CLIENT INPUT | J8: Shared | K8: Edit here only - page rows reference this row.
A9: vizag | B9: /visakhapatnam/ | C9: 1 | D9: Breadcrumb | E9: Breadcrumb | G9: Home › Areas We Supply › Andhra Pradesh › Visakhapatnam | H9: =IF(LEN(TRIM(SUBSTITUTE(F9,CHAR(10)," ")))=0,0,LEN(TRIM(SUBSTITUTE(F9,CHAR(10)," ")))-LEN(SUBSTITUTE(TRIM(SUBSTITUTE(F9,CHAR(10)," "))," ",""))+1)+IF(LEN(TRIM(SUBSTITUTE(G9,CHAR(10)," ")))=0,0,LEN(TRIM(SUBSTITUTE(G9,CHAR(10)," ")))-LEN(SUBSTITUTE(TRIM(SUBSTITUTE(G9,CHAR(10)," "))," ",""))+1) -> 10 | I9: =IF(ISNUMBER(FIND("[CLIENT",F9&G9)),"CLIENT INPUT",IF(ISNUMBER(FIND("[CONFIRM",F9&G9)),"CONFIRM",IF(ISNUMBER(FIND("[DEV",F9&G9)),"DEV NOTE","Ready"))) -> Ready | J9: Template | K9: Slash-form links; see tab 12.
A10: vizag | B10: /visakhapatnam/ | C10: 2 | D10: Hero | E10: H1 | G10: Flange Supplier in Visakhapatnam (Vizag) | H10: =IF(LEN(TRIM(SUBSTITUTE(F10,CHAR(10)," ")))=0,0,LEN(TRIM(SUBSTITUTE(F10,CHAR(10)," ")))-LEN(SUBSTITUTE(TRIM(SUBSTITUTE(F10,CHAR(10)," "))," ",""))+1)+IF(LEN(TRIM(SUBSTITUTE(G10,CHAR(10)," ")))=0,0,LEN(TRIM(SUBSTITUTE(G10,CHAR(10)," ")))-LEN(SUBSTITUTE(TRIM(SUBSTITUTE(G10,CHAR(10)," "))," ",""))+1) -> 5 | I10: =IF(ISNUMBER(FIND("[CLIENT",F10&G10)),"CLIENT INPUT",IF(ISNUMBER(FIND("[CONFIRM",F10&G10)),"CONFIRM",IF(ISNUMBER(FIND("[DEV",F10&G10)),"DEV NOTE","Ready"))) -> Ready | J10: Unique | K10: The only <h1> on the page.
A11: vizag | B11: /visakhapatnam/ | C11: 2 | D11: Hero | E11: Subline (P under H1) | G11: Flanges manufacturer in Mumbai supplying Visakhapatnam and Anakapalli steel, refinery, port, power and pharma sites. | H11: =IF(LEN(TRIM(SUBSTITUTE(F11,CHAR(10)," ")))=0,0,LEN(TRIM(SUBSTITUTE(F11,CHAR(10)," ")))-LEN(SUBSTITUTE(TRIM(SUBSTITUTE(F11,CHAR(10)," "))," ",""))+1)+IF(LEN(TRIM(SUBSTITUTE(G11,CHAR(10)," ")))=0,0,LEN(TRIM(SUBSTITUTE(G11,CHAR(10)," ")))-LEN(SUBSTITUTE(TRIM(SUBSTITUTE(G11,CHAR(10)," "))," ",""))+1) -> 15 | I11: =IF(ISNUMBER(FIND("[CLIENT",F11&G11)),"CLIENT INPUT",IF(ISNUMBER(FIND("[CONFIRM",F11&G11)),"CONFIRM",IF(ISNUMBER(FIND("[DEV",F11&G11)),"DEV NOTE","Ready"))) -> Ready | J11: Unique
A12: vizag | B12: /visakhapatnam/ | C12: 2 | D12: Hero | E12: P (hero) + Form A | G12: Remax Forge is a flanges manufacturer in Mumbai that supplies forged flanges to plants, EPC contractors and fabricators across Visakhapatnam and the neighbouring Anakapalli district - the steel and refinery belt, the ports and shipyard, and the pharma and SEZ clusters at Parawada, Duvvada and Atchutapuram. Send your sizes, pressure class and material through the form and we reply by email with a line-by-line price and dispatch date [CLIENT: reply time, e.g. within one working day]. | H12: =IF(LEN(TRIM(SUBSTITUTE(F12,CHAR(10)," ")))=0,0,LEN(TRIM(SUBSTITUTE(F12,CHAR(10)," ")))-LEN(SUBSTITUTE(TRIM(SUBSTITUTE(F12,CHAR(10)," "))," ",""))+1)+IF(LEN(TRIM(SUBSTITUTE(G12,CHAR(10)," ")))=0,0,LEN(TRIM(SUBSTITUTE(G12,CHAR(10)," ")))-LEN(SUBSTITUTE(TRIM(SUBSTITUTE(G12,CHAR(10)," "))," ",""))+1) -> 76 | I12: =IF(ISNUMBER(FIND("[CLIENT",F12&G12)),"CLIENT INPUT",IF(ISNUMBER(FIND("[CONFIRM",F12&G12)),"CONFIRM",IF(ISNUMBER(FIND("[DEV",F12&G12)),"DEV NOTE","Ready"))) -> CLIENT INPUT | J12: Unique | K12: Form A (tab 10) beside/below this paragraph.
A13: vizag | B13: /visakhapatnam/ | C13: 3 | D13: Trust strip | F13: =IF($F$5="","",$F$5) | G13: =$G$5 -> GSTIN 27FFLPP0007K1ZA (verify on the GST portal) · GST-registered since 2020 · Proprietorship led by Vikas Purohit, CEO · Manufacturing unit in Mumbai, Maharashtra [CLIENT: locality] · [CLIENT: real certifications only, e.g. ISO 9001:2015 — delete if none] · Written quotes by email, no calls needed | H13: =IF(LEN(TRIM(SUBSTITUTE(F13,CHAR(10)," ")))=0,0,LEN(TRIM(SUBSTITUTE(F13,CHAR(10)," ")))-LEN(SUBSTITUTE(TRIM(SUBSTITUTE(F13,CHAR(10)," "))," ",""))+1)+IF(LEN(TRIM(SUBSTITUTE(G13,CHAR(10)," ")))=0,0,LEN(TRIM(SUBSTITUTE(G13,CHAR(10)," ")))-LEN(SUBSTITUTE(TRIM(SUBSTITUTE(G13,CHAR(10)," "))," ",""))+1) -> 46 | I13: =IF(ISNUMBER(FIND("[CLIENT",F13&G13)),"CLIENT INPUT",IF(ISNUMBER(FIND("[CONFIRM",F13&G13)),"CONFIRM",IF(ISNUMBER(FIND("[DEV",F13&G13)),"DEV NOTE","Ready"))) -> CLIENT INPUT | J13: Shared
A14: vizag | B14: /visakhapatnam/ | C14: 4 | D14: Local demand | E14: H2 + P (table: tab 8b) | F14: Where flanges are used in Visakhapatnam - and what each site usually specifies | G14: Vizag buys flanges for very different services: oxygen lines in a steel plant, sour hydrocarbons in a refinery, seawater at the harbour. The table maps each local industry to what its piping engineers usually specify, so your enquiry starts in the right place. | H14: =IF(LEN(TRIM(SUBSTITUTE(F14,CHAR(10)," ")))=0,0,LEN(TRIM(SUBSTITUTE(F14,CHAR(10)," ")))-LEN(SUBSTITUTE(TRIM(SUBSTITUTE(F14,CHAR(10)," "))," ",""))+1)+IF(LEN(TRIM(SUBSTITUTE(G14,CHAR(10)," ")))=0,0,LEN(TRIM(SUBSTITUTE(G14,CHAR(10)," ")))-LEN(SUBSTITUTE(TRIM(SUBSTITUTE(G14,CHAR(10)," "))," ",""))+1) -> 56 | I14: =IF(ISNUMBER(FIND("[CLIENT",F14&G14)),"CLIENT INPUT",IF(ISNUMBER(FIND("[CONFIRM",F14&G14)),"CONFIRM",IF(ISNUMBER(FIND("[DEV",F14&G14)),"DEV NOTE","Ready"))) -> Ready | J14: Unique | K14: Table columns: Industry | Local sites and projects | Where flanges are used | What is usually specified.
A15: vizag | B15: /visakhapatnam/ | C15: 5 | D15: Materials guidance | E15: H2 + P | F15: Choosing flange materials for Visakhapatnam's coastal and process conditions | G15: Three things set a Vizag specification apart from an inland one. Salt air and seawater. Carbon-steel flanges near the harbour corrode quickly unless the coating is written into the purchase order - tell us the paint or galvanising system you need [CLIENT: confirm coating options]. Where seawater actually wets the flange, 304L and 316L pit and suffer crevice corrosion at the gasket face in warm harbour water; super duplex (ASTM A182 F53/F55) or 6Mo (F44) is the usual choice for pumped seawater, with standard duplex (F51/F60) and 316L kept to splash-zone and marine-air duty. The final call belongs to your process engineer - we quote whatever the line list says. Sour service. Refinery lines carrying wet H2S need material that meets NACE MR0103 / ISO 17945, with hardness control and certificates that say so. MR0175 / ISO 15156 is the equivalent for oil and gas production. State the standard on your enquiry and we price it in. Oxygen and high-temperature steam. Steel-plant oxygen lines need components cleaned and certified for oxygen service [CONFIRM offered]. Power-plant steam lines use chrome-moly grades - F11 and F22, and F91 at higher temperatures - supplied in the heat-treated condition ASTM A182 requires. | H15: =IF(LEN(TRIM(SUBSTITUTE(F15,CHAR(10)," ")))=0,0,LEN(TRIM(SUBSTITUTE(F15,CHAR(10)," ")))-LEN(SUBSTITUTE(TRIM(SUBSTITUTE(F15,CHAR(10)," "))," ",""))+1)+IF(LEN(TRIM(SUBSTITUTE(G15,CHAR(10)," ")))=0,0,LEN(TRIM(SUBSTITUTE(G15,CHAR(10)," ")))-LEN(SUBSTITUTE(TRIM(SUBSTITUTE(G15,CHAR(10)," "))," ",""))+1) -> 207 | I15: =IF(ISNUMBER(FIND("[CLIENT",F15&G15)),"CLIENT INPUT",IF(ISNUMBER(FIND("[CONFIRM",F15&G15)),"CONFIRM",IF(ISNUMBER(FIND("[DEV",F15&G15)),"DEV NOTE","Ready"))) -> CLIENT INPUT | J15: Unique | K15: Each line break = new paragraph.
A16: vizag | B16: /visakhapatnam/ | C16: 6 | D16: Product range | E16: H2 + P (table: tab 8b) | F16: Flange types we supply to Visakhapatnam | G16: Carbon-steel (MS) flanges in ASTM A105, stainless steel (SS 304/304L, 316/316L), alloy and duplex grades are forged and machined in our Mumbai unit [CLIENT: confirm which types are made in-house] and reach Visakhapatnam with material test certificates traceable to the heat number stamped on each flange. | H16: =IF(LEN(TRIM(SUBSTITUTE(F16,CHAR(10)," ")))=0,0,LEN(TRIM(SUBSTITUTE(F16,CHAR(10)," ")))-LEN(SUBSTITUTE(TRIM(SUBSTITUTE(F16,CHAR(10)," "))," ",""))+1)+IF(LEN(TRIM(SUBSTITUTE(G16,CHAR(10)," ")))=0,0,LEN(TRIM(SUBSTITUTE(G16,CHAR(10)," ")))-LEN(SUBSTITUTE(TRIM(SUBSTITUTE(G16,CHAR(10)," "))," ",""))+1) -> 52 | I16: =IF(ISNUMBER(FIND("[CLIENT",F16&G16)),"CLIENT INPUT",IF(ISNUMBER(FIND("[CONFIRM",F16&G16)),"CONFIRM",IF(ISNUMBER(FIND("[DEV",F16&G16)),"DEV NOTE","Ready"))) -> CLIENT INPUT | J16: Semi-unique | K16: Table columns: Flange type (link) | Typical use in Visakhapatnam.
A17: vizag | B17: /visakhapatnam/ | C17: 7 | D17: Manufacturing & QA | F17: =IF($F$6="","",$F$6) -> How every flange is made and checked | G17: =$G$6 -> Every flange starts as a certified billet or bar whose heat number follows it through cutting, forging, heat treatment where the material specification requires it, CNC machining and drilling, and final marking of grade, class, size and heat number. Before dispatch we check dimensions against the governing standard and [CLIENT: list only tests actually done in-house, e.g. PMI, hardness, ultrasonic], and issue material test certificates that tie each flange back to its heat. Buyer-nominated third-party inspection can witness any stage [CONFIRM]. | H17: =IF(LEN(TRIM(SUBSTITUTE(F17,CHAR(10)," ")))=0,0,LEN(TRIM(SUBSTITUTE(F17,CHAR(10)," ")))-LEN(SUBSTITUTE(TRIM(SUBSTITUTE(F17,CHAR(10)," "))," ",""))+1)+IF(LEN(TRIM(SUBSTITUTE(G17,CHAR(10)," ")))=0,0,LEN(TRIM(SUBSTITUTE(G17,CHAR(10)," ")))-LEN(SUBSTITUTE(TRIM(SUBSTITUTE(G17,CHAR(10)," "))," ",""))+1) -> 88 | I17: =IF(ISNUMBER(FIND("[CLIENT",F17&G17)),"CLIENT INPUT",IF(ISNUMBER(FIND("[CONFIRM",F17&G17)),"CONFIRM",IF(ISNUMBER(FIND("[DEV",F17&G17)),"DEV NOTE","Ready"))) -> CLIENT INPUT | J17: Shared
A18: vizag | B18: /visakhapatnam/ | C18: 8 | D18: Delivery & documents | E18: H2 + P | F18: Delivery to Visakhapatnam, Anakapalli and the port | G18: We dispatch from Mumbai by road [CLIENT: part-load or full-truck; transporter]. Door delivery to Visakhapatnam city, Gajuwaka, Autonagar, Parawada and Anakapalli sites typically takes [CLIENT: X-Y days] after dispatch; manufacturing time depends on size, grade and quantity, and both dates are written into your quote. Each consignment travels with a GST tax invoice (IGST, as an inter-state supply from Maharashtra), an e-way bill (mandatory above Rs 50,000 consignment value), a packing list and material test certificates. For cargo moving through Visakhapatnam or Gangavaram port, specify seaworthy packing - wooden cases, VCI wrapping, marking to your shipping instructions - in the form. | H18: =IF(LEN(TRIM(SUBSTITUTE(F18,CHAR(10)," ")))=0,0,LEN(TRIM(SUBSTITUTE(F18,CHAR(10)," ")))-LEN(SUBSTITUTE(TRIM(SUBSTITUTE(F18,CHAR(10)," "))," ",""))+1)+IF(LEN(TRIM(SUBSTITUTE(G18,CHAR(10)," ")))=0,0,LEN(TRIM(SUBSTITUTE(G18,CHAR(10)," ")))-LEN(SUBSTITUTE(TRIM(SUBSTITUTE(G18,CHAR(10)," "))," ",""))+1) -> 108 | I18: =IF(ISNUMBER(FIND("[CLIENT",F18&G18)),"CLIENT INPUT",IF(ISNUMBER(FIND("[CONFIRM",F18&G18)),"CONFIRM",IF(ISNUMBER(FIND("[DEV",F18&G18)),"DEV NOTE","Ready"))) -> CLIENT INPUT | J18: Unique
A19: vizag | B19: /visakhapatnam/ | C19: 9 | D19: Price guidance | E19: H2 + P | F19: Flange prices for Visakhapatnam delivery | G19: Flange prices move with material grade, weight (size x class), forged versus plate construction, facing (RTJ grooves cost more than raised face), extra testing (NACE, impact, third-party inspection) and quantity. [CLIENT: indicative Rs/kg bands for A105, 304L/316L and F11/F22, dated this month.] Freight to Visakhapatnam is shown as a separate line so you can compare like with like [CONFIRM]. Upload your BOQ and you get a line-by-line price rather than a lump sum. | H19: =IF(LEN(TRIM(SUBSTITUTE(F19,CHAR(10)," ")))=0,0,LEN(TRIM(SUBSTITUTE(F19,CHAR(10)," ")))-LEN(SUBSTITUTE(TRIM(SUBSTITUTE(F19,CHAR(10)," "))," ",""))+1)+IF(LEN(TRIM(SUBSTITUTE(G19,CHAR(10)," ")))=0,0,LEN(TRIM(SUBSTITUTE(G19,CHAR(10)," ")))-LEN(SUBSTITUTE(TRIM(SUBSTITUTE(G19,CHAR(10)," "))," ",""))+1) -> 78 | I19: =IF(ISNUMBER(FIND("[CLIENT",F19&G19)),"CLIENT INPUT",IF(ISNUMBER(FIND("[CONFIRM",F19&G19)),"CONFIRM",IF(ISNUMBER(FIND("[DEV",F19&G19)),"DEV NOTE","Ready"))) -> CLIENT INPUT | J19: Unique | K19: Add the dated Rs/kg band table here once the client supplies it (tab 15 I-26).
A20: vizag | B20: /visakhapatnam/ | C20: 10 | D20: Areas served | E20: H2 + P | F20: Areas we deliver in and around Visakhapatnam | G20: We deliver to sites across Gajuwaka and Autonagar, the Visakhapatnam SEZ at Duvvada, Jawaharlal Nehru Pharma City at Parawada, the Atchutapuram SEZ, and Anakapalli district from Nakkapalli to Rajayyapeta and Pudimadaka. [CLIENT: delete any area you would not deliver to.] For projects elsewhere on the coast, see our Andhra Pradesh page. | H20: =IF(LEN(TRIM(SUBSTITUTE(F20,CHAR(10)," ")))=0,0,LEN(TRIM(SUBSTITUTE(F20,CHAR(10)," ")))-LEN(SUBSTITUTE(TRIM(SUBSTITUTE(F20,CHAR(10)," "))," ",""))+1)+IF(LEN(TRIM(SUBSTITUTE(G20,CHAR(10)," ")))=0,0,LEN(TRIM(SUBSTITUTE(G20,CHAR(10)," ")))-LEN(SUBSTITUTE(TRIM(SUBSTITUTE(G20,CHAR(10)," "))," ",""))+1) -> 58 | I20: =IF(ISNUMBER(FIND("[CLIENT",F20&G20)),"CLIENT INPUT",IF(ISNUMBER(FIND("[CONFIRM",F20&G20)),"CONFIRM",IF(ISNUMBER(FIND("[DEV",F20&G20)),"DEV NOTE","Ready"))) -> CLIENT INPUT | J20: Unique | K20: Plain text, no locality links.
A21: vizag | B21: /visakhapatnam/ | C21: 11 | D21: Request a quote | F21: =IF($F$7="","",$F$7) -> Request a written quote | G21: =$G$7 -> A quote-ready enquiry lists: flange type · nominal size (NPS or DN) · pressure class or PN · facing (RF, FF or RTJ) · material specification and grade · bore or schedule for weld neck flanges · quantity · delivery location · testing and certificate needs (NACE, impact test, EN 10204 3.1/3.2, third-party inspection). Upload a BOQ or drawing and we will read it for you. | H21: =IF(LEN(TRIM(SUBSTITUTE(F21,CHAR(10)," ")))=0,0,LEN(TRIM(SUBSTITUTE(F21,CHAR(10)," ")))-LEN(SUBSTITUTE(TRIM(SUBSTITUTE(F21,CHAR(10)," "))," ",""))+1)+IF(LEN(TRIM(SUBSTITUTE(G21,CHAR(10)," ")))=0,0,LEN(TRIM(SUBSTITUTE(G21,CHAR(10)," ")))-LEN(SUBSTITUTE(TRIM(SUBSTITUTE(G21,CHAR(10)," "))," ",""))+1) -> 70 | I21: =IF(ISNUMBER(FIND("[CLIENT",F21&G21)),"CLIENT INPUT",IF(ISNUMBER(FIND("[CONFIRM",F21&G21)),"CONFIRM",IF(ISNUMBER(FIND("[DEV",F21&G21)),"DEV NOTE","Ready"))) -> Ready | J21: Shared
A22: vizag | B22: /visakhapatnam/ | C22: 12 | D22: FAQs | E22: H2 (Q&A in tab 9) | F22: Flange questions from Visakhapatnam buyers | H22: =IF(LEN(TRIM(SUBSTITUTE(F22,CHAR(10)," ")))=0,0,LEN(TRIM(SUBSTITUTE(F22,CHAR(10)," ")))-LEN(SUBSTITUTE(TRIM(SUBSTITUTE(F22,CHAR(10)," "))," ",""))+1)+IF(LEN(TRIM(SUBSTITUTE(G22,CHAR(10)," ")))=0,0,LEN(TRIM(SUBSTITUTE(G22,CHAR(10)," ")))-LEN(SUBSTITUTE(TRIM(SUBSTITUTE(G22,CHAR(10)," "))," ",""))+1) -> 5 | I22: =IF(ISNUMBER(FIND("[CLIENT",F22&G22)),"CLIENT INPUT",IF(ISNUMBER(FIND("[CONFIRM",F22&G22)),"CONFIRM",IF(ISNUMBER(FIND("[DEV",F22&G22)),"DEV NOTE","Ready"))) -> Ready | J22: Unique | K22: Questions and answers: tab 9.
A23: vizag | B23: /visakhapatnam/ | C23: 13 | D23: Related pages | E23: H2 + link list | F23: Related pages | G23: Flange supply across Andhra Pradesh · Nellore (refinery projects) · Sour-service NACE flanges · Flanges for oil & gas · Pipe flanges guide | H23: =IF(LEN(TRIM(SUBSTITUTE(F23,CHAR(10)," ")))=0,0,LEN(TRIM(SUBSTITUTE(F23,CHAR(10)," ")))-LEN(SUBSTITUTE(TRIM(SUBSTITUTE(F23,CHAR(10)," "))," ",""))+1)+IF(LEN(TRIM(SUBSTITUTE(G23,CHAR(10)," ")))=0,0,LEN(TRIM(SUBSTITUTE(G23,CHAR(10)," ")))-LEN(SUBSTITUTE(TRIM(SUBSTITUTE(G23,CHAR(10)," "))," ",""))+1) -> 25 | I23: =IF(ISNUMBER(FIND("[CLIENT",F23&G23)),"CLIENT INPUT",IF(ISNUMBER(FIND("[CONFIRM",F23&G23)),"CONFIRM",IF(ISNUMBER(FIND("[DEV",F23&G23)),"DEV NOTE","Ready"))) -> Ready | J23: Template | K23: Links: Flange supply across Andhra Pradesh → /market-area/andhra-pradesh/; Nellore (refinery projects) → /nellore/; Sour-service NACE flanges → /products/flanges/sour-service-nace-flange/; Flanges for oil & gas → /industries/oil-and-gas/; Pipe flanges guide → /blogs/pipe-flanges-guide/
A24: vizag | B24: /visakhapatnam/ | C24: 14 | D24: Final CTA | F24: =IF($F$8="","",$F$8) | G24: =$G$8 -> Send your requirement - we reply in writing. Fill the form or upload your BOQ; you get a line-by-line quote by email [CLIENT: reply time, e.g. within one working day]. No phone calls needed - everything is in writing. | H24: =IF(LEN(TRIM(SUBSTITUTE(F24,CHAR(10)," ")))=0,0,LEN(TRIM(SUBSTITUTE(F24,CHAR(10)," ")))-LEN(SUBSTITUTE(TRIM(SUBSTITUTE(F24,CHAR(10)," "))," ",""))+1)+IF(LEN(TRIM(SUBSTITUTE(G24,CHAR(10)," ")))=0,0,LEN(TRIM(SUBSTITUTE(G24,CHAR(10)," ")))-LEN(SUBSTITUTE(TRIM(SUBSTITUTE(G24,CHAR(10)," "))," ",""))+1) -> 39 | I24: =IF(ISNUMBER(FIND("[CLIENT",F24&G24)),"CLIENT INPUT",IF(ISNUMBER(FIND("[CONFIRM",F24&G24)),"CONFIRM",IF(ISNUMBER(FIND("[DEV",F24&G24)),"DEV NOTE","Ready"))) -> CLIENT INPUT | J24: Shared
A25: vijayawada | B25: /vijayawada/ | C25: 1 | D25: Breadcrumb | E25: Breadcrumb | G25: Home › Areas We Supply › Andhra Pradesh › Vijayawada | H25: =IF(LEN(TRIM(SUBSTITUTE(F25,CHAR(10)," ")))=0,0,LEN(TRIM(SUBSTITUTE(F25,CHAR(10)," ")))-LEN(SUBSTITUTE(TRIM(SUBSTITUTE(F25,CHAR(10)," "))," ",""))+1)+IF(LEN(TRIM(SUBSTITUTE(G25,CHAR(10)," ")))=0,0,LEN(TRIM(SUBSTITUTE(G25,CHAR(10)," ")))-LEN(SUBSTITUTE(TRIM(SUBSTITUTE(G25,CHAR(10)," "))," ",""))+1) -> 10 | I25: =IF(ISNUMBER(FIND("[CLIENT",F25&G25)),"CLIENT INPUT",IF(ISNUMBER(FIND("[CONFIRM",F25&G25)),"CONFIRM",IF(ISNUMBER(FIND("[DEV",F25&G25)),"DEV NOTE","Ready"))) -> Ready | J25: Template | K25: Slash-form links; see tab 12.
A26: vijayawada | B26: /vijayawada/ | C26: 2 | D26: Hero | E26: H1 | G26: Flange Supplier in Vijayawada & the Amaravati Capital Region | H26: =IF(LEN(TRIM(SUBSTITUTE(F26,CHAR(10)," ")))=0,0,LEN(TRIM(SUBSTITUTE(F26,CHAR(10)," ")))-LEN(SUBSTITUTE(TRIM(SUBSTITUTE(F26,CHAR(10)," "))," ",""))+1)+IF(LEN(TRIM(SUBSTITUTE(G26,CHAR(10)," ")))=0,0,LEN(TRIM(SUBSTITUTE(G26,CHAR(10)," ")))-LEN(SUBSTITUTE(TRIM(SUBSTITUTE(G26,CHAR(10)," "))," ",""))+1) -> 9 | I26: =IF(ISNUMBER(FIND("[CLIENT",F26&G26)),"CLIENT INPUT",IF(ISNUMBER(FIND("[CONFIRM",F26&G26)),"CONFIRM",IF(ISNUMBER(FIND("[DEV",F26&G26)),"DEV NOTE","Ready"))) -> Ready | J26: Unique | K26: The only <h1> on the page.
A27: vijayawada | B27: /vijayawada/ | C27: 2 | D27: Hero | E27: Subline (P under H1) | G27: Flanges manufacturer in Mumbai supplying power, industrial and capital-region projects around Vijayawada. | H27: =IF(LEN(TRIM(SUBSTITUTE(F27,CHAR(10)," ")))=0,0,LEN(TRIM(SUBSTITUTE(F27,CHAR(10)," ")))-LEN(SUBSTITUTE(TRIM(SUBSTITUTE(F27,CHAR(10)," "))," ",""))+1)+IF(LEN(TRIM(SUBSTITUTE(G27,CHAR(10)," ")))=0,0,LEN(TRIM(SUBSTITUTE(G27,CHAR(10)," ")))-LEN(SUBSTITUTE(TRIM(SUBSTITUTE(G27,CHAR(10)," "))," ",""))+1) -> 12 | I27: =IF(ISNUMBER(FIND("[CLIENT",F27&G27)),"CLIENT INPUT",IF(ISNUMBER(FIND("[CONFIRM",F27&G27)),"CONFIRM",IF(ISNUMBER(FIND("[DEV",F27&G27)),"DEV NOTE","Ready"))) -> Ready | J27: Unique
A28: vijayawada | B28: /vijayawada/ | C28: 2 | D28: Hero | E28: P (hero) + Form A | G28: Remax Forge is a flanges manufacturer in Mumbai supplying Vijayawada's power stations, the Kondapalli industrial belt, Autonagar fabricators and the contractors building the Amaravati capital region. Tell us the size, class and material in the form - or upload your BOQ - and we send a written quote by email [CLIENT: reply time]. | H28: =IF(LEN(TRIM(SUBSTITUTE(F28,CHAR(10)," ")))=0,0,LEN(TRIM(SUBSTITUTE(F28,CHAR(10)," ")))-LEN(SUBSTITUTE(TRIM(SUBSTITUTE(F28,CHAR(10)," "))," ",""))+1)+IF(LEN(TRIM(SUBSTITUTE(G28,CHAR(10)," ")))=0,0,LEN(TRIM(SUBSTITUTE(G28,CHAR(10)," ")))-LEN(SUBSTITUTE(TRIM(SUBSTITUTE(G28,CHAR(10)," "))," ",""))+1) -> 53 | I28: =IF(ISNUMBER(FIND("[CLIENT",F28&G28)),"CLIENT INPUT",IF(ISNUMBER(FIND("[CONFIRM",F28&G28)),"CONFIRM",IF(ISNUMBER(FIND("[DEV",F28&G28)),"DEV NOTE","Ready"))) -> CLIENT INPUT | J28: Unique | K28: Form A (tab 10) beside/below this paragraph.
A29: vijayawada | B29: /vijayawada/ | C29: 3 | D29: Trust strip | F29: =IF($F$5="","",$F$5) | G29: =$G$5 -> GSTIN 27FFLPP0007K1ZA (verify on the GST portal) · GST-registered since 2020 · Proprietorship led by Vikas Purohit, CEO · Manufacturing unit in Mumbai, Maharashtra [CLIENT: locality] · [CLIENT: real certifications only, e.g. ISO 9001:2015 — delete if none] · Written quotes by email, no calls needed | H29: =IF(LEN(TRIM(SUBSTITUTE(F29,CHAR(10)," ")))=0,0,LEN(TRIM(SUBSTITUTE(F29,CHAR(10)," ")))-LEN(SUBSTITUTE(TRIM(SUBSTITUTE(F29,CHAR(10)," "))," ",""))+1)+IF(LEN(TRIM(SUBSTITUTE(G29,CHAR(10)," ")))=0,0,LEN(TRIM(SUBSTITUTE(G29,CHAR(10)," ")))-LEN(SUBSTITUTE(TRIM(SUBSTITUTE(G29,CHAR(10)," "))," ",""))+1) -> 46 | I29: =IF(ISNUMBER(FIND("[CLIENT",F29&G29)),"CLIENT INPUT",IF(ISNUMBER(FIND("[CONFIRM",F29&G29)),"CONFIRM",IF(ISNUMBER(FIND("[DEV",F29&G29)),"DEV NOTE","Ready"))) -> CLIENT INPUT | J29: Shared
A30: vijayawada | B30: /vijayawada/ | C30: 4 | D30: Local demand | E30: H2 + P (table: tab 8b) | F30: What Vijayawada's projects specify | G30: Demand around Vijayawada splits between high-temperature power-plant piping and very large, low-pressure water and building-services work. The two need completely different flanges, so start with the row that matches your job. | H30: =IF(LEN(TRIM(SUBSTITUTE(F30,CHAR(10)," ")))=0,0,LEN(TRIM(SUBSTITUTE(F30,CHAR(10)," ")))-LEN(SUBSTITUTE(TRIM(SUBSTITUTE(F30,CHAR(10)," "))," ",""))+1)+IF(LEN(TRIM(SUBSTITUTE(G30,CHAR(10)," ")))=0,0,LEN(TRIM(SUBSTITUTE(G30,CHAR(10)," ")))-LEN(SUBSTITUTE(TRIM(SUBSTITUTE(G30,CHAR(10)," "))," ",""))+1) -> 35 | I30: =IF(ISNUMBER(FIND("[CLIENT",F30&G30)),"CLIENT INPUT",IF(ISNUMBER(FIND("[CONFIRM",F30&G30)),"CONFIRM",IF(ISNUMBER(FIND("[DEV",F30&G30)),"DEV NOTE","Ready"))) -> Ready | J30: Unique | K30: Table columns: Industry | Local sites and projects | Where flanges are used | What is usually specified.
A31: vijayawada | B31: /vijayawada/ | C31: 5 | D31: Materials guidance | E31: H2 + P | F31: Class 150 or PN16? The drilling mistake that stalls Vijayawada water jobs | G31: Work around Vijayawada and Amaravati often mixes equipment from different standards: pumps and valves drilled to EN 1092-1 PN10/PN16, pipe specified to IS or AWWA standards, and fire-fighting packages built to ASME. An ASME B16.5 Class 150 flange and an EN 1092-1 PN16 flange of the same nominal size generally have different bolt circles and bolt-hole sizes, so they will not bolt together. Before ordering, check the drilling standard of the valve or pump you are mating to and put it on the enquiry - we machine to ASME, EN, IS [CLIENT: confirm IS 6392 / BS / DIN capability] or to your drawing. Power-plant buyers face the opposite problem: pressure and temperature. For steam service, chrome-moly grades F11, F22 and F91 must be supplied in the heat-treated condition ASTM A182 requires, and the certificate should show it. Ask for the heat-treatment record with your quote. | H31: =IF(LEN(TRIM(SUBSTITUTE(F31,CHAR(10)," ")))=0,0,LEN(TRIM(SUBSTITUTE(F31,CHAR(10)," ")))-LEN(SUBSTITUTE(TRIM(SUBSTITUTE(F31,CHAR(10)," "))," ",""))+1)+IF(LEN(TRIM(SUBSTITUTE(G31,CHAR(10)," ")))=0,0,LEN(TRIM(SUBSTITUTE(G31,CHAR(10)," ")))-LEN(SUBSTITUTE(TRIM(SUBSTITUTE(G31,CHAR(10)," "))," ",""))+1) -> 158 | I31: =IF(ISNUMBER(FIND("[CLIENT",F31&G31)),"CLIENT INPUT",IF(ISNUMBER(FIND("[CONFIRM",F31&G31)),"CONFIRM",IF(ISNUMBER(FIND("[DEV",F31&G31)),"DEV NOTE","Ready"))) -> CLIENT INPUT | J31: Unique | K31: Each line break = new paragraph.
A32: vijayawada | B32: /vijayawada/ | C32: 6 | D32: Product range | E32: H2 + P (table: tab 8b) | F32: Flange types we supply to Vijayawada | G32: MS (carbon steel A105), SS 304L/316L and chrome-moly flanges ship from Mumbai to Vijayawada with certificates tied to each flange's heat number. Large-diameter and custom-drilled flanges for water projects are made to order [CLIENT: confirm maximum size]. | H32: =IF(LEN(TRIM(SUBSTITUTE(F32,CHAR(10)," ")))=0,0,LEN(TRIM(SUBSTITUTE(F32,CHAR(10)," ")))-LEN(SUBSTITUTE(TRIM(SUBSTITUTE(F32,CHAR(10)," "))," ",""))+1)+IF(LEN(TRIM(SUBSTITUTE(G32,CHAR(10)," ")))=0,0,LEN(TRIM(SUBSTITUTE(G32,CHAR(10)," ")))-LEN(SUBSTITUTE(TRIM(SUBSTITUTE(G32,CHAR(10)," "))," ",""))+1) -> 43 | I32: =IF(ISNUMBER(FIND("[CLIENT",F32&G32)),"CLIENT INPUT",IF(ISNUMBER(FIND("[CONFIRM",F32&G32)),"CONFIRM",IF(ISNUMBER(FIND("[DEV",F32&G32)),"DEV NOTE","Ready"))) -> CLIENT INPUT | J32: Semi-unique | K32: Table columns: Flange type (link) | Typical use in Vijayawada.
A33: vijayawada | B33: /vijayawada/ | C33: 7 | D33: Manufacturing & QA | F33: =IF($F$6="","",$F$6) -> How every flange is made and checked | G33: =$G$6 -> Every flange starts as a certified billet or bar whose heat number follows it through cutting, forging, heat treatment where the material specification requires it, CNC machining and drilling, and final marking of grade, class, size and heat number. Before dispatch we check dimensions against the governing standard and [CLIENT: list only tests actually done in-house, e.g. PMI, hardness, ultrasonic], and issue material test certificates that tie each flange back to its heat. Buyer-nominated third-party inspection can witness any stage [CONFIRM]. | H33: =IF(LEN(TRIM(SUBSTITUTE(F33,CHAR(10)," ")))=0,0,LEN(TRIM(SUBSTITUTE(F33,CHAR(10)," ")))-LEN(SUBSTITUTE(TRIM(SUBSTITUTE(F33,CHAR(10)," "))," ",""))+1)+IF(LEN(TRIM(SUBSTITUTE(G33,CHAR(10)," ")))=0,0,LEN(TRIM(SUBSTITUTE(G33,CHAR(10)," ")))-LEN(SUBSTITUTE(TRIM(SUBSTITUTE(G33,CHAR(10)," "))," ",""))+1) -> 88 | I33: =IF(ISNUMBER(FIND("[CLIENT",F33&G33)),"CLIENT INPUT",IF(ISNUMBER(FIND("[CONFIRM",F33&G33)),"CONFIRM",IF(ISNUMBER(FIND("[DEV",F33&G33)),"DEV NOTE","Ready"))) -> CLIENT INPUT | J33: Shared
A34: vijayawada | B34: /vijayawada/ | C34: 8 | D34: Delivery & documents | E34: H2 + P | F34: Delivery to Vijayawada, Kondapalli and Amaravati sites | G34: Road dispatch from Mumbai reaches Vijayawada, Kondapalli, Ibrahimpatnam and the Amaravati capital area in typically [CLIENT: X-Y days] after dispatch. Construction sites often have no receiving store, so add the site contact and unloading constraints (crane, access road, working hours) in the form and the transporter can plan around them. Invoices are raised with IGST as an inter-state supply from Maharashtra, and an e-way bill travels with every consignment above Rs 50,000. Certificates are matched to the heat numbers stamped on the flanges, which keeps the contractor's material reconciliation simple. | H34: =IF(LEN(TRIM(SUBSTITUTE(F34,CHAR(10)," ")))=0,0,LEN(TRIM(SUBSTITUTE(F34,CHAR(10)," ")))-LEN(SUBSTITUTE(TRIM(SUBSTITUTE(F34,CHAR(10)," "))," ",""))+1)+IF(LEN(TRIM(SUBSTITUTE(G34,CHAR(10)," ")))=0,0,LEN(TRIM(SUBSTITUTE(G34,CHAR(10)," ")))-LEN(SUBSTITUTE(TRIM(SUBSTITUTE(G34,CHAR(10)," "))," ",""))+1) -> 97 | I34: =IF(ISNUMBER(FIND("[CLIENT",F34&G34)),"CLIENT INPUT",IF(ISNUMBER(FIND("[CONFIRM",F34&G34)),"CONFIRM",IF(ISNUMBER(FIND("[DEV",F34&G34)),"DEV NOTE","Ready"))) -> CLIENT INPUT | J34: Unique
A35: vijayawada | B35: /vijayawada/ | C35: 9 | D35: Price guidance | E35: H2 + P | F35: Pricing water-project and power-plant flanges | G35: Water-project flanges are priced mostly by weight and drilling; power-plant flanges by grade, class and testing. [CLIENT: indicative Rs/kg bands.] Send the tender BOQ and we quote line by line, with freight to Vijayawada shown separately [CONFIRM]. | H35: =IF(LEN(TRIM(SUBSTITUTE(F35,CHAR(10)," ")))=0,0,LEN(TRIM(SUBSTITUTE(F35,CHAR(10)," ")))-LEN(SUBSTITUTE(TRIM(SUBSTITUTE(F35,CHAR(10)," "))," ",""))+1)+IF(LEN(TRIM(SUBSTITUTE(G35,CHAR(10)," ")))=0,0,LEN(TRIM(SUBSTITUTE(G35,CHAR(10)," ")))-LEN(SUBSTITUTE(TRIM(SUBSTITUTE(G35,CHAR(10)," "))," ",""))+1) -> 42 | I35: =IF(ISNUMBER(FIND("[CLIENT",F35&G35)),"CLIENT INPUT",IF(ISNUMBER(FIND("[CONFIRM",F35&G35)),"CONFIRM",IF(ISNUMBER(FIND("[DEV",F35&G35)),"DEV NOTE","Ready"))) -> CLIENT INPUT | J35: Unique | K35: Add the dated Rs/kg band table here once the client supplies it (tab 15 I-26).
A36: vijayawada | B36: /vijayawada/ | C36: 10 | D36: Areas served | E36: H2 + P | F36: Areas we deliver around Vijayawada | G36: We deliver across Vijayawada city and Autonagar, the Kondapalli industrial area, Ibrahimpatnam, Gannavaram, Mangalagiri and Tadepalli, and capital-region sites around Amaravati. [CLIENT: remove anything you would not deliver to.] Guntur has its own page, and the rest of the state is on our Andhra Pradesh page. | H36: =IF(LEN(TRIM(SUBSTITUTE(F36,CHAR(10)," ")))=0,0,LEN(TRIM(SUBSTITUTE(F36,CHAR(10)," ")))-LEN(SUBSTITUTE(TRIM(SUBSTITUTE(F36,CHAR(10)," "))," ",""))+1)+IF(LEN(TRIM(SUBSTITUTE(G36,CHAR(10)," ")))=0,0,LEN(TRIM(SUBSTITUTE(G36,CHAR(10)," ")))-LEN(SUBSTITUTE(TRIM(SUBSTITUTE(G36,CHAR(10)," "))," ",""))+1) -> 51 | I36: =IF(ISNUMBER(FIND("[CLIENT",F36&G36)),"CLIENT INPUT",IF(ISNUMBER(FIND("[CONFIRM",F36&G36)),"CONFIRM",IF(ISNUMBER(FIND("[DEV",F36&G36)),"DEV NOTE","Ready"))) -> CLIENT INPUT | J36: Unique | K36: Plain text, no locality links.
A37: vijayawada | B37: /vijayawada/ | C37: 11 | D37: Request a quote | F37: =IF($F$7="","",$F$7) -> Request a written quote | G37: =$G$7 -> A quote-ready enquiry lists: flange type · nominal size (NPS or DN) · pressure class or PN · facing (RF, FF or RTJ) · material specification and grade · bore or schedule for weld neck flanges · quantity · delivery location · testing and certificate needs (NACE, impact test, EN 10204 3.1/3.2, third-party inspection). Upload a BOQ or drawing and we will read it for you. | H37: =IF(LEN(TRIM(SUBSTITUTE(F37,CHAR(10)," ")))=0,0,LEN(TRIM(SUBSTITUTE(F37,CHAR(10)," ")))-LEN(SUBSTITUTE(TRIM(SUBSTITUTE(F37,CHAR(10)," "))," ",""))+1)+IF(LEN(TRIM(SUBSTITUTE(G37,CHAR(10)," ")))=0,0,LEN(TRIM(SUBSTITUTE(G37,CHAR(10)," ")))-LEN(SUBSTITUTE(TRIM(SUBSTITUTE(G37,CHAR(10)," "))," ",""))+1) -> 70 | I37: =IF(ISNUMBER(FIND("[CLIENT",F37&G37)),"CLIENT INPUT",IF(ISNUMBER(FIND("[CONFIRM",F37&G37)),"CONFIRM",IF(ISNUMBER(FIND("[DEV",F37&G37)),"DEV NOTE","Ready"))) -> Ready | J37: Shared
A38: vijayawada | B38: /vijayawada/ | C38: 12 | D38: FAQs | E38: H2 (Q&A in tab 9) | F38: Flange questions from Vijayawada buyers | H38: =IF(LEN(TRIM(SUBSTITUTE(F38,CHAR(10)," ")))=0,0,LEN(TRIM(SUBSTITUTE(F38,CHAR(10)," ")))-LEN(SUBSTITUTE(TRIM(SUBSTITUTE(F38,CHAR(10)," "))," ",""))+1)+IF(LEN(TRIM(SUBSTITUTE(G38,CHAR(10)," ")))=0,0,LEN(TRIM(SUBSTITUTE(G38,CHAR(10)," ")))-LEN(SUBSTITUTE(TRIM(SUBSTITUTE(G38,CHAR(10)," "))," ",""))+1) -> 5 | I38: =IF(ISNUMBER(FIND("[CLIENT",F38&G38)),"CLIENT INPUT",IF(ISNUMBER(FIND("[CONFIRM",F38&G38)),"CONFIRM",IF(ISNUMBER(FIND("[DEV",F38&G38)),"DEV NOTE","Ready"))) -> Ready | J38: Unique | K38: Questions and answers: tab 9.
A39: vijayawada | B39: /vijayawada/ | C39: 13 | D39: Related pages | E39: H2 + link list | F39: Related pages | G39: Flange supply across Andhra Pradesh · Guntur · Pipe flanges guide · Kurnool (large-bore water projects) | H39: =IF(LEN(TRIM(SUBSTITUTE(F39,CHAR(10)," ")))=0,0,LEN(TRIM(SUBSTITUTE(F39,CHAR(10)," ")))-LEN(SUBSTITUTE(TRIM(SUBSTITUTE(F39,CHAR(10)," "))," ",""))+1)+IF(LEN(TRIM(SUBSTITUTE(G39,CHAR(10)," ")))=0,0,LEN(TRIM(SUBSTITUTE(G39,CHAR(10)," ")))-LEN(SUBSTITUTE(TRIM(SUBSTITUTE(G39,CHAR(10)," "))," ",""))+1) -> 18 | I39: =IF(ISNUMBER(FIND("[CLIENT",F39&G39)),"CLIENT INPUT",IF(ISNUMBER(FIND("[CONFIRM",F39&G39)),"CONFIRM",IF(ISNUMBER(FIND("[DEV",F39&G39)),"DEV NOTE","Ready"))) -> Ready | J39: Template | K39: Links: Flange supply across Andhra Pradesh → /market-area/andhra-pradesh/; Guntur → /guntur/; Pipe flanges guide → /blogs/pipe-flanges-guide/; Kurnool (large-bore water projects) → /kurnool/
A40: vijayawada | B40: /vijayawada/ | C40: 14 | D40: Final CTA | F40: =IF($F$8="","",$F$8) | G40: =$G$8 -> Send your requirement - we reply in writing. Fill the form or upload your BOQ; you get a line-by-line quote by email [CLIENT: reply time, e.g. within one working day]. No phone calls needed - everything is in writing. | H40: =IF(LEN(TRIM(SUBSTITUTE(F40,CHAR(10)," ")))=0,0,LEN(TRIM(SUBSTITUTE(F40,CHAR(10)," ")))-LEN(SUBSTITUTE(TRIM(SUBSTITUTE(F40,CHAR(10)," "))," ",""))+1)+IF(LEN(TRIM(SUBSTITUTE(G40,CHAR(10)," ")))=0,0,LEN(TRIM(SUBSTITUTE(G40,CHAR(10)," ")))-LEN(SUBSTITUTE(TRIM(SUBSTITUTE(G40,CHAR(10)," "))," ",""))+1) -> 39 | I40: =IF(ISNUMBER(FIND("[CLIENT",F40&G40)),"CLIENT INPUT",IF(ISNUMBER(FIND("[CONFIRM",F40&G40)),"CONFIRM",IF(ISNUMBER(FIND("[DEV",F40&G40)),"DEV NOTE","Ready"))) -> CLIENT INPUT | J40: Shared
A41: guntur | B41: /guntur/ | C41: 1 | D41: Breadcrumb | E41: Breadcrumb | G41: Home › Areas We Supply › Andhra Pradesh › Guntur | H41: =IF(LEN(TRIM(SUBSTITUTE(F41,CHAR(10)," ")))=0,0,LEN(TRIM(SUBSTITUTE(F41,CHAR(10)," ")))-LEN(SUBSTITUTE(TRIM(SUBSTITUTE(F41,CHAR(10)," "))," ",""))+1)+IF(LEN(TRIM(SUBSTITUTE(G41,CHAR(10)," ")))=0,0,LEN(TRIM(SUBSTITUTE(G41,CHAR(10)," ")))-LEN(SUBSTITUTE(TRIM(SUBSTITUTE(G41,CHAR(10)," "))," ",""))+1) -> 10 | I41: =IF(ISNUMBER(FIND("[CLIENT",F41&G41)),"CLIENT INPUT",IF(ISNUMBER(FIND("[CONFIRM",F41&G41)),"CONFIRM",IF(ISNUMBER(FIND("[DEV",F41&G41)),"DEV NOTE","Ready"))) -> Ready | J41: Template | K41: Slash-form links; see tab 12.
A42: guntur | B42: /guntur/ | C42: 2 | D42: Hero | E42: H1 | G42: Flange Supplier in Guntur | H42: =IF(LEN(TRIM(SUBSTITUTE(F42,CHAR(10)," ")))=0,0,LEN(TRIM(SUBSTITUTE(F42,CHAR(10)," ")))-LEN(SUBSTITUTE(TRIM(SUBSTITUTE(F42,CHAR(10)," "))," ",""))+1)+IF(LEN(TRIM(SUBSTITUTE(G42,CHAR(10)," ")))=0,0,LEN(TRIM(SUBSTITUTE(G42,CHAR(10)," ")))-LEN(SUBSTITUTE(TRIM(SUBSTITUTE(G42,CHAR(10)," "))," ",""))+1) -> 4 | I42: =IF(ISNUMBER(FIND("[CLIENT",F42&G42)),"CLIENT INPUT",IF(ISNUMBER(FIND("[CONFIRM",F42&G42)),"CONFIRM",IF(ISNUMBER(FIND("[DEV",F42&G42)),"DEV NOTE","Ready"))) -> Ready | J42: Unique | K42: The only <h1> on the page.
A43: guntur | B43: /guntur/ | C43: 2 | D43: Hero | E43: Subline (P under H1) | G43: Flanges manufacturer in Mumbai supplying cold chain, agro-processing and capital-region projects in Guntur district. | H43: =IF(LEN(TRIM(SUBSTITUTE(F43,CHAR(10)," ")))=0,0,LEN(TRIM(SUBSTITUTE(F43,CHAR(10)," ")))-LEN(SUBSTITUTE(TRIM(SUBSTITUTE(F43,CHAR(10)," "))," ",""))+1)+IF(LEN(TRIM(SUBSTITUTE(G43,CHAR(10)," ")))=0,0,LEN(TRIM(SUBSTITUTE(G43,CHAR(10)," ")))-LEN(SUBSTITUTE(TRIM(SUBSTITUTE(G43,CHAR(10)," "))," ",""))+1) -> 14 | I43: =IF(ISNUMBER(FIND("[CLIENT",F43&G43)),"CLIENT INPUT",IF(ISNUMBER(FIND("[CONFIRM",F43&G43)),"CONFIRM",IF(ISNUMBER(FIND("[DEV",F43&G43)),"DEV NOTE","Ready"))) -> Ready | J43: Unique
A44: guntur | B44: /guntur/ | C44: 2 | D44: Hero | E44: P (hero) + Form A | G44: Remax Forge is a flanges manufacturer in Mumbai supplying Guntur's cold-storage operators, agro-processing plants, refrigeration and boiler contractors, and projects in the capital-region mandals of Guntur district. Send your size, class and grade in the form and we reply with a written quote [CLIENT: reply time]. | H44: =IF(LEN(TRIM(SUBSTITUTE(F44,CHAR(10)," ")))=0,0,LEN(TRIM(SUBSTITUTE(F44,CHAR(10)," ")))-LEN(SUBSTITUTE(TRIM(SUBSTITUTE(F44,CHAR(10)," "))," ",""))+1)+IF(LEN(TRIM(SUBSTITUTE(G44,CHAR(10)," ")))=0,0,LEN(TRIM(SUBSTITUTE(G44,CHAR(10)," ")))-LEN(SUBSTITUTE(TRIM(SUBSTITUTE(G44,CHAR(10)," "))," ",""))+1) -> 46 | I44: =IF(ISNUMBER(FIND("[CLIENT",F44&G44)),"CLIENT INPUT",IF(ISNUMBER(FIND("[CONFIRM",F44&G44)),"CONFIRM",IF(ISNUMBER(FIND("[DEV",F44&G44)),"DEV NOTE","Ready"))) -> CLIENT INPUT | J44: Unique | K44: Form A (tab 10) beside/below this paragraph.
A45: guntur | B45: /guntur/ | C45: 3 | D45: Trust strip | F45: =IF($F$5="","",$F$5) | G45: =$G$5 -> GSTIN 27FFLPP0007K1ZA (verify on the GST portal) · GST-registered since 2020 · Proprietorship led by Vikas Purohit, CEO · Manufacturing unit in Mumbai, Maharashtra [CLIENT: locality] · [CLIENT: real certifications only, e.g. ISO 9001:2015 — delete if none] · Written quotes by email, no calls needed | H45: =IF(LEN(TRIM(SUBSTITUTE(F45,CHAR(10)," ")))=0,0,LEN(TRIM(SUBSTITUTE(F45,CHAR(10)," ")))-LEN(SUBSTITUTE(TRIM(SUBSTITUTE(F45,CHAR(10)," "))," ",""))+1)+IF(LEN(TRIM(SUBSTITUTE(G45,CHAR(10)," ")))=0,0,LEN(TRIM(SUBSTITUTE(G45,CHAR(10)," ")))-LEN(SUBSTITUTE(TRIM(SUBSTITUTE(G45,CHAR(10)," "))," ",""))+1) -> 46 | I45: =IF(ISNUMBER(FIND("[CLIENT",F45&G45)),"CLIENT INPUT",IF(ISNUMBER(FIND("[CONFIRM",F45&G45)),"CONFIRM",IF(ISNUMBER(FIND("[DEV",F45&G45)),"DEV NOTE","Ready"))) -> CLIENT INPUT | J45: Shared
A46: guntur | B46: /guntur/ | C46: 4 | D46: Local demand | E46: H2 + P (table: tab 8b) | F46: Where Guntur's flange demand comes from | G46: Guntur's piping is mostly utilities - refrigeration, steam and water - rather than heavy process plant. That makes material choice and documentation, not exotic grades, the things most likely to go wrong. | H46: =IF(LEN(TRIM(SUBSTITUTE(F46,CHAR(10)," ")))=0,0,LEN(TRIM(SUBSTITUTE(F46,CHAR(10)," ")))-LEN(SUBSTITUTE(TRIM(SUBSTITUTE(F46,CHAR(10)," "))," ",""))+1)+IF(LEN(TRIM(SUBSTITUTE(G46,CHAR(10)," ")))=0,0,LEN(TRIM(SUBSTITUTE(G46,CHAR(10)," ")))-LEN(SUBSTITUTE(TRIM(SUBSTITUTE(G46,CHAR(10)," "))," ",""))+1) -> 38 | I46: =IF(ISNUMBER(FIND("[CLIENT",F46&G46)),"CLIENT INPUT",IF(ISNUMBER(FIND("[CONFIRM",F46&G46)),"CONFIRM",IF(ISNUMBER(FIND("[DEV",F46&G46)),"DEV NOTE","Ready"))) -> Ready | J46: Unique | K46: Table columns: Industry | Local sites and projects | Where flanges are used | What is usually specified.
A47: guntur | B47: /guntur/ | C47: 5 | D47: Materials guidance | E47: H2 + P | F47: Refrigeration and boiler flanges: what Guntur buyers should specify | G47: Two rules prevent most of the problems we see in utility piping. Ammonia and copper do not mix. Ammonia attacks copper and its alloys, so every flange and fitting on an ammonia refrigeration circuit should be steel. Carbon steel A105 suits typical cold-store temperatures. ASME B16.5 tabulates pressure-temperature ratings only from -29 °C upward, so for colder design metal temperatures - blast freezers, low-temperature stores - specify impact-tested A350 LF2 (Class 1 is impact-tested at -46 °C) and confirm against your refrigeration code. Steam under IBR needs paperwork. Boiler steam lines that fall under the Indian Boiler Regulations need IBR-certified material and documents, and inspectors check them. Tell us at enquiry stage if your line is IBR - it changes the certificates, the lead time and the price. [CLIENT: confirm IBR capability; if not offered, say so plainly here.] | H47: =IF(LEN(TRIM(SUBSTITUTE(F47,CHAR(10)," ")))=0,0,LEN(TRIM(SUBSTITUTE(F47,CHAR(10)," ")))-LEN(SUBSTITUTE(TRIM(SUBSTITUTE(F47,CHAR(10)," "))," ",""))+1)+IF(LEN(TRIM(SUBSTITUTE(G47,CHAR(10)," ")))=0,0,LEN(TRIM(SUBSTITUTE(G47,CHAR(10)," ")))-LEN(SUBSTITUTE(TRIM(SUBSTITUTE(G47,CHAR(10)," "))," ",""))+1) -> 148 | I47: =IF(ISNUMBER(FIND("[CLIENT",F47&G47)),"CLIENT INPUT",IF(ISNUMBER(FIND("[CONFIRM",F47&G47)),"CONFIRM",IF(ISNUMBER(FIND("[DEV",F47&G47)),"DEV NOTE","Ready"))) -> CLIENT INPUT | J47: Unique | K47: Each line break = new paragraph.
A48: guntur | B48: /guntur/ | C48: 6 | D48: Product range | E48: H2 + P (table: tab 8b) | F48: Flange types we supply to Guntur | G48: Most Guntur orders are standard sizes in MS (A105) and SS 304L/316L, which keeps lead times short [CLIENT: confirm stocked sizes]. The full range ships from Mumbai with heat-number-traceable certificates. | H48: =IF(LEN(TRIM(SUBSTITUTE(F48,CHAR(10)," ")))=0,0,LEN(TRIM(SUBSTITUTE(F48,CHAR(10)," ")))-LEN(SUBSTITUTE(TRIM(SUBSTITUTE(F48,CHAR(10)," "))," ",""))+1)+IF(LEN(TRIM(SUBSTITUTE(G48,CHAR(10)," ")))=0,0,LEN(TRIM(SUBSTITUTE(G48,CHAR(10)," ")))-LEN(SUBSTITUTE(TRIM(SUBSTITUTE(G48,CHAR(10)," "))," ",""))+1) -> 36 | I48: =IF(ISNUMBER(FIND("[CLIENT",F48&G48)),"CLIENT INPUT",IF(ISNUMBER(FIND("[CONFIRM",F48&G48)),"CONFIRM",IF(ISNUMBER(FIND("[DEV",F48&G48)),"DEV NOTE","Ready"))) -> CLIENT INPUT | J48: Semi-unique | K48: Table columns: Flange type (link) | Typical use in Guntur.
A49: guntur | B49: /guntur/ | C49: 7 | D49: Manufacturing & QA | F49: =IF($F$6="","",$F$6) -> How every flange is made and checked | G49: =$G$6 -> Every flange starts as a certified billet or bar whose heat number follows it through cutting, forging, heat treatment where the material specification requires it, CNC machining and drilling, and final marking of grade, class, size and heat number. Before dispatch we check dimensions against the governing standard and [CLIENT: list only tests actually done in-house, e.g. PMI, hardness, ultrasonic], and issue material test certificates that tie each flange back to its heat. Buyer-nominated third-party inspection can witness any stage [CONFIRM]. | H49: =IF(LEN(TRIM(SUBSTITUTE(F49,CHAR(10)," ")))=0,0,LEN(TRIM(SUBSTITUTE(F49,CHAR(10)," ")))-LEN(SUBSTITUTE(TRIM(SUBSTITUTE(F49,CHAR(10)," "))," ",""))+1)+IF(LEN(TRIM(SUBSTITUTE(G49,CHAR(10)," ")))=0,0,LEN(TRIM(SUBSTITUTE(G49,CHAR(10)," ")))-LEN(SUBSTITUTE(TRIM(SUBSTITUTE(G49,CHAR(10)," "))," ",""))+1) -> 88 | I49: =IF(ISNUMBER(FIND("[CLIENT",F49&G49)),"CLIENT INPUT",IF(ISNUMBER(FIND("[CONFIRM",F49&G49)),"CONFIRM",IF(ISNUMBER(FIND("[DEV",F49&G49)),"DEV NOTE","Ready"))) -> CLIENT INPUT | J49: Shared
A50: guntur | B50: /guntur/ | C50: 8 | D50: Delivery & documents | E50: H2 + P | F50: Delivery to Guntur and the district | G50: We dispatch by road from Mumbai to Guntur city, the cold-storage belt around the Mirchi Yard, Mangalagiri, Tadepalli and mill clusters in the district, typically [CLIENT: X-Y days] after dispatch. Cold-storage and mill maintenance jobs are often urgent - put your shutdown date in the form and we will say honestly whether we can meet it. The invoice carries IGST, an e-way bill accompanies consignments above Rs 50,000, and the certificates match the heat numbers on each flange. | H50: =IF(LEN(TRIM(SUBSTITUTE(F50,CHAR(10)," ")))=0,0,LEN(TRIM(SUBSTITUTE(F50,CHAR(10)," ")))-LEN(SUBSTITUTE(TRIM(SUBSTITUTE(F50,CHAR(10)," "))," ",""))+1)+IF(LEN(TRIM(SUBSTITUTE(G50,CHAR(10)," ")))=0,0,LEN(TRIM(SUBSTITUTE(G50,CHAR(10)," ")))-LEN(SUBSTITUTE(TRIM(SUBSTITUTE(G50,CHAR(10)," "))," ",""))+1) -> 84 | I50: =IF(ISNUMBER(FIND("[CLIENT",F50&G50)),"CLIENT INPUT",IF(ISNUMBER(FIND("[CONFIRM",F50&G50)),"CONFIRM",IF(ISNUMBER(FIND("[DEV",F50&G50)),"DEV NOTE","Ready"))) -> CLIENT INPUT | J50: Unique
A51: guntur | B51: /guntur/ | C51: 9 | D51: Price guidance | E51: H2 + P | F51: What drives the price of refrigeration and boiler flanges | G51: For refrigeration and boiler work, price depends mainly on grade (A105 or LF2), class, size and whether IBR documentation is needed. [CLIENT: indicative Rs/kg bands.] Upload your BOQ for a line-by-line quote. | H51: =IF(LEN(TRIM(SUBSTITUTE(F51,CHAR(10)," ")))=0,0,LEN(TRIM(SUBSTITUTE(F51,CHAR(10)," ")))-LEN(SUBSTITUTE(TRIM(SUBSTITUTE(F51,CHAR(10)," "))," ",""))+1)+IF(LEN(TRIM(SUBSTITUTE(G51,CHAR(10)," ")))=0,0,LEN(TRIM(SUBSTITUTE(G51,CHAR(10)," ")))-LEN(SUBSTITUTE(TRIM(SUBSTITUTE(G51,CHAR(10)," "))," ",""))+1) -> 41 | I51: =IF(ISNUMBER(FIND("[CLIENT",F51&G51)),"CLIENT INPUT",IF(ISNUMBER(FIND("[CONFIRM",F51&G51)),"CONFIRM",IF(ISNUMBER(FIND("[DEV",F51&G51)),"DEV NOTE","Ready"))) -> CLIENT INPUT | J51: Unique | K51: Add the dated Rs/kg band table here once the client supplies it (tab 15 I-26).
A52: guntur | B52: /guntur/ | C52: 10 | D52: Areas served | E52: H2 + P | F52: Areas we deliver around Guntur | G52: We deliver across Guntur city, the cold-storage clusters around the Mirchi Yard, Mangalagiri, Tadepalli and Thullur in the capital area, and nearby towns such as Tenali, Narasaraopet and Chilakaluripet. [CLIENT: adjust.] Vijayawada and Amaravati construction packages are covered on our Vijayawada page. | H52: =IF(LEN(TRIM(SUBSTITUTE(F52,CHAR(10)," ")))=0,0,LEN(TRIM(SUBSTITUTE(F52,CHAR(10)," ")))-LEN(SUBSTITUTE(TRIM(SUBSTITUTE(F52,CHAR(10)," "))," ",""))+1)+IF(LEN(TRIM(SUBSTITUTE(G52,CHAR(10)," ")))=0,0,LEN(TRIM(SUBSTITUTE(G52,CHAR(10)," ")))-LEN(SUBSTITUTE(TRIM(SUBSTITUTE(G52,CHAR(10)," "))," ",""))+1) -> 47 | I52: =IF(ISNUMBER(FIND("[CLIENT",F52&G52)),"CLIENT INPUT",IF(ISNUMBER(FIND("[CONFIRM",F52&G52)),"CONFIRM",IF(ISNUMBER(FIND("[DEV",F52&G52)),"DEV NOTE","Ready"))) -> CLIENT INPUT | J52: Unique | K52: Plain text, no locality links.
A53: guntur | B53: /guntur/ | C53: 11 | D53: Request a quote | F53: =IF($F$7="","",$F$7) -> Request a written quote | G53: =$G$7 -> A quote-ready enquiry lists: flange type · nominal size (NPS or DN) · pressure class or PN · facing (RF, FF or RTJ) · material specification and grade · bore or schedule for weld neck flanges · quantity · delivery location · testing and certificate needs (NACE, impact test, EN 10204 3.1/3.2, third-party inspection). Upload a BOQ or drawing and we will read it for you. | H53: =IF(LEN(TRIM(SUBSTITUTE(F53,CHAR(10)," ")))=0,0,LEN(TRIM(SUBSTITUTE(F53,CHAR(10)," ")))-LEN(SUBSTITUTE(TRIM(SUBSTITUTE(F53,CHAR(10)," "))," ",""))+1)+IF(LEN(TRIM(SUBSTITUTE(G53,CHAR(10)," ")))=0,0,LEN(TRIM(SUBSTITUTE(G53,CHAR(10)," ")))-LEN(SUBSTITUTE(TRIM(SUBSTITUTE(G53,CHAR(10)," "))," ",""))+1) -> 70 | I53: =IF(ISNUMBER(FIND("[CLIENT",F53&G53)),"CLIENT INPUT",IF(ISNUMBER(FIND("[CONFIRM",F53&G53)),"CONFIRM",IF(ISNUMBER(FIND("[DEV",F53&G53)),"DEV NOTE","Ready"))) -> Ready | J53: Shared
A54: guntur | B54: /guntur/ | C54: 12 | D54: FAQs | E54: H2 (Q&A in tab 9) | F54: Flange questions from Guntur buyers | H54: =IF(LEN(TRIM(SUBSTITUTE(F54,CHAR(10)," ")))=0,0,LEN(TRIM(SUBSTITUTE(F54,CHAR(10)," ")))-LEN(SUBSTITUTE(TRIM(SUBSTITUTE(F54,CHAR(10)," "))," ",""))+1)+IF(LEN(TRIM(SUBSTITUTE(G54,CHAR(10)," ")))=0,0,LEN(TRIM(SUBSTITUTE(G54,CHAR(10)," ")))-LEN(SUBSTITUTE(TRIM(SUBSTITUTE(G54,CHAR(10)," "))," ",""))+1) -> 5 | I54: =IF(ISNUMBER(FIND("[CLIENT",F54&G54)),"CLIENT INPUT",IF(ISNUMBER(FIND("[CONFIRM",F54&G54)),"CONFIRM",IF(ISNUMBER(FIND("[DEV",F54&G54)),"DEV NOTE","Ready"))) -> Ready | J54: Unique | K54: Questions and answers: tab 9.
A55: guntur | B55: /guntur/ | C55: 13 | D55: Related pages | E55: H2 + link list | F55: Related pages | G55: Flange supply across Andhra Pradesh · Vijayawada & Amaravati · Low-temperature flanges | H55: =IF(LEN(TRIM(SUBSTITUTE(F55,CHAR(10)," ")))=0,0,LEN(TRIM(SUBSTITUTE(F55,CHAR(10)," ")))-LEN(SUBSTITUTE(TRIM(SUBSTITUTE(F55,CHAR(10)," "))," ",""))+1)+IF(LEN(TRIM(SUBSTITUTE(G55,CHAR(10)," ")))=0,0,LEN(TRIM(SUBSTITUTE(G55,CHAR(10)," ")))-LEN(SUBSTITUTE(TRIM(SUBSTITUTE(G55,CHAR(10)," "))," ",""))+1) -> 14 | I55: =IF(ISNUMBER(FIND("[CLIENT",F55&G55)),"CLIENT INPUT",IF(ISNUMBER(FIND("[CONFIRM",F55&G55)),"CONFIRM",IF(ISNUMBER(FIND("[DEV",F55&G55)),"DEV NOTE","Ready"))) -> Ready | J55: Template | K55: Links: Flange supply across Andhra Pradesh → /market-area/andhra-pradesh/; Vijayawada & Amaravati → /vijayawada/; Low-temperature flanges → /products/flanges/high-temperature-cryogenic-flange/
A56: guntur | B56: /guntur/ | C56: 14 | D56: Final CTA | F56: =IF($F$8="","",$F$8) | G56: =$G$8 -> Send your requirement - we reply in writing. Fill the form or upload your BOQ; you get a line-by-line quote by email [CLIENT: reply time, e.g. within one working day]. No phone calls needed - everything is in writing. | H56: =IF(LEN(TRIM(SUBSTITUTE(F56,CHAR(10)," ")))=0,0,LEN(TRIM(SUBSTITUTE(F56,CHAR(10)," ")))-LEN(SUBSTITUTE(TRIM(SUBSTITUTE(F56,CHAR(10)," "))," ",""))+1)+IF(LEN(TRIM(SUBSTITUTE(G56,CHAR(10)," ")))=0,0,LEN(TRIM(SUBSTITUTE(G56,CHAR(10)," ")))-LEN(SUBSTITUTE(TRIM(SUBSTITUTE(G56,CHAR(10)," "))," ",""))+1) -> 39 | I56: =IF(ISNUMBER(FIND("[CLIENT",F56&G56)),"CLIENT INPUT",IF(ISNUMBER(FIND("[CONFIRM",F56&G56)),"CONFIRM",IF(ISNUMBER(FIND("[DEV",F56&G56)),"DEV NOTE","Ready"))) -> CLIENT INPUT | J56: Shared
A57: nellore | B57: /nellore/ | C57: 1 | D57: Breadcrumb | E57: Breadcrumb | G57: Home › Areas We Supply › Andhra Pradesh › Nellore | H57: =IF(LEN(TRIM(SUBSTITUTE(F57,CHAR(10)," ")))=0,0,LEN(TRIM(SUBSTITUTE(F57,CHAR(10)," ")))-LEN(SUBSTITUTE(TRIM(SUBSTITUTE(F57,CHAR(10)," "))," ",""))+1)+IF(LEN(TRIM(SUBSTITUTE(G57,CHAR(10)," ")))=0,0,LEN(TRIM(SUBSTITUTE(G57,CHAR(10)," ")))-LEN(SUBSTITUTE(TRIM(SUBSTITUTE(G57,CHAR(10)," "))," ",""))+1) -> 10 | I57: =IF(ISNUMBER(FIND("[CLIENT",F57&G57)),"CLIENT INPUT",IF(ISNUMBER(FIND("[CONFIRM",F57&G57)),"CONFIRM",IF(ISNUMBER(FIND("[DEV",F57&G57)),"DEV NOTE","Ready"))) -> Ready | J57: Template | K57: Slash-form links; see tab 12.
A58: nellore | B58: /nellore/ | C58: 2 | D58: Hero | E58: H1 | G58: Flange Supplier in Nellore, Krishnapatnam & Ramayapatnam | H58: =IF(LEN(TRIM(SUBSTITUTE(F58,CHAR(10)," ")))=0,0,LEN(TRIM(SUBSTITUTE(F58,CHAR(10)," ")))-LEN(SUBSTITUTE(TRIM(SUBSTITUTE(F58,CHAR(10)," "))," ",""))+1)+IF(LEN(TRIM(SUBSTITUTE(G58,CHAR(10)," ")))=0,0,LEN(TRIM(SUBSTITUTE(G58,CHAR(10)," ")))-LEN(SUBSTITUTE(TRIM(SUBSTITUTE(G58,CHAR(10)," "))," ",""))+1) -> 7 | I58: =IF(ISNUMBER(FIND("[CLIENT",F58&G58)),"CLIENT INPUT",IF(ISNUMBER(FIND("[CONFIRM",F58&G58)),"CONFIRM",IF(ISNUMBER(FIND("[DEV",F58&G58)),"DEV NOTE","Ready"))) -> Ready | J58: Unique | K58: The only <h1> on the page.
A59: nellore | B59: /nellore/ | C59: 2 | D59: Hero | E59: Subline (P under H1) | G59: Flanges manufacturer in Mumbai supplying Nellore's power, port, seafood and refinery-project buyers. | H59: =IF(LEN(TRIM(SUBSTITUTE(F59,CHAR(10)," ")))=0,0,LEN(TRIM(SUBSTITUTE(F59,CHAR(10)," ")))-LEN(SUBSTITUTE(TRIM(SUBSTITUTE(F59,CHAR(10)," "))," ",""))+1)+IF(LEN(TRIM(SUBSTITUTE(G59,CHAR(10)," ")))=0,0,LEN(TRIM(SUBSTITUTE(G59,CHAR(10)," ")))-LEN(SUBSTITUTE(TRIM(SUBSTITUTE(G59,CHAR(10)," "))," ",""))+1) -> 12 | I59: =IF(ISNUMBER(FIND("[CLIENT",F59&G59)),"CLIENT INPUT",IF(ISNUMBER(FIND("[CONFIRM",F59&G59)),"CONFIRM",IF(ISNUMBER(FIND("[DEV",F59&G59)),"DEV NOTE","Ready"))) -> Ready | J59: Unique
A60: nellore | B60: /nellore/ | C60: 2 | D60: Hero | E60: P (hero) + Form A | G60: Remax Forge is a flanges manufacturer in Mumbai supplying Nellore's power stations, the Krishnapatnam port area, seafood processors and the EPC supply chain forming around BPCL's planned refinery near Ramayapatnam. Send sizes, classes and grades - or your project line list - through the form and we reply in writing [CLIENT: reply time]. | H60: =IF(LEN(TRIM(SUBSTITUTE(F60,CHAR(10)," ")))=0,0,LEN(TRIM(SUBSTITUTE(F60,CHAR(10)," ")))-LEN(SUBSTITUTE(TRIM(SUBSTITUTE(F60,CHAR(10)," "))," ",""))+1)+IF(LEN(TRIM(SUBSTITUTE(G60,CHAR(10)," ")))=0,0,LEN(TRIM(SUBSTITUTE(G60,CHAR(10)," ")))-LEN(SUBSTITUTE(TRIM(SUBSTITUTE(G60,CHAR(10)," "))," ",""))+1) -> 53 | I60: =IF(ISNUMBER(FIND("[CLIENT",F60&G60)),"CLIENT INPUT",IF(ISNUMBER(FIND("[CONFIRM",F60&G60)),"CONFIRM",IF(ISNUMBER(FIND("[DEV",F60&G60)),"DEV NOTE","Ready"))) -> CLIENT INPUT | J60: Unique | K60: Form A (tab 10) beside/below this paragraph.
A61: nellore | B61: /nellore/ | C61: 3 | D61: Trust strip | F61: =IF($F$5="","",$F$5) | G61: =$G$5 -> GSTIN 27FFLPP0007K1ZA (verify on the GST portal) · GST-registered since 2020 · Proprietorship led by Vikas Purohit, CEO · Manufacturing unit in Mumbai, Maharashtra [CLIENT: locality] · [CLIENT: real certifications only, e.g. ISO 9001:2015 — delete if none] · Written quotes by email, no calls needed | H61: =IF(LEN(TRIM(SUBSTITUTE(F61,CHAR(10)," ")))=0,0,LEN(TRIM(SUBSTITUTE(F61,CHAR(10)," ")))-LEN(SUBSTITUTE(TRIM(SUBSTITUTE(F61,CHAR(10)," "))," ",""))+1)+IF(LEN(TRIM(SUBSTITUTE(G61,CHAR(10)," ")))=0,0,LEN(TRIM(SUBSTITUTE(G61,CHAR(10)," ")))-LEN(SUBSTITUTE(TRIM(SUBSTITUTE(G61,CHAR(10)," "))," ",""))+1) -> 46 | I61: =IF(ISNUMBER(FIND("[CLIENT",F61&G61)),"CLIENT INPUT",IF(ISNUMBER(FIND("[CONFIRM",F61&G61)),"CONFIRM",IF(ISNUMBER(FIND("[DEV",F61&G61)),"DEV NOTE","Ready"))) -> CLIENT INPUT | J61: Shared
A62: nellore | B62: /nellore/ | C62: 4 | D62: Local demand | E62: H2 + P (table: tab 8b) | F62: Nellore's flange demand, today and next | G62: Nellore's largest flange requirement is still ahead of it: a greenfield refinery-cum-petrochemical complex. Until construction peaks, power, port and seafood-processing plants drive steady maintenance and expansion demand. | H62: =IF(LEN(TRIM(SUBSTITUTE(F62,CHAR(10)," ")))=0,0,LEN(TRIM(SUBSTITUTE(F62,CHAR(10)," ")))-LEN(SUBSTITUTE(TRIM(SUBSTITUTE(F62,CHAR(10)," "))," ",""))+1)+IF(LEN(TRIM(SUBSTITUTE(G62,CHAR(10)," ")))=0,0,LEN(TRIM(SUBSTITUTE(G62,CHAR(10)," ")))-LEN(SUBSTITUTE(TRIM(SUBSTITUTE(G62,CHAR(10)," "))," ",""))+1) -> 33 | I62: =IF(ISNUMBER(FIND("[CLIENT",F62&G62)),"CLIENT INPUT",IF(ISNUMBER(FIND("[CONFIRM",F62&G62)),"CONFIRM",IF(ISNUMBER(FIND("[DEV",F62&G62)),"DEV NOTE","Ready"))) -> Ready | J62: Unique | K62: Table columns: Industry | Local sites and projects | Where flanges are used | What is usually specified.
A63: nellore | B63: /nellore/ | C63: 5 | D63: Materials guidance | E63: H2 + P | F63: Specifying flanges for a refinery-petrochemical project: an EPC buyer's checklist | G63: If you are pricing packages for the Ramayapatnam complex or a similar project, five lines on the enquiry decide whether a quote is usable: 1. Material specification and grade - for example ASTM A105, A350 LF2 Class 1, A182 F5, F9 or F316L - plus any supplementary requirements such as carbon-equivalent limits or hardness. 2. Service standard - NACE MR0103 / ISO 17945 for sour refining service, or none. 3. Design metal temperature - LPG, propylene and other auto-refrigerating services can chill piping well below -29 °C, which is where impact-tested A350 LF2 replaces A105. 4. Facing and finish - raised face with the specified finish, or ring-type joint grooves for higher classes. 5. Documentation - EN 10204 3.1 or 3.2 certificates, the inspection and test plan, the third-party inspection agency and marking requirements. Get these right at enquiry stage and the quote can go straight into your technical bid evaluation. | H63: =IF(LEN(TRIM(SUBSTITUTE(F63,CHAR(10)," ")))=0,0,LEN(TRIM(SUBSTITUTE(F63,CHAR(10)," ")))-LEN(SUBSTITUTE(TRIM(SUBSTITUTE(F63,CHAR(10)," "))," ",""))+1)+IF(LEN(TRIM(SUBSTITUTE(G63,CHAR(10)," ")))=0,0,LEN(TRIM(SUBSTITUTE(G63,CHAR(10)," ")))-LEN(SUBSTITUTE(TRIM(SUBSTITUTE(G63,CHAR(10)," "))," ",""))+1) -> 161 | I63: =IF(ISNUMBER(FIND("[CLIENT",F63&G63)),"CLIENT INPUT",IF(ISNUMBER(FIND("[CONFIRM",F63&G63)),"CONFIRM",IF(ISNUMBER(FIND("[DEV",F63&G63)),"DEV NOTE","Ready"))) -> Ready | J63: Unique | K63: Each line break = new paragraph. Lines '1.'-'5.' = ordered list.
A64: nellore | B64: /nellore/ | C64: 6 | D64: Product range | E64: H2 + P (table: tab 8b) | F64: Flange types we supply to Nellore | G64: For project packages we quote full ranges - MS/carbon steel, low-temperature carbon steel, stainless, alloy and duplex - across sizes and classes from one manufacturer, which simplifies vendor documentation. [CLIENT: confirm range limits and whether B16.47 large-bore is made in-house.] | H64: =IF(LEN(TRIM(SUBSTITUTE(F64,CHAR(10)," ")))=0,0,LEN(TRIM(SUBSTITUTE(F64,CHAR(10)," ")))-LEN(SUBSTITUTE(TRIM(SUBSTITUTE(F64,CHAR(10)," "))," ",""))+1)+IF(LEN(TRIM(SUBSTITUTE(G64,CHAR(10)," ")))=0,0,LEN(TRIM(SUBSTITUTE(G64,CHAR(10)," ")))-LEN(SUBSTITUTE(TRIM(SUBSTITUTE(G64,CHAR(10)," "))," ",""))+1) -> 46 | I64: =IF(ISNUMBER(FIND("[CLIENT",F64&G64)),"CLIENT INPUT",IF(ISNUMBER(FIND("[CONFIRM",F64&G64)),"CONFIRM",IF(ISNUMBER(FIND("[DEV",F64&G64)),"DEV NOTE","Ready"))) -> CLIENT INPUT | J64: Semi-unique | K64: Table columns: Flange type (link) | Typical use in Nellore.
A65: nellore | B65: /nellore/ | C65: 7 | D65: Manufacturing & QA | F65: =IF($F$6="","",$F$6) -> How every flange is made and checked | G65: =$G$6 -> Every flange starts as a certified billet or bar whose heat number follows it through cutting, forging, heat treatment where the material specification requires it, CNC machining and drilling, and final marking of grade, class, size and heat number. Before dispatch we check dimensions against the governing standard and [CLIENT: list only tests actually done in-house, e.g. PMI, hardness, ultrasonic], and issue material test certificates that tie each flange back to its heat. Buyer-nominated third-party inspection can witness any stage [CONFIRM]. | H65: =IF(LEN(TRIM(SUBSTITUTE(F65,CHAR(10)," ")))=0,0,LEN(TRIM(SUBSTITUTE(F65,CHAR(10)," ")))-LEN(SUBSTITUTE(TRIM(SUBSTITUTE(F65,CHAR(10)," "))," ",""))+1)+IF(LEN(TRIM(SUBSTITUTE(G65,CHAR(10)," ")))=0,0,LEN(TRIM(SUBSTITUTE(G65,CHAR(10)," ")))-LEN(SUBSTITUTE(TRIM(SUBSTITUTE(G65,CHAR(10)," "))," ",""))+1) -> 88 | I65: =IF(ISNUMBER(FIND("[CLIENT",F65&G65)),"CLIENT INPUT",IF(ISNUMBER(FIND("[CONFIRM",F65&G65)),"CONFIRM",IF(ISNUMBER(FIND("[DEV",F65&G65)),"DEV NOTE","Ready"))) -> CLIENT INPUT | J65: Shared
A66: nellore | B66: /nellore/ | C66: 8 | D66: Delivery & documents | E66: H2 + P | F66: Delivery to Nellore, Krishnapatnam and Ramayapatnam | G66: Road dispatch from Mumbai reaches Nellore city, Krishnapatnam and the Muthukur-Painampuram industrial area in typically [CLIENT: X-Y days]; Ramayapatnam sites are further up the coast [CLIENT: add days]. For project deliveries we can mark and pack by line or tag number so the site store can issue straight to the erection contractor [CONFIRM]. Invoices carry IGST as an inter-state supply, an e-way bill accompanies consignments above Rs 50,000, and material test certificates are traceable to the heat number stamped on each flange. | H66: =IF(LEN(TRIM(SUBSTITUTE(F66,CHAR(10)," ")))=0,0,LEN(TRIM(SUBSTITUTE(F66,CHAR(10)," ")))-LEN(SUBSTITUTE(TRIM(SUBSTITUTE(F66,CHAR(10)," "))," ",""))+1)+IF(LEN(TRIM(SUBSTITUTE(G66,CHAR(10)," ")))=0,0,LEN(TRIM(SUBSTITUTE(G66,CHAR(10)," ")))-LEN(SUBSTITUTE(TRIM(SUBSTITUTE(G66,CHAR(10)," "))," ",""))+1) -> 88 | I66: =IF(ISNUMBER(FIND("[CLIENT",F66&G66)),"CLIENT INPUT",IF(ISNUMBER(FIND("[CONFIRM",F66&G66)),"CONFIRM",IF(ISNUMBER(FIND("[DEV",F66&G66)),"DEV NOTE","Ready"))) -> CLIENT INPUT | J66: Unique
A67: nellore | B67: /nellore/ | C67: 9 | D67: Price guidance | E67: H2 + P | F67: How project flange packages are priced | G67: For project buying, price is driven by grade, class, facing, testing and documentation as much as by weight. [CLIENT: indicative Rs/kg bands for A105, LF2, F11/F22 and 316L.] Send the line list or MTO and we quote line by line, with freight shown separately [CONFIRM]. | H67: =IF(LEN(TRIM(SUBSTITUTE(F67,CHAR(10)," ")))=0,0,LEN(TRIM(SUBSTITUTE(F67,CHAR(10)," ")))-LEN(SUBSTITUTE(TRIM(SUBSTITUTE(F67,CHAR(10)," "))," ",""))+1)+IF(LEN(TRIM(SUBSTITUTE(G67,CHAR(10)," ")))=0,0,LEN(TRIM(SUBSTITUTE(G67,CHAR(10)," ")))-LEN(SUBSTITUTE(TRIM(SUBSTITUTE(G67,CHAR(10)," "))," ",""))+1) -> 51 | I67: =IF(ISNUMBER(FIND("[CLIENT",F67&G67)),"CLIENT INPUT",IF(ISNUMBER(FIND("[CONFIRM",F67&G67)),"CONFIRM",IF(ISNUMBER(FIND("[DEV",F67&G67)),"DEV NOTE","Ready"))) -> CLIENT INPUT | J67: Unique | K67: Add the dated Rs/kg band table here once the client supplies it (tab 15 I-26).
A68: nellore | B68: /nellore/ | C68: 10 | D68: Areas served | E68: H2 + P | F68: Areas we deliver around Nellore | G68: We deliver across Nellore city, the Krishnapatnam port and power belt, Muthukur and Painampuram, Kavali and the coastal aquaculture clusters, with Ramayapatnam to the north and Sri City to the south. [CLIENT: adjust.] | H68: =IF(LEN(TRIM(SUBSTITUTE(F68,CHAR(10)," ")))=0,0,LEN(TRIM(SUBSTITUTE(F68,CHAR(10)," ")))-LEN(SUBSTITUTE(TRIM(SUBSTITUTE(F68,CHAR(10)," "))," ",""))+1)+IF(LEN(TRIM(SUBSTITUTE(G68,CHAR(10)," ")))=0,0,LEN(TRIM(SUBSTITUTE(G68,CHAR(10)," ")))-LEN(SUBSTITUTE(TRIM(SUBSTITUTE(G68,CHAR(10)," "))," ",""))+1) -> 38 | I68: =IF(ISNUMBER(FIND("[CLIENT",F68&G68)),"CLIENT INPUT",IF(ISNUMBER(FIND("[CONFIRM",F68&G68)),"CONFIRM",IF(ISNUMBER(FIND("[DEV",F68&G68)),"DEV NOTE","Ready"))) -> CLIENT INPUT | J68: Unique | K68: Plain text, no locality links.
A69: nellore | B69: /nellore/ | C69: 11 | D69: Request a quote | F69: =IF($F$7="","",$F$7) -> Request a written quote | G69: =$G$7 -> A quote-ready enquiry lists: flange type · nominal size (NPS or DN) · pressure class or PN · facing (RF, FF or RTJ) · material specification and grade · bore or schedule for weld neck flanges · quantity · delivery location · testing and certificate needs (NACE, impact test, EN 10204 3.1/3.2, third-party inspection). Upload a BOQ or drawing and we will read it for you. | H69: =IF(LEN(TRIM(SUBSTITUTE(F69,CHAR(10)," ")))=0,0,LEN(TRIM(SUBSTITUTE(F69,CHAR(10)," ")))-LEN(SUBSTITUTE(TRIM(SUBSTITUTE(F69,CHAR(10)," "))," ",""))+1)+IF(LEN(TRIM(SUBSTITUTE(G69,CHAR(10)," ")))=0,0,LEN(TRIM(SUBSTITUTE(G69,CHAR(10)," ")))-LEN(SUBSTITUTE(TRIM(SUBSTITUTE(G69,CHAR(10)," "))," ",""))+1) -> 70 | I69: =IF(ISNUMBER(FIND("[CLIENT",F69&G69)),"CLIENT INPUT",IF(ISNUMBER(FIND("[CONFIRM",F69&G69)),"CONFIRM",IF(ISNUMBER(FIND("[DEV",F69&G69)),"DEV NOTE","Ready"))) -> Ready | J69: Shared
A70: nellore | B70: /nellore/ | C70: 12 | D70: FAQs | E70: H2 (Q&A in tab 9) | F70: Flange questions from Nellore buyers | H70: =IF(LEN(TRIM(SUBSTITUTE(F70,CHAR(10)," ")))=0,0,LEN(TRIM(SUBSTITUTE(F70,CHAR(10)," ")))-LEN(SUBSTITUTE(TRIM(SUBSTITUTE(F70,CHAR(10)," "))," ",""))+1)+IF(LEN(TRIM(SUBSTITUTE(G70,CHAR(10)," ")))=0,0,LEN(TRIM(SUBSTITUTE(G70,CHAR(10)," ")))-LEN(SUBSTITUTE(TRIM(SUBSTITUTE(G70,CHAR(10)," "))," ",""))+1) -> 5 | I70: =IF(ISNUMBER(FIND("[CLIENT",F70&G70)),"CLIENT INPUT",IF(ISNUMBER(FIND("[CONFIRM",F70&G70)),"CONFIRM",IF(ISNUMBER(FIND("[DEV",F70&G70)),"DEV NOTE","Ready"))) -> Ready | J70: Unique | K70: Questions and answers: tab 9.
A71: nellore | B71: /nellore/ | C71: 13 | D71: Related pages | E71: H2 + link list | F71: Related pages | G71: Flange supply across Andhra Pradesh · Visakhapatnam · Sour-service NACE flanges · Low-temperature flanges · Flanges for oil & gas | H71: =IF(LEN(TRIM(SUBSTITUTE(F71,CHAR(10)," ")))=0,0,LEN(TRIM(SUBSTITUTE(F71,CHAR(10)," ")))-LEN(SUBSTITUTE(TRIM(SUBSTITUTE(F71,CHAR(10)," "))," ",""))+1)+IF(LEN(TRIM(SUBSTITUTE(G71,CHAR(10)," ")))=0,0,LEN(TRIM(SUBSTITUTE(G71,CHAR(10)," ")))-LEN(SUBSTITUTE(TRIM(SUBSTITUTE(G71,CHAR(10)," "))," ",""))+1) -> 22 | I71: =IF(ISNUMBER(FIND("[CLIENT",F71&G71)),"CLIENT INPUT",IF(ISNUMBER(FIND("[CONFIRM",F71&G71)),"CONFIRM",IF(ISNUMBER(FIND("[DEV",F71&G71)),"DEV NOTE","Ready"))) -> Ready | J71: Template | K71: Links: Flange supply across Andhra Pradesh → /market-area/andhra-pradesh/; Visakhapatnam → /visakhapatnam/; Sour-service NACE flanges → /products/flanges/sour-service-nace-flange/; Low-temperature flanges → /products/flanges/high-temperature-cryogenic-flange/; Flanges for oil & gas → /industries/oil-and-gas/
A72: nellore | B72: /nellore/ | C72: 14 | D72: Final CTA | F72: =IF($F$8="","",$F$8) | G72: =$G$8 -> Send your requirement - we reply in writing. Fill the form or upload your BOQ; you get a line-by-line quote by email [CLIENT: reply time, e.g. within one working day]. No phone calls needed - everything is in writing. | H72: =IF(LEN(TRIM(SUBSTITUTE(F72,CHAR(10)," ")))=0,0,LEN(TRIM(SUBSTITUTE(F72,CHAR(10)," ")))-LEN(SUBSTITUTE(TRIM(SUBSTITUTE(F72,CHAR(10)," "))," ",""))+1)+IF(LEN(TRIM(SUBSTITUTE(G72,CHAR(10)," ")))=0,0,LEN(TRIM(SUBSTITUTE(G72,CHAR(10)," ")))-LEN(SUBSTITUTE(TRIM(SUBSTITUTE(G72,CHAR(10)," "))," ",""))+1) -> 39 | I72: =IF(ISNUMBER(FIND("[CLIENT",F72&G72)),"CLIENT INPUT",IF(ISNUMBER(FIND("[CONFIRM",F72&G72)),"CONFIRM",IF(ISNUMBER(FIND("[DEV",F72&G72)),"DEV NOTE","Ready"))) -> CLIENT INPUT | J72: Shared
A73: kurnool | B73: /kurnool/ | C73: 1 | D73: Breadcrumb | E73: Breadcrumb | G73: Home › Areas We Supply › Andhra Pradesh › Kurnool | H73: =IF(LEN(TRIM(SUBSTITUTE(F73,CHAR(10)," ")))=0,0,LEN(TRIM(SUBSTITUTE(F73,CHAR(10)," ")))-LEN(SUBSTITUTE(TRIM(SUBSTITUTE(F73,CHAR(10)," "))," ",""))+1)+IF(LEN(TRIM(SUBSTITUTE(G73,CHAR(10)," ")))=0,0,LEN(TRIM(SUBSTITUTE(G73,CHAR(10)," ")))-LEN(SUBSTITUTE(TRIM(SUBSTITUTE(G73,CHAR(10)," "))," ",""))+1) -> 10 | I73: =IF(ISNUMBER(FIND("[CLIENT",F73&G73)),"CLIENT INPUT",IF(ISNUMBER(FIND("[CONFIRM",F73&G73)),"CONFIRM",IF(ISNUMBER(FIND("[DEV",F73&G73)),"DEV NOTE","Ready"))) -> Ready | J73: Template | K73: Slash-form links; see tab 12.
A74: kurnool | B74: /kurnool/ | C74: 2 | D74: Hero | E74: H1 | G74: Flange Supplier in Kurnool | H74: =IF(LEN(TRIM(SUBSTITUTE(F74,CHAR(10)," ")))=0,0,LEN(TRIM(SUBSTITUTE(F74,CHAR(10)," ")))-LEN(SUBSTITUTE(TRIM(SUBSTITUTE(F74,CHAR(10)," "))," ",""))+1)+IF(LEN(TRIM(SUBSTITUTE(G74,CHAR(10)," ")))=0,0,LEN(TRIM(SUBSTITUTE(G74,CHAR(10)," ")))-LEN(SUBSTITUTE(TRIM(SUBSTITUTE(G74,CHAR(10)," "))," ",""))+1) -> 4 | I74: =IF(ISNUMBER(FIND("[CLIENT",F74&G74)),"CLIENT INPUT",IF(ISNUMBER(FIND("[CONFIRM",F74&G74)),"CONFIRM",IF(ISNUMBER(FIND("[DEV",F74&G74)),"DEV NOTE","Ready"))) -> Ready | J74: Unique | K74: The only <h1> on the page.
A75: kurnool | B75: /kurnool/ | C75: 2 | D75: Hero | E75: Subline (P under H1) | G75: Flanges manufacturer in Mumbai supplying pumped-storage, irrigation, renewable and industrial projects around Kurnool. | H75: =IF(LEN(TRIM(SUBSTITUTE(F75,CHAR(10)," ")))=0,0,LEN(TRIM(SUBSTITUTE(F75,CHAR(10)," ")))-LEN(SUBSTITUTE(TRIM(SUBSTITUTE(F75,CHAR(10)," "))," ",""))+1)+IF(LEN(TRIM(SUBSTITUTE(G75,CHAR(10)," ")))=0,0,LEN(TRIM(SUBSTITUTE(G75,CHAR(10)," ")))-LEN(SUBSTITUTE(TRIM(SUBSTITUTE(G75,CHAR(10)," "))," ",""))+1) -> 13 | I75: =IF(ISNUMBER(FIND("[CLIENT",F75&G75)),"CLIENT INPUT",IF(ISNUMBER(FIND("[CONFIRM",F75&G75)),"CONFIRM",IF(ISNUMBER(FIND("[DEV",F75&G75)),"DEV NOTE","Ready"))) -> Ready | J75: Unique
A76: kurnool | B76: /kurnool/ | C76: 2 | D76: Hero | E76: P (hero) + Form A | G76: Remax Forge is a flanges manufacturer in Mumbai supplying Kurnool's pumped-storage and renewable projects, lift-irrigation schemes, cement and mineral plants and the Orvakal industrial area. Send your sizes, drilling standard and material through the form - large-bore and custom-drilled flanges included [CLIENT: confirm] - and we reply in writing [CLIENT: reply time]. | H76: =IF(LEN(TRIM(SUBSTITUTE(F76,CHAR(10)," ")))=0,0,LEN(TRIM(SUBSTITUTE(F76,CHAR(10)," ")))-LEN(SUBSTITUTE(TRIM(SUBSTITUTE(F76,CHAR(10)," "))," ",""))+1)+IF(LEN(TRIM(SUBSTITUTE(G76,CHAR(10)," ")))=0,0,LEN(TRIM(SUBSTITUTE(G76,CHAR(10)," ")))-LEN(SUBSTITUTE(TRIM(SUBSTITUTE(G76,CHAR(10)," "))," ",""))+1) -> 52 | I76: =IF(ISNUMBER(FIND("[CLIENT",F76&G76)),"CLIENT INPUT",IF(ISNUMBER(FIND("[CONFIRM",F76&G76)),"CONFIRM",IF(ISNUMBER(FIND("[DEV",F76&G76)),"DEV NOTE","Ready"))) -> CLIENT INPUT | J76: Unique | K76: Form A (tab 10) beside/below this paragraph.
A77: kurnool | B77: /kurnool/ | C77: 3 | D77: Trust strip | F77: =IF($F$5="","",$F$5) | G77: =$G$5 -> GSTIN 27FFLPP0007K1ZA (verify on the GST portal) · GST-registered since 2020 · Proprietorship led by Vikas Purohit, CEO · Manufacturing unit in Mumbai, Maharashtra [CLIENT: locality] · [CLIENT: real certifications only, e.g. ISO 9001:2015 — delete if none] · Written quotes by email, no calls needed | H77: =IF(LEN(TRIM(SUBSTITUTE(F77,CHAR(10)," ")))=0,0,LEN(TRIM(SUBSTITUTE(F77,CHAR(10)," ")))-LEN(SUBSTITUTE(TRIM(SUBSTITUTE(F77,CHAR(10)," "))," ",""))+1)+IF(LEN(TRIM(SUBSTITUTE(G77,CHAR(10)," ")))=0,0,LEN(TRIM(SUBSTITUTE(G77,CHAR(10)," ")))-LEN(SUBSTITUTE(TRIM(SUBSTITUTE(G77,CHAR(10)," "))," ",""))+1) -> 46 | I77: =IF(ISNUMBER(FIND("[CLIENT",F77&G77)),"CLIENT INPUT",IF(ISNUMBER(FIND("[CONFIRM",F77&G77)),"CONFIRM",IF(ISNUMBER(FIND("[DEV",F77&G77)),"DEV NOTE","Ready"))) -> CLIENT INPUT | J77: Shared
A78: kurnool | B78: /kurnool/ | C78: 4 | D78: Local demand | E78: H2 + P (table: tab 8b) | F78: Kurnool's flange demand is mostly water | G78: Pumped storage, lift irrigation and pipelines dominate here, which means large diameters, lower pressures and drilling standards that must match imported valves and pumps. | H78: =IF(LEN(TRIM(SUBSTITUTE(F78,CHAR(10)," ")))=0,0,LEN(TRIM(SUBSTITUTE(F78,CHAR(10)," ")))-LEN(SUBSTITUTE(TRIM(SUBSTITUTE(F78,CHAR(10)," "))," ",""))+1)+IF(LEN(TRIM(SUBSTITUTE(G78,CHAR(10)," ")))=0,0,LEN(TRIM(SUBSTITUTE(G78,CHAR(10)," ")))-LEN(SUBSTITUTE(TRIM(SUBSTITUTE(G78,CHAR(10)," "))," ",""))+1) -> 30 | I78: =IF(ISNUMBER(FIND("[CLIENT",F78&G78)),"CLIENT INPUT",IF(ISNUMBER(FIND("[CONFIRM",F78&G78)),"CONFIRM",IF(ISNUMBER(FIND("[DEV",F78&G78)),"DEV NOTE","Ready"))) -> Ready | J78: Unique | K78: Table columns: Industry | Local sites and projects | Where flanges are used | What is usually specified.
A79: kurnool | B79: /kurnool/ | C79: 5 | D79: Materials guidance | E79: H2 + P | F79: Plate flange or forged flange? Choosing for Kurnool's water projects | G79: Large water headers use a lot of flanges, so the construction method matters for cost. Plate flanges are machined from steel plate and are economical for low-pressure water service at large diameters - typical of lift-irrigation and pipeline work at PN10/PN16. Forged flanges have a worked grain structure and are the choice where the design code, pressure class or cyclic loading calls for them, such as pump discharge branches on high-head equipment and pumped-storage auxiliaries at higher classes. [CLIENT: confirm which construction Remax offers at each size.] Whichever you choose, specify the drilling standard - ASME B16.5/B16.47, AWWA C207, EN 1092-1 or IS 6392 - to match the valve or pump, and state the coating for buried or wet-well service. | H79: =IF(LEN(TRIM(SUBSTITUTE(F79,CHAR(10)," ")))=0,0,LEN(TRIM(SUBSTITUTE(F79,CHAR(10)," ")))-LEN(SUBSTITUTE(TRIM(SUBSTITUTE(F79,CHAR(10)," "))," ",""))+1)+IF(LEN(TRIM(SUBSTITUTE(G79,CHAR(10)," ")))=0,0,LEN(TRIM(SUBSTITUTE(G79,CHAR(10)," ")))-LEN(SUBSTITUTE(TRIM(SUBSTITUTE(G79,CHAR(10)," "))," ",""))+1) -> 130 | I79: =IF(ISNUMBER(FIND("[CLIENT",F79&G79)),"CLIENT INPUT",IF(ISNUMBER(FIND("[CONFIRM",F79&G79)),"CONFIRM",IF(ISNUMBER(FIND("[DEV",F79&G79)),"DEV NOTE","Ready"))) -> CLIENT INPUT | J79: Unique | K79: Each line break = new paragraph.
A80: kurnool | B80: /kurnool/ | C80: 6 | D80: Product range | E80: H2 + P (table: tab 8b) | F80: Flange types we supply to Kurnool | G80: Standard MS (A105) and SS ranges ship from Mumbai; large-bore and custom-drilled flanges are made to order [CLIENT: confirm maximum diameter]. | H80: =IF(LEN(TRIM(SUBSTITUTE(F80,CHAR(10)," ")))=0,0,LEN(TRIM(SUBSTITUTE(F80,CHAR(10)," ")))-LEN(SUBSTITUTE(TRIM(SUBSTITUTE(F80,CHAR(10)," "))," ",""))+1)+IF(LEN(TRIM(SUBSTITUTE(G80,CHAR(10)," ")))=0,0,LEN(TRIM(SUBSTITUTE(G80,CHAR(10)," ")))-LEN(SUBSTITUTE(TRIM(SUBSTITUTE(G80,CHAR(10)," "))," ",""))+1) -> 27 | I80: =IF(ISNUMBER(FIND("[CLIENT",F80&G80)),"CLIENT INPUT",IF(ISNUMBER(FIND("[CONFIRM",F80&G80)),"CONFIRM",IF(ISNUMBER(FIND("[DEV",F80&G80)),"DEV NOTE","Ready"))) -> CLIENT INPUT | J80: Semi-unique | K80: Table columns: Flange type (link) | Typical use in Kurnool.
A81: kurnool | B81: /kurnool/ | C81: 7 | D81: Manufacturing & QA | F81: =IF($F$6="","",$F$6) -> How every flange is made and checked | G81: =$G$6 -> Every flange starts as a certified billet or bar whose heat number follows it through cutting, forging, heat treatment where the material specification requires it, CNC machining and drilling, and final marking of grade, class, size and heat number. Before dispatch we check dimensions against the governing standard and [CLIENT: list only tests actually done in-house, e.g. PMI, hardness, ultrasonic], and issue material test certificates that tie each flange back to its heat. Buyer-nominated third-party inspection can witness any stage [CONFIRM]. | H81: =IF(LEN(TRIM(SUBSTITUTE(F81,CHAR(10)," ")))=0,0,LEN(TRIM(SUBSTITUTE(F81,CHAR(10)," ")))-LEN(SUBSTITUTE(TRIM(SUBSTITUTE(F81,CHAR(10)," "))," ",""))+1)+IF(LEN(TRIM(SUBSTITUTE(G81,CHAR(10)," ")))=0,0,LEN(TRIM(SUBSTITUTE(G81,CHAR(10)," ")))-LEN(SUBSTITUTE(TRIM(SUBSTITUTE(G81,CHAR(10)," "))," ",""))+1) -> 88 | I81: =IF(ISNUMBER(FIND("[CLIENT",F81&G81)),"CLIENT INPUT",IF(ISNUMBER(FIND("[CONFIRM",F81&G81)),"CONFIRM",IF(ISNUMBER(FIND("[DEV",F81&G81)),"DEV NOTE","Ready"))) -> CLIENT INPUT | J81: Shared
A82: kurnool | B82: /kurnool/ | C82: 8 | D82: Delivery & documents | E82: H2 + P | F82: Delivery to Kurnool, Orvakal and project sites | G82: Road dispatch from Mumbai reaches Kurnool city and Orvakal in typically [CLIENT: X-Y days]; project sites in Panyam and other mandals may need a site contact and access details for heavy or long loads, which you can add in the form. Large-diameter flanges are palletised or crated to protect the faces in transit [CONFIRM]. Invoices carry IGST; an e-way bill travels with consignments above Rs 50,000; certificates match the heat numbers on each flange. | H82: =IF(LEN(TRIM(SUBSTITUTE(F82,CHAR(10)," ")))=0,0,LEN(TRIM(SUBSTITUTE(F82,CHAR(10)," ")))-LEN(SUBSTITUTE(TRIM(SUBSTITUTE(F82,CHAR(10)," "))," ",""))+1)+IF(LEN(TRIM(SUBSTITUTE(G82,CHAR(10)," ")))=0,0,LEN(TRIM(SUBSTITUTE(G82,CHAR(10)," ")))-LEN(SUBSTITUTE(TRIM(SUBSTITUTE(G82,CHAR(10)," "))," ",""))+1) -> 81 | I82: =IF(ISNUMBER(FIND("[CLIENT",F82&G82)),"CLIENT INPUT",IF(ISNUMBER(FIND("[CONFIRM",F82&G82)),"CONFIRM",IF(ISNUMBER(FIND("[DEV",F82&G82)),"DEV NOTE","Ready"))) -> CLIENT INPUT | J82: Unique
A83: kurnool | B83: /kurnool/ | C83: 9 | D83: Price guidance | E83: H2 + P | F83: How large-bore water flanges are priced | G83: Large water flanges are priced mainly by weight and drilling; pumped-storage auxiliaries by grade and class. [CLIENT: indicative Rs/kg bands for plate and forged.] Upload your BOQ or drawings for a line-by-line quote. | H83: =IF(LEN(TRIM(SUBSTITUTE(F83,CHAR(10)," ")))=0,0,LEN(TRIM(SUBSTITUTE(F83,CHAR(10)," ")))-LEN(SUBSTITUTE(TRIM(SUBSTITUTE(F83,CHAR(10)," "))," ",""))+1)+IF(LEN(TRIM(SUBSTITUTE(G83,CHAR(10)," ")))=0,0,LEN(TRIM(SUBSTITUTE(G83,CHAR(10)," ")))-LEN(SUBSTITUTE(TRIM(SUBSTITUTE(G83,CHAR(10)," "))," ",""))+1) -> 39 | I83: =IF(ISNUMBER(FIND("[CLIENT",F83&G83)),"CLIENT INPUT",IF(ISNUMBER(FIND("[CONFIRM",F83&G83)),"CONFIRM",IF(ISNUMBER(FIND("[DEV",F83&G83)),"DEV NOTE","Ready"))) -> CLIENT INPUT | J83: Unique | K83: Add the dated Rs/kg band table here once the client supplies it (tab 15 I-26).
A84: kurnool | B84: /kurnool/ | C84: 10 | D84: Areas served | E84: H2 + P | F84: Areas we deliver around Kurnool | G84: We deliver across Kurnool city, the Orvakal industrial area, Panyam and Nandyal, and cement and mineral sites in the Kurnool-Nandyal belt. [CLIENT: adjust.] For the rest of Andhra Pradesh see our state page. | H84: =IF(LEN(TRIM(SUBSTITUTE(F84,CHAR(10)," ")))=0,0,LEN(TRIM(SUBSTITUTE(F84,CHAR(10)," ")))-LEN(SUBSTITUTE(TRIM(SUBSTITUTE(F84,CHAR(10)," "))," ",""))+1)+IF(LEN(TRIM(SUBSTITUTE(G84,CHAR(10)," ")))=0,0,LEN(TRIM(SUBSTITUTE(G84,CHAR(10)," ")))-LEN(SUBSTITUTE(TRIM(SUBSTITUTE(G84,CHAR(10)," "))," ",""))+1) -> 38 | I84: =IF(ISNUMBER(FIND("[CLIENT",F84&G84)),"CLIENT INPUT",IF(ISNUMBER(FIND("[CONFIRM",F84&G84)),"CONFIRM",IF(ISNUMBER(FIND("[DEV",F84&G84)),"DEV NOTE","Ready"))) -> CLIENT INPUT | J84: Unique | K84: Plain text, no locality links.
A85: kurnool | B85: /kurnool/ | C85: 11 | D85: Request a quote | F85: =IF($F$7="","",$F$7) -> Request a written quote | G85: =$G$7 -> A quote-ready enquiry lists: flange type · nominal size (NPS or DN) · pressure class or PN · facing (RF, FF or RTJ) · material specification and grade · bore or schedule for weld neck flanges · quantity · delivery location · testing and certificate needs (NACE, impact test, EN 10204 3.1/3.2, third-party inspection). Upload a BOQ or drawing and we will read it for you. | H85: =IF(LEN(TRIM(SUBSTITUTE(F85,CHAR(10)," ")))=0,0,LEN(TRIM(SUBSTITUTE(F85,CHAR(10)," ")))-LEN(SUBSTITUTE(TRIM(SUBSTITUTE(F85,CHAR(10)," "))," ",""))+1)+IF(LEN(TRIM(SUBSTITUTE(G85,CHAR(10)," ")))=0,0,LEN(TRIM(SUBSTITUTE(G85,CHAR(10)," ")))-LEN(SUBSTITUTE(TRIM(SUBSTITUTE(G85,CHAR(10)," "))," ",""))+1) -> 70 | I85: =IF(ISNUMBER(FIND("[CLIENT",F85&G85)),"CLIENT INPUT",IF(ISNUMBER(FIND("[CONFIRM",F85&G85)),"CONFIRM",IF(ISNUMBER(FIND("[DEV",F85&G85)),"DEV NOTE","Ready"))) -> Ready | J85: Shared
A86: kurnool | B86: /kurnool/ | C86: 12 | D86: FAQs | E86: H2 (Q&A in tab 9) | F86: Flange questions from Kurnool buyers | H86: =IF(LEN(TRIM(SUBSTITUTE(F86,CHAR(10)," ")))=0,0,LEN(TRIM(SUBSTITUTE(F86,CHAR(10)," ")))-LEN(SUBSTITUTE(TRIM(SUBSTITUTE(F86,CHAR(10)," "))," ",""))+1)+IF(LEN(TRIM(SUBSTITUTE(G86,CHAR(10)," ")))=0,0,LEN(TRIM(SUBSTITUTE(G86,CHAR(10)," ")))-LEN(SUBSTITUTE(TRIM(SUBSTITUTE(G86,CHAR(10)," "))," ",""))+1) -> 5 | I86: =IF(ISNUMBER(FIND("[CLIENT",F86&G86)),"CLIENT INPUT",IF(ISNUMBER(FIND("[CONFIRM",F86&G86)),"CONFIRM",IF(ISNUMBER(FIND("[DEV",F86&G86)),"DEV NOTE","Ready"))) -> Ready | J86: Unique | K86: Questions and answers: tab 9.
A87: kurnool | B87: /kurnool/ | C87: 13 | D87: Related pages | E87: H2 + link list | F87: Related pages | G87: Flange supply across Andhra Pradesh · Pipe flanges guide · Vijayawada (Class 150 vs PN16 drilling) | H87: =IF(LEN(TRIM(SUBSTITUTE(F87,CHAR(10)," ")))=0,0,LEN(TRIM(SUBSTITUTE(F87,CHAR(10)," ")))-LEN(SUBSTITUTE(TRIM(SUBSTITUTE(F87,CHAR(10)," "))," ",""))+1)+IF(LEN(TRIM(SUBSTITUTE(G87,CHAR(10)," ")))=0,0,LEN(TRIM(SUBSTITUTE(G87,CHAR(10)," ")))-LEN(SUBSTITUTE(TRIM(SUBSTITUTE(G87,CHAR(10)," "))," ",""))+1) -> 18 | I87: =IF(ISNUMBER(FIND("[CLIENT",F87&G87)),"CLIENT INPUT",IF(ISNUMBER(FIND("[CONFIRM",F87&G87)),"CONFIRM",IF(ISNUMBER(FIND("[DEV",F87&G87)),"DEV NOTE","Ready"))) -> Ready | J87: Template | K87: Links: Flange supply across Andhra Pradesh → /market-area/andhra-pradesh/; Pipe flanges guide → /blogs/pipe-flanges-guide/; Vijayawada (Class 150 vs PN16 drilling) → /vijayawada/
A88: kurnool | B88: /kurnool/ | C88: 14 | D88: Final CTA | F88: =IF($F$8="","",$F$8) | G88: =$G$8 -> Send your requirement - we reply in writing. Fill the form or upload your BOQ; you get a line-by-line quote by email [CLIENT: reply time, e.g. within one working day]. No phone calls needed - everything is in writing. | H88: =IF(LEN(TRIM(SUBSTITUTE(F88,CHAR(10)," ")))=0,0,LEN(TRIM(SUBSTITUTE(F88,CHAR(10)," ")))-LEN(SUBSTITUTE(TRIM(SUBSTITUTE(F88,CHAR(10)," "))," ",""))+1)+IF(LEN(TRIM(SUBSTITUTE(G88,CHAR(10)," ")))=0,0,LEN(TRIM(SUBSTITUTE(G88,CHAR(10)," ")))-LEN(SUBSTITUTE(TRIM(SUBSTITUTE(G88,CHAR(10)," "))," ",""))+1) -> 39 | I88: =IF(ISNUMBER(FIND("[CLIENT",F88&G88)),"CLIENT INPUT",IF(ISNUMBER(FIND("[CONFIRM",F88&G88)),"CONFIRM",IF(ISNUMBER(FIND("[DEV",F88&G88)),"DEV NOTE","Ready"))) -> CLIENT INPUT | J88: Shared
A89: itanagar | B89: /itanagar/ | C89: 1 | D89: Breadcrumb | E89: Breadcrumb | G89: Home › Areas We Supply › Arunachal Pradesh › Itanagar & Naharlagun | H89: =IF(LEN(TRIM(SUBSTITUTE(F89,CHAR(10)," ")))=0,0,LEN(TRIM(SUBSTITUTE(F89,CHAR(10)," ")))-LEN(SUBSTITUTE(TRIM(SUBSTITUTE(F89,CHAR(10)," "))," ",""))+1)+IF(LEN(TRIM(SUBSTITUTE(G89,CHAR(10)," ")))=0,0,LEN(TRIM(SUBSTITUTE(G89,CHAR(10)," ")))-LEN(SUBSTITUTE(TRIM(SUBSTITUTE(G89,CHAR(10)," "))," ",""))+1) -> 12 | I89: =IF(ISNUMBER(FIND("[CLIENT",F89&G89)),"CLIENT INPUT",IF(ISNUMBER(FIND("[CONFIRM",F89&G89)),"CONFIRM",IF(ISNUMBER(FIND("[DEV",F89&G89)),"DEV NOTE","Ready"))) -> Ready | J89: Template | K89: Slash-form links; see tab 12.
A90: itanagar | B90: /itanagar/ | C90: 2 | D90: Hero | E90: H1 | G90: Flange Supplier in Itanagar & Naharlagun (Capital Region) | H90: =IF(LEN(TRIM(SUBSTITUTE(F90,CHAR(10)," ")))=0,0,LEN(TRIM(SUBSTITUTE(F90,CHAR(10)," ")))-LEN(SUBSTITUTE(TRIM(SUBSTITUTE(F90,CHAR(10)," "))," ",""))+1)+IF(LEN(TRIM(SUBSTITUTE(G90,CHAR(10)," ")))=0,0,LEN(TRIM(SUBSTITUTE(G90,CHAR(10)," ")))-LEN(SUBSTITUTE(TRIM(SUBSTITUTE(G90,CHAR(10)," "))," ",""))+1) -> 8 | I90: =IF(ISNUMBER(FIND("[CLIENT",F90&G90)),"CLIENT INPUT",IF(ISNUMBER(FIND("[CONFIRM",F90&G90)),"CONFIRM",IF(ISNUMBER(FIND("[DEV",F90&G90)),"DEV NOTE","Ready"))) -> Ready | J90: Unique | K90: The only <h1> on the page.
A91: itanagar | B91: /itanagar/ | C91: 2 | D91: Hero | E91: Subline (P under H1) | G91: Flanges manufacturer in Mumbai supplying water-supply, building and hydropower work in the Itanagar capital region. | H91: =IF(LEN(TRIM(SUBSTITUTE(F91,CHAR(10)," ")))=0,0,LEN(TRIM(SUBSTITUTE(F91,CHAR(10)," ")))-LEN(SUBSTITUTE(TRIM(SUBSTITUTE(F91,CHAR(10)," "))," ",""))+1)+IF(LEN(TRIM(SUBSTITUTE(G91,CHAR(10)," ")))=0,0,LEN(TRIM(SUBSTITUTE(G91,CHAR(10)," ")))-LEN(SUBSTITUTE(TRIM(SUBSTITUTE(G91,CHAR(10)," "))," ",""))+1) -> 15 | I91: =IF(ISNUMBER(FIND("[CLIENT",F91&G91)),"CLIENT INPUT",IF(ISNUMBER(FIND("[CONFIRM",F91&G91)),"CONFIRM",IF(ISNUMBER(FIND("[DEV",F91&G91)),"DEV NOTE","Ready"))) -> Ready | J91: Unique
A92: itanagar | B92: /itanagar/ | C92: 2 | D92: Hero | E92: P (hero) + Form A | G92: Remax Forge is a flanges manufacturer in Mumbai supplying contractors, departments and plant operators across the Itanagar capital region - Itanagar, Naharlagun, Nirjuli and Doimukh. Tell us what you need in the form and we reply in writing with price, dispatch date and a realistic delivery estimate for Arunachal Pradesh [CLIENT: reply time]. | H92: =IF(LEN(TRIM(SUBSTITUTE(F92,CHAR(10)," ")))=0,0,LEN(TRIM(SUBSTITUTE(F92,CHAR(10)," ")))-LEN(SUBSTITUTE(TRIM(SUBSTITUTE(F92,CHAR(10)," "))," ",""))+1)+IF(LEN(TRIM(SUBSTITUTE(G92,CHAR(10)," ")))=0,0,LEN(TRIM(SUBSTITUTE(G92,CHAR(10)," ")))-LEN(SUBSTITUTE(TRIM(SUBSTITUTE(G92,CHAR(10)," "))," ",""))+1) -> 53 | I92: =IF(ISNUMBER(FIND("[CLIENT",F92&G92)),"CLIENT INPUT",IF(ISNUMBER(FIND("[CONFIRM",F92&G92)),"CONFIRM",IF(ISNUMBER(FIND("[DEV",F92&G92)),"DEV NOTE","Ready"))) -> CLIENT INPUT | J92: Unique | K92: Form A (tab 10) beside/below this paragraph.
A93: itanagar | B93: /itanagar/ | C93: 3 | D93: Trust strip | F93: =IF($F$5="","",$F$5) | G93: =$G$5 -> GSTIN 27FFLPP0007K1ZA (verify on the GST portal) · GST-registered since 2020 · Proprietorship led by Vikas Purohit, CEO · Manufacturing unit in Mumbai, Maharashtra [CLIENT: locality] · [CLIENT: real certifications only, e.g. ISO 9001:2015 — delete if none] · Written quotes by email, no calls needed | H93: =IF(LEN(TRIM(SUBSTITUTE(F93,CHAR(10)," ")))=0,0,LEN(TRIM(SUBSTITUTE(F93,CHAR(10)," ")))-LEN(SUBSTITUTE(TRIM(SUBSTITUTE(F93,CHAR(10)," "))," ",""))+1)+IF(LEN(TRIM(SUBSTITUTE(G93,CHAR(10)," ")))=0,0,LEN(TRIM(SUBSTITUTE(G93,CHAR(10)," ")))-LEN(SUBSTITUTE(TRIM(SUBSTITUTE(G93,CHAR(10)," "))," ",""))+1) -> 46 | I93: =IF(ISNUMBER(FIND("[CLIENT",F93&G93)),"CLIENT INPUT",IF(ISNUMBER(FIND("[CONFIRM",F93&G93)),"CONFIRM",IF(ISNUMBER(FIND("[DEV",F93&G93)),"DEV NOTE","Ready"))) -> CLIENT INPUT | J93: Shared
A94: itanagar | B94: /itanagar/ | C94: 4 | D94: Local demand | E94: H2 + P (table: tab 8b) | F94: Where flanges go in the capital region | G94: In and around Itanagar, flanges go mainly into water supply, public buildings and hydropower auxiliaries. Quantities are modest, so planning the logistics matters as much as the price. | H94: =IF(LEN(TRIM(SUBSTITUTE(F94,CHAR(10)," ")))=0,0,LEN(TRIM(SUBSTITUTE(F94,CHAR(10)," ")))-LEN(SUBSTITUTE(TRIM(SUBSTITUTE(F94,CHAR(10)," "))," ",""))+1)+IF(LEN(TRIM(SUBSTITUTE(G94,CHAR(10)," ")))=0,0,LEN(TRIM(SUBSTITUTE(G94,CHAR(10)," ")))-LEN(SUBSTITUTE(TRIM(SUBSTITUTE(G94,CHAR(10)," "))," ",""))+1) -> 35 | I94: =IF(ISNUMBER(FIND("[CLIENT",F94&G94)),"CLIENT INPUT",IF(ISNUMBER(FIND("[CONFIRM",F94&G94)),"CONFIRM",IF(ISNUMBER(FIND("[DEV",F94&G94)),"DEV NOTE","Ready"))) -> Ready | J94: Unique | K94: Table columns: Industry | Local sites and projects | Where flanges are used | What is usually specified.
A95: itanagar | B95: /itanagar/ | C95: 5 | D95: Materials guidance | E95: H2 + P | F95: Planning a flange delivery to Arunachal Pradesh | G95: Getting flanges to Itanagar is usually straightforward, but three things catch first-time buyers out. Permits. Anyone from outside the state who enters Arunachal Pradesh - including a truck's crew - needs an Inner Line Permit. We use transporters who handle this routinely [CONFIRM], but allow for it in your timeline. Monsoon. Landslide closures on hill roads are common in the monsoon months, so build a buffer into June-September deliveries and tell us your latest acceptable date. Consolidation. Small orders travel more economically when consolidated through Guwahati. If you can accept a slightly longer lead time, say so in the form and we will quote the cheaper route [CONFIRM offered]. | H95: =IF(LEN(TRIM(SUBSTITUTE(F95,CHAR(10)," ")))=0,0,LEN(TRIM(SUBSTITUTE(F95,CHAR(10)," ")))-LEN(SUBSTITUTE(TRIM(SUBSTITUTE(F95,CHAR(10)," "))," ",""))+1)+IF(LEN(TRIM(SUBSTITUTE(G95,CHAR(10)," ")))=0,0,LEN(TRIM(SUBSTITUTE(G95,CHAR(10)," ")))-LEN(SUBSTITUTE(TRIM(SUBSTITUTE(G95,CHAR(10)," "))," ",""))+1) -> 116 | I95: =IF(ISNUMBER(FIND("[CLIENT",F95&G95)),"CLIENT INPUT",IF(ISNUMBER(FIND("[CONFIRM",F95&G95)),"CONFIRM",IF(ISNUMBER(FIND("[DEV",F95&G95)),"DEV NOTE","Ready"))) -> CONFIRM | J95: Unique | K95: Each line break = new paragraph.
A96: itanagar | B96: /itanagar/ | C96: 6 | D96: Product range | E96: H2 + P (table: tab 8b) | F96: Flange types we supply to Itanagar & Naharlagun | G96: Most capital-region orders are MS/carbon-steel slip-on, weld neck and blind flanges in standard sizes; stainless and alloy grades are available for plant auxiliaries [CLIENT: confirm]. | H96: =IF(LEN(TRIM(SUBSTITUTE(F96,CHAR(10)," ")))=0,0,LEN(TRIM(SUBSTITUTE(F96,CHAR(10)," ")))-LEN(SUBSTITUTE(TRIM(SUBSTITUTE(F96,CHAR(10)," "))," ",""))+1)+IF(LEN(TRIM(SUBSTITUTE(G96,CHAR(10)," ")))=0,0,LEN(TRIM(SUBSTITUTE(G96,CHAR(10)," ")))-LEN(SUBSTITUTE(TRIM(SUBSTITUTE(G96,CHAR(10)," "))," ",""))+1) -> 33 | I96: =IF(ISNUMBER(FIND("[CLIENT",F96&G96)),"CLIENT INPUT",IF(ISNUMBER(FIND("[CONFIRM",F96&G96)),"CONFIRM",IF(ISNUMBER(FIND("[DEV",F96&G96)),"DEV NOTE","Ready"))) -> CLIENT INPUT | J96: Semi-unique | K96: Table columns: Flange type (link) | Typical use in Itanagar & Naharlagun.
A97: itanagar | B97: /itanagar/ | C97: 7 | D97: Manufacturing & QA | F97: =IF($F$6="","",$F$6) -> How every flange is made and checked | G97: =$G$6 -> Every flange starts as a certified billet or bar whose heat number follows it through cutting, forging, heat treatment where the material specification requires it, CNC machining and drilling, and final marking of grade, class, size and heat number. Before dispatch we check dimensions against the governing standard and [CLIENT: list only tests actually done in-house, e.g. PMI, hardness, ultrasonic], and issue material test certificates that tie each flange back to its heat. Buyer-nominated third-party inspection can witness any stage [CONFIRM]. | H97: =IF(LEN(TRIM(SUBSTITUTE(F97,CHAR(10)," ")))=0,0,LEN(TRIM(SUBSTITUTE(F97,CHAR(10)," ")))-LEN(SUBSTITUTE(TRIM(SUBSTITUTE(F97,CHAR(10)," "))," ",""))+1)+IF(LEN(TRIM(SUBSTITUTE(G97,CHAR(10)," ")))=0,0,LEN(TRIM(SUBSTITUTE(G97,CHAR(10)," ")))-LEN(SUBSTITUTE(TRIM(SUBSTITUTE(G97,CHAR(10)," "))," ",""))+1) -> 88 | I97: =IF(ISNUMBER(FIND("[CLIENT",F97&G97)),"CLIENT INPUT",IF(ISNUMBER(FIND("[CONFIRM",F97&G97)),"CONFIRM",IF(ISNUMBER(FIND("[DEV",F97&G97)),"DEV NOTE","Ready"))) -> CLIENT INPUT | J97: Shared
A98: itanagar | B98: /itanagar/ | C98: 8 | D98: Delivery & documents | E98: H2 + P | F98: Delivery to Itanagar, Naharlagun and Doimukh | G98: Consignments travel by road from Mumbai via Guwahati, entering Arunachal at the Banderdewa check gate, and typically reach the capital region [CLIENT: X-Y days] after dispatch [CLIENT: confirm route, and whether rail to Naharlagun is an option]. Invoices carry IGST as an inter-state supply, an e-way bill accompanies consignments above Rs 50,000, and material test certificates match each flange's heat number. | H98: =IF(LEN(TRIM(SUBSTITUTE(F98,CHAR(10)," ")))=0,0,LEN(TRIM(SUBSTITUTE(F98,CHAR(10)," ")))-LEN(SUBSTITUTE(TRIM(SUBSTITUTE(F98,CHAR(10)," "))," ",""))+1)+IF(LEN(TRIM(SUBSTITUTE(G98,CHAR(10)," ")))=0,0,LEN(TRIM(SUBSTITUTE(G98,CHAR(10)," ")))-LEN(SUBSTITUTE(TRIM(SUBSTITUTE(G98,CHAR(10)," "))," ",""))+1) -> 67 | I98: =IF(ISNUMBER(FIND("[CLIENT",F98&G98)),"CLIENT INPUT",IF(ISNUMBER(FIND("[CONFIRM",F98&G98)),"CONFIRM",IF(ISNUMBER(FIND("[DEV",F98&G98)),"DEV NOTE","Ready"))) -> CLIENT INPUT | J98: Unique
A99: itanagar | B99: /itanagar/ | C99: 9 | D99: Price guidance | E99: H2 + P | F99: Freight and pricing for small Northeast orders | G99: Freight is a bigger share of the cost on small Northeast orders, so we show it as a separate line and suggest consolidation where it saves money [CONFIRM]. [CLIENT: indicative Rs/kg bands.] | H99: =IF(LEN(TRIM(SUBSTITUTE(F99,CHAR(10)," ")))=0,0,LEN(TRIM(SUBSTITUTE(F99,CHAR(10)," ")))-LEN(SUBSTITUTE(TRIM(SUBSTITUTE(F99,CHAR(10)," "))," ",""))+1)+IF(LEN(TRIM(SUBSTITUTE(G99,CHAR(10)," ")))=0,0,LEN(TRIM(SUBSTITUTE(G99,CHAR(10)," ")))-LEN(SUBSTITUTE(TRIM(SUBSTITUTE(G99,CHAR(10)," "))," ",""))+1) -> 39 | I99: =IF(ISNUMBER(FIND("[CLIENT",F99&G99)),"CLIENT INPUT",IF(ISNUMBER(FIND("[CONFIRM",F99&G99)),"CONFIRM",IF(ISNUMBER(FIND("[DEV",F99&G99)),"DEV NOTE","Ready"))) -> CLIENT INPUT | J99: Unique | K99: Add the dated Rs/kg band table here once the client supplies it (tab 15 I-26).
A100: itanagar | B100: /itanagar/ | C100: 10 | D100: Areas served | E100: H2 + P | F100: Areas we deliver in the capital region | G100: We deliver across Itanagar, Naharlagun, Nirjuli, Banderdewa and Doimukh. Tawang, Ziro, Pasighat and the rest of the state are covered on our Arunachal Pradesh page. | H100: =IF(LEN(TRIM(SUBSTITUTE(F100,CHAR(10)," ")))=0,0,LEN(TRIM(SUBSTITUTE(F100,CHAR(10)," ")))-LEN(SUBSTITUTE(TRIM(SUBSTITUTE(F100,CHAR(10)," "))," ",""))+1)+IF(LEN(TRIM(SUBSTITUTE(G100,CHAR(10)," ")))=0,0,LEN(TRIM(SUBSTITUTE(G100,CHAR(10)," ")))-LEN(SUBSTITUTE(TRIM(SUBSTITUTE(G100,CHAR(10)," "))," ",""))+1) -> 32 | I100: =IF(ISNUMBER(FIND("[CLIENT",F100&G100)),"CLIENT INPUT",IF(ISNUMBER(FIND("[CONFIRM",F100&G100)),"CONFIRM",IF(ISNUMBER(FIND("[DEV",F100&G100)),"DEV NOTE","Ready"))) -> Ready | J100: Unique | K100: Plain text, no locality links.
A101: itanagar | B101: /itanagar/ | C101: 11 | D101: Request a quote | F101: =IF($F$7="","",$F$7) -> Request a written quote | G101: =$G$7 -> A quote-ready enquiry lists: flange type · nominal size (NPS or DN) · pressure class or PN · facing (RF, FF or RTJ) · material specification and grade · bore or schedule for weld neck flanges · quantity · delivery location · testing and certificate needs (NACE, impact test, EN 10204 3.1/3.2, third-party inspection). Upload a BOQ or drawing and we will read it for you. | H101: =IF(LEN(TRIM(SUBSTITUTE(F101,CHAR(10)," ")))=0,0,LEN(TRIM(SUBSTITUTE(F101,CHAR(10)," ")))-LEN(SUBSTITUTE(TRIM(SUBSTITUTE(F101,CHAR(10)," "))," ",""))+1)+IF(LEN(TRIM(SUBSTITUTE(G101,CHAR(10)," ")))=0,0,LEN(TRIM(SUBSTITUTE(G101,CHAR(10)," ")))-LEN(SUBSTITUTE(TRIM(SUBSTITUTE(G101,CHAR(10)," "))," ",""))+1) -> 70 | I101: =IF(ISNUMBER(FIND("[CLIENT",F101&G101)),"CLIENT INPUT",IF(ISNUMBER(FIND("[CONFIRM",F101&G101)),"CONFIRM",IF(ISNUMBER(FIND("[DEV",F101&G101)),"DEV NOTE","Ready"))) -> Ready | J101: Shared
...

Sheet 8b. Page Tables (Paste)
A1: 8b. Page tables (paste-ready) - the local-demand table and the product-range table for each city page
A2: Build both as real HTML tables (not images). Product links are slash-form; rows marked [CONFIRM] need the slug checked before launch (otherwise link /products/flanges/).
A4: Page key | B4: Table | C4: Row | D4: Column 1 | E4: Column 2 | F4: Column 3 | G4: Column 4 | H4: Words | I4: Status | J4: Note
A5: vizag | B5: Local demand | C5: 1 | D5: Integrated steel | E5: Visakhapatnam Steel Plant (RINL); AM/NS India's 8.2 MTPA greenfield plant at Rajayyapeta, Anakapalli (foundation stone laid March 2026, steelmaking targeted for 2029) | F5: Cooling water, compressed air, fuel gas, oxygen / nitrogen / argon distribution, hydraulic systems | G5: A105 weld neck and slip-on, Class 150-300 RF for water and air; 304L/316L for industrial gases (oxygen service needs cleaned, certified components); blind and spectacle blinds for isolation | H5: =IF(LEN(TRIM(SUBSTITUTE(D5,CHAR(10)," ")))=0,0,LEN(TRIM(SUBSTITUTE(D5,CHAR(10)," ")))-LEN(SUBSTITUTE(TRIM(SUBSTITUTE(D5,CHAR(10)," "))," ",""))+1)+IF(LEN(TRIM(SUBSTITUTE(E5,CHAR(10)," ")))=0,0,LEN(TRIM(SUBSTITUTE(E5,CHAR(10)," ")))-LEN(SUBSTITUTE(TRIM(SUBSTITUTE(E5,CHAR(10)," "))," ",""))+1)+IF(LEN(TRIM(SUBSTITUTE(F5,CHAR(10)," ")))=0,0,LEN(TRIM(SUBSTITUTE(F5,CHAR(10)," ")))-LEN(SUBSTITUTE(TRIM(SUBSTITUTE(F5,CHAR(10)," "))," ",""))+1)+IF(LEN(TRIM(SUBSTITUTE(G5,CHAR(10)," ")))=0,0,LEN(TRIM(SUBSTITUTE(G5,CHAR(10)," ")))-LEN(SUBSTITUTE(TRIM(SUBSTITUTE(G5,CHAR(10)," "))," ",""))+1) -> 66 | I5: =IF(ISNUMBER(FIND("[CLIENT",D5&E5&F5&G5)),"CLIENT INPUT",IF(ISNUMBER(FIND("[CONFIRM",D5&E5&F5&G5)),"CONFIRM",IF(ISNUMBER(FIND("[DEV",D5&E5&F5&G5)),"DEV NOTE","Ready"))) -> Ready | J5: Headers: Industry | Local sites and projects | Where flanges are used | What is usually specified
A6: vizag | B6: Local demand | C6: 2 | D6: Refining & fuel terminals | E6: HPCL Visakh Refinery and petroleum product terminals around the port | F6: Process and utility lines, hydrocarbon storage and loading, flare headers | G6: A105 weld neck RF/RTJ from Class 150 upward; A182 F5/F9 where hot, sulphur-bearing streams need chrome-moly; NACE MR0103 / ISO 17945 for wet H2S refinery service | H6: =IF(LEN(TRIM(SUBSTITUTE(D6,CHAR(10)," ")))=0,0,LEN(TRIM(SUBSTITUTE(D6,CHAR(10)," ")))-LEN(SUBSTITUTE(TRIM(SUBSTITUTE(D6,CHAR(10)," "))," ",""))+1)+IF(LEN(TRIM(SUBSTITUTE(E6,CHAR(10)," ")))=0,0,LEN(TRIM(SUBSTITUTE(E6,CHAR(10)," ")))-LEN(SUBSTITUTE(TRIM(SUBSTITUTE(E6,CHAR(10)," "))," ",""))+1)+IF(LEN(TRIM(SUBSTITUTE(F6,CHAR(10)," ")))=0,0,LEN(TRIM(SUBSTITUTE(F6,CHAR(10)," ")))-LEN(SUBSTITUTE(TRIM(SUBSTITUTE(F6,CHAR(10)," "))," ",""))+1)+IF(LEN(TRIM(SUBSTITUTE(G6,CHAR(10)," ")))=0,0,LEN(TRIM(SUBSTITUTE(G6,CHAR(10)," ")))-LEN(SUBSTITUTE(TRIM(SUBSTITUTE(G6,CHAR(10)," "))," ",""))+1) -> 50 | I6: =IF(ISNUMBER(FIND("[CLIENT",D6&E6&F6&G6)),"CLIENT INPUT",IF(ISNUMBER(FIND("[CONFIRM",D6&E6&F6&G6)),"CONFIRM",IF(ISNUMBER(FIND("[DEV",D6&E6&F6&G6)),"DEV NOTE","Ready"))) -> Ready
A7: vizag | B7: Local demand | C7: 3 | D7: Ports, shipbuilding & marine | E7: Visakhapatnam Port, Gangavaram Port, Hindustan Shipyard; captive port approved for AM/NS at D.L. Puram | F7: Fire-water rings, bunker and fuel lines, ballast and seawater cooling, cargo-handling hydraulics | G7: A105 (painted or galvanised) for freshwater fire-water; super duplex A182 F53/F55 or 6Mo F44 where seawater wets the flange; 316L for marine air, not immersion | H7: =IF(LEN(TRIM(SUBSTITUTE(D7,CHAR(10)," ")))=0,0,LEN(TRIM(SUBSTITUTE(D7,CHAR(10)," ")))-LEN(SUBSTITUTE(TRIM(SUBSTITUTE(D7,CHAR(10)," "))," ",""))+1)+IF(LEN(TRIM(SUBSTITUTE(E7,CHAR(10)," ")))=0,0,LEN(TRIM(SUBSTITUTE(E7,CHAR(10)," ")))-LEN(SUBSTITUTE(TRIM(SUBSTITUTE(E7,CHAR(10)," "))," ",""))+1)+IF(LEN(TRIM(SUBSTITUTE(F7,CHAR(10)," ")))=0,0,LEN(TRIM(SUBSTITUTE(F7,CHAR(10)," ")))-LEN(SUBSTITUTE(TRIM(SUBSTITUTE(F7,CHAR(10)," "))," ",""))+1)+IF(LEN(TRIM(SUBSTITUTE(G7,CHAR(10)," ")))=0,0,LEN(TRIM(SUBSTITUTE(G7,CHAR(10)," ")))-LEN(SUBSTITUTE(TRIM(SUBSTITUTE(G7,CHAR(10)," "))," ",""))+1) -> 55 | I7: =IF(ISNUMBER(FIND("[CLIENT",D7&E7&F7&G7)),"CLIENT INPUT",IF(ISNUMBER(FIND("[CONFIRM",D7&E7&F7&G7)),"CONFIRM",IF(ISNUMBER(FIND("[DEV",D7&E7&F7&G7)),"DEV NOTE","Ready"))) -> Ready
A8: vizag | B8: Local demand | C8: 4 | D8: Power & new energy | E8: NTPC Simhadri; NTPC Green's hydrogen hub planned at Pudimadaka | F8: Feedwater and steam, cooling water, demineralised water, gas utilities | G8: A182 F11/F22 (F91 for higher-temperature steam) weld neck, Class 600-1500; A105 for cooling water; 316L for DM water | H8: =IF(LEN(TRIM(SUBSTITUTE(D8,CHAR(10)," ")))=0,0,LEN(TRIM(SUBSTITUTE(D8,CHAR(10)," ")))-LEN(SUBSTITUTE(TRIM(SUBSTITUTE(D8,CHAR(10)," "))," ",""))+1)+IF(LEN(TRIM(SUBSTITUTE(E8,CHAR(10)," ")))=0,0,LEN(TRIM(SUBSTITUTE(E8,CHAR(10)," ")))-LEN(SUBSTITUTE(TRIM(SUBSTITUTE(E8,CHAR(10)," "))," ",""))+1)+IF(LEN(TRIM(SUBSTITUTE(F8,CHAR(10)," ")))=0,0,LEN(TRIM(SUBSTITUTE(F8,CHAR(10)," ")))-LEN(SUBSTITUTE(TRIM(SUBSTITUTE(F8,CHAR(10)," "))," ",""))+1)+IF(LEN(TRIM(SUBSTITUTE(G8,CHAR(10)," ")))=0,0,LEN(TRIM(SUBSTITUTE(G8,CHAR(10)," ")))-LEN(SUBSTITUTE(TRIM(SUBSTITUTE(G8,CHAR(10)," "))," ",""))+1) -> 40 | I8: =IF(ISNUMBER(FIND("[CLIENT",D8&E8&F8&G8)),"CLIENT INPUT",IF(ISNUMBER(FIND("[CONFIRM",D8&E8&F8&G8)),"CONFIRM",IF(ISNUMBER(FIND("[DEV",D8&E8&F8&G8)),"DEV NOTE","Ready"))) -> Ready
A9: vizag | B9: Local demand | C9: 5 | D9: Pharma & chemicals | E9: Jawaharlal Nehru Pharma City (Parawada), Visakhapatnam SEZ (Duvvada), Atchutapuram SEZ, the bulk drug park at Nakkapalli | F9: Plant utilities - steam, condensate, cooling water, solvents, nitrogen - and effluent treatment | G9: 316L slip-on or weld neck, Class 150, for solvents and nitrogen; A105 for steam utilities. Product-contact hygienic lines normally use ASME BPE fittings, not B16.5 flanges | H9: =IF(LEN(TRIM(SUBSTITUTE(D9,CHAR(10)," ")))=0,0,LEN(TRIM(SUBSTITUTE(D9,CHAR(10)," ")))-LEN(SUBSTITUTE(TRIM(SUBSTITUTE(D9,CHAR(10)," "))," ",""))+1)+IF(LEN(TRIM(SUBSTITUTE(E9,CHAR(10)," ")))=0,0,LEN(TRIM(SUBSTITUTE(E9,CHAR(10)," ")))-LEN(SUBSTITUTE(TRIM(SUBSTITUTE(E9,CHAR(10)," "))," ",""))+1)+IF(LEN(TRIM(SUBSTITUTE(F9,CHAR(10)," ")))=0,0,LEN(TRIM(SUBSTITUTE(F9,CHAR(10)," ")))-LEN(SUBSTITUTE(TRIM(SUBSTITUTE(F9,CHAR(10)," "))," ",""))+1)+IF(LEN(TRIM(SUBSTITUTE(G9,CHAR(10)," ")))=0,0,LEN(TRIM(SUBSTITUTE(G9,CHAR(10)," ")))-LEN(SUBSTITUTE(TRIM(SUBSTITUTE(G9,CHAR(10)," "))," ",""))+1) -> 58 | I9: =IF(ISNUMBER(FIND("[CLIENT",D9&E9&F9&G9)),"CLIENT INPUT",IF(ISNUMBER(FIND("[CONFIRM",D9&E9&F9&G9)),"CONFIRM",IF(ISNUMBER(FIND("[DEV",D9&E9&F9&G9)),"DEV NOTE","Ready"))) -> Ready
A10: vizag | B10: Local demand | C10: 6 | D10: Heavy fabrication | E10: BHEL's Heavy Plates & Vessels Plant and fabricators around Autonagar and Gajuwaka | F10: Nozzle flanges for pressure vessels, heat exchangers and skids | G10: Weld neck and long weld neck to drawing; A105, A350 LF2 or A182 grades to match the vessel design code | H10: =IF(LEN(TRIM(SUBSTITUTE(D10,CHAR(10)," ")))=0,0,LEN(TRIM(SUBSTITUTE(D10,CHAR(10)," ")))-LEN(SUBSTITUTE(TRIM(SUBSTITUTE(D10,CHAR(10)," "))," ",""))+1)+IF(LEN(TRIM(SUBSTITUTE(E10,CHAR(10)," ")))=0,0,LEN(TRIM(SUBSTITUTE(E10,CHAR(10)," ")))-LEN(SUBSTITUTE(TRIM(SUBSTITUTE(E10,CHAR(10)," "))," ",""))+1)+IF(LEN(TRIM(SUBSTITUTE(F10,CHAR(10)," ")))=0,0,LEN(TRIM(SUBSTITUTE(F10,CHAR(10)," ")))-LEN(SUBSTITUTE(TRIM(SUBSTITUTE(F10,CHAR(10)," "))," ",""))+1)+IF(LEN(TRIM(SUBSTITUTE(G10,CHAR(10)," ")))=0,0,LEN(TRIM(SUBSTITUTE(G10,CHAR(10)," ")))-LEN(SUBSTITUTE(TRIM(SUBSTITUTE(G10,CHAR(10)," "))," ",""))+1) -> 43 | I10: =IF(ISNUMBER(FIND("[CLIENT",D10&E10&F10&G10)),"CLIENT INPUT",IF(ISNUMBER(FIND("[CONFIRM",D10&E10&F10&G10)),"CONFIRM",IF(ISNUMBER(FIND("[DEV",D10&E10&F10&G10)),"DEV NOTE","Ready"))) -> Ready
A11: vizag | B11: Product range | C11: 1 | D11: Weld neck (WNRF / WNRTJ) | E11: /products/flanges/weld-neck-flange/ | F11: Refinery process lines and power-plant steam piping | G11: [CONFIRM] slug exists - else link /products/flanges/ | H11: =IF(LEN(TRIM(SUBSTITUTE(D11,CHAR(10)," ")))=0,0,LEN(TRIM(SUBSTITUTE(D11,CHAR(10)," ")))-LEN(SUBSTITUTE(TRIM(SUBSTITUTE(D11,CHAR(10)," "))," ",""))+1)+IF(LEN(TRIM(SUBSTITUTE(F11,CHAR(10)," ")))=0,0,LEN(TRIM(SUBSTITUTE(F11,CHAR(10)," ")))-LEN(SUBSTITUTE(TRIM(SUBSTITUTE(F11,CHAR(10)," "))," ",""))+1) -> 12 | I11: =IF(ISNUMBER(FIND("[CLIENT",D11&E11&F11&G11)),"CLIENT INPUT",IF(ISNUMBER(FIND("[CONFIRM",D11&E11&F11&G11)),"CONFIRM",IF(ISNUMBER(FIND("[DEV",D11&E11&F11&G11)),"DEV NOTE","Ready"))) -> CONFIRM | J11: Headers: Flange type | Typical use in Visakhapatnam (link column D to the URL in column E)
A12: vizag | B12: Product range | C12: 2 | D12: Slip-on (SORF / SOFF) | E12: /products/flanges/slip-on-flange/ | F12: Fire-water rings and cooling water at the port and steel plant | G12: Yes - live page | H12: =IF(LEN(TRIM(SUBSTITUTE(D12,CHAR(10)," ")))=0,0,LEN(TRIM(SUBSTITUTE(D12,CHAR(10)," ")))-LEN(SUBSTITUTE(TRIM(SUBSTITUTE(D12,CHAR(10)," "))," ",""))+1)+IF(LEN(TRIM(SUBSTITUTE(F12,CHAR(10)," ")))=0,0,LEN(TRIM(SUBSTITUTE(F12,CHAR(10)," ")))-LEN(SUBSTITUTE(TRIM(SUBSTITUTE(F12,CHAR(10)," "))," ",""))+1) -> 15 | I12: =IF(ISNUMBER(FIND("[CLIENT",D12&E12&F12&G12)),"CLIENT INPUT",IF(ISNUMBER(FIND("[CONFIRM",D12&E12&F12&G12)),"CONFIRM",IF(ISNUMBER(FIND("[DEV",D12&E12&F12&G12)),"DEV NOTE","Ready"))) -> Ready
A13: vizag | B13: Product range | C13: 3 | D13: Blind (BLRF / BLFF) | E13: /products/flanges/blind-flange/ | F13: Isolation points and future tie-ins on plant headers | G13: [CONFIRM] slug exists - else link /products/flanges/ | H13: =IF(LEN(TRIM(SUBSTITUTE(D13,CHAR(10)," ")))=0,0,LEN(TRIM(SUBSTITUTE(D13,CHAR(10)," ")))-LEN(SUBSTITUTE(TRIM(SUBSTITUTE(D13,CHAR(10)," "))," ",""))+1)+IF(LEN(TRIM(SUBSTITUTE(F13,CHAR(10)," ")))=0,0,LEN(TRIM(SUBSTITUTE(F13,CHAR(10)," ")))-LEN(SUBSTITUTE(TRIM(SUBSTITUTE(F13,CHAR(10)," "))," ",""))+1) -> 12 | I13: =IF(ISNUMBER(FIND("[CLIENT",D13&E13&F13&G13)),"CLIENT INPUT",IF(ISNUMBER(FIND("[CONFIRM",D13&E13&F13&G13)),"CONFIRM",IF(ISNUMBER(FIND("[DEV",D13&E13&F13&G13)),"DEV NOTE","Ready"))) -> CONFIRM
A14: vizag | B14: Product range | C14: 4 | D14: Spectacle blind, spade & spacer | E14: /products/flanges/spectacle-blind-flange/ | F14: Positive isolation on refinery and fuel-gas lines during shutdowns | G14: Yes - live page | H14: =IF(LEN(TRIM(SUBSTITUTE(D14,CHAR(10)," ")))=0,0,LEN(TRIM(SUBSTITUTE(D14,CHAR(10)," ")))-LEN(SUBSTITUTE(TRIM(SUBSTITUTE(D14,CHAR(10)," "))," ",""))+1)+IF(LEN(TRIM(SUBSTITUTE(F14,CHAR(10)," ")))=0,0,LEN(TRIM(SUBSTITUTE(F14,CHAR(10)," ")))-LEN(SUBSTITUTE(TRIM(SUBSTITUTE(F14,CHAR(10)," "))," ",""))+1) -> 14 | I14: =IF(ISNUMBER(FIND("[CLIENT",D14&E14&F14&G14)),"CLIENT INPUT",IF(ISNUMBER(FIND("[CONFIRM",D14&E14&F14&G14)),"CONFIRM",IF(ISNUMBER(FIND("[DEV",D14&E14&F14&G14)),"DEV NOTE","Ready"))) -> Ready
A15: vizag | B15: Product range | C15: 5 | D15: Socket weld | E15: /products/flanges/socket-weld-flange/ | F15: Small-bore instrument and utility lines in pharma and refinery units | G15: [CONFIRM] slug exists - else link /products/flanges/ | H15: =IF(LEN(TRIM(SUBSTITUTE(D15,CHAR(10)," ")))=0,0,LEN(TRIM(SUBSTITUTE(D15,CHAR(10)," ")))-LEN(SUBSTITUTE(TRIM(SUBSTITUTE(D15,CHAR(10)," "))," ",""))+1)+IF(LEN(TRIM(SUBSTITUTE(F15,CHAR(10)," ")))=0,0,LEN(TRIM(SUBSTITUTE(F15,CHAR(10)," ")))-LEN(SUBSTITUTE(TRIM(SUBSTITUTE(F15,CHAR(10)," "))," ",""))+1) -> 12 | I15: =IF(ISNUMBER(FIND("[CLIENT",D15&E15&F15&G15)),"CLIENT INPUT",IF(ISNUMBER(FIND("[CONFIRM",D15&E15&F15&G15)),"CONFIRM",IF(ISNUMBER(FIND("[DEV",D15&E15&F15&G15)),"DEV NOTE","Ready"))) -> CONFIRM
A16: vizag | B16: Product range | C16: 6 | D16: Threaded | E16: /products/flanges/threaded-flange/ | F16: Small, non-critical utility lines where hot work is restricted | G16: [CONFIRM] slug exists - else link /products/flanges/ | H16: =IF(LEN(TRIM(SUBSTITUTE(D16,CHAR(10)," ")))=0,0,LEN(TRIM(SUBSTITUTE(D16,CHAR(10)," ")))-LEN(SUBSTITUTE(TRIM(SUBSTITUTE(D16,CHAR(10)," "))," ",""))+1)+IF(LEN(TRIM(SUBSTITUTE(F16,CHAR(10)," ")))=0,0,LEN(TRIM(SUBSTITUTE(F16,CHAR(10)," ")))-LEN(SUBSTITUTE(TRIM(SUBSTITUTE(F16,CHAR(10)," "))," ",""))+1) -> 10 | I16: =IF(ISNUMBER(FIND("[CLIENT",D16&E16&F16&G16)),"CLIENT INPUT",IF(ISNUMBER(FIND("[CONFIRM",D16&E16&F16&G16)),"CONFIRM",IF(ISNUMBER(FIND("[DEV",D16&E16&F16&G16)),"DEV NOTE","Ready"))) -> CONFIRM
A17: vizag | B17: Product range | C17: 7 | D17: Lap joint (with stub end) | E17: /products/flanges/lap-joint-flange/ | F17: Stainless lines that are dismantled for cleaning or inspection | G17: [CONFIRM] slug exists - else link /products/flanges/ | H17: =IF(LEN(TRIM(SUBSTITUTE(D17,CHAR(10)," ")))=0,0,LEN(TRIM(SUBSTITUTE(D17,CHAR(10)," ")))-LEN(SUBSTITUTE(TRIM(SUBSTITUTE(D17,CHAR(10)," "))," ",""))+1)+IF(LEN(TRIM(SUBSTITUTE(F17,CHAR(10)," ")))=0,0,LEN(TRIM(SUBSTITUTE(F17,CHAR(10)," ")))-LEN(SUBSTITUTE(TRIM(SUBSTITUTE(F17,CHAR(10)," "))," ",""))+1) -> 14 | I17: =IF(ISNUMBER(FIND("[CLIENT",D17&E17&F17&G17)),"CLIENT INPUT",IF(ISNUMBER(FIND("[CONFIRM",D17&E17&F17&G17)),"CONFIRM",IF(ISNUMBER(FIND("[DEV",D17&E17&F17&G17)),"DEV NOTE","Ready"))) -> CONFIRM
A18: vijayawada | B18: Local demand | C18: 1 | D18: Thermal power | E18: Dr. Narla Tata Rao Thermal Power Station (APGENCO) at Ibrahimpatnam | F18: Boiler feedwater and steam, cooling water, fuel oil, ash handling | G18: A182 F11/F22 (F91 for higher-temperature steam) weld neck, Class 600-2500; A105 for cooling water and fuel oil; slip-on or plate flanges on lined ash-slurry lines | H18: =IF(LEN(TRIM(SUBSTITUTE(D18,CHAR(10)," ")))=0,0,LEN(TRIM(SUBSTITUTE(D18,CHAR(10)," ")))-LEN(SUBSTITUTE(TRIM(SUBSTITUTE(D18,CHAR(10)," "))," ",""))+1)+IF(LEN(TRIM(SUBSTITUTE(E18,CHAR(10)," ")))=0,0,LEN(TRIM(SUBSTITUTE(E18,CHAR(10)," ")))-LEN(SUBSTITUTE(TRIM(SUBSTITUTE(E18,CHAR(10)," "))," ",""))+1)+IF(LEN(TRIM(SUBSTITUTE(F18,CHAR(10)," ")))=0,0,LEN(TRIM(SUBSTITUTE(F18,CHAR(10)," ")))-LEN(SUBSTITUTE(TRIM(SUBSTITUTE(F18,CHAR(10)," "))," ",""))+1)+IF(LEN(TRIM(SUBSTITUTE(G18,CHAR(10)," ")))=0,0,LEN(TRIM(SUBSTITUTE(G18,CHAR(10)," ")))-LEN(SUBSTITUTE(TRIM(SUBSTITUTE(G18,CHAR(10)," "))," ",""))+1) -> 47 | I18: =IF(ISNUMBER(FIND("[CLIENT",D18&E18&F18&G18)),"CLIENT INPUT",IF(ISNUMBER(FIND("[CONFIRM",D18&E18&F18&G18)),"CONFIRM",IF(ISNUMBER(FIND("[DEV",D18&E18&F18&G18)),"DEV NOTE","Ready"))) -> Ready | J18: Headers: Industry | Local sites and projects | Where flanges are used | What is usually specified
A19: vijayawada | B19: Local demand | C19: 2 | D19: Industrial estates | E19: Kondapalli Industrial Development Area, Autonagar workshops and body builders, the Mallavalli industrial park | F19: Process piping, boilers and steam, compressed air, skids and fabricated assemblies | G19: A105 slip-on and weld neck, Class 150-300 RF; 304L/316L for food-processing utilities | H19: =IF(LEN(TRIM(SUBSTITUTE(D19,CHAR(10)," ")))=0,0,LEN(TRIM(SUBSTITUTE(D19,CHAR(10)," ")))-LEN(SUBSTITUTE(TRIM(SUBSTITUTE(D19,CHAR(10)," "))," ",""))+1)+IF(LEN(TRIM(SUBSTITUTE(E19,CHAR(10)," ")))=0,0,LEN(TRIM(SUBSTITUTE(E19,CHAR(10)," ")))-LEN(SUBSTITUTE(TRIM(SUBSTITUTE(E19,CHAR(10)," "))," ",""))+1)+IF(LEN(TRIM(SUBSTITUTE(F19,CHAR(10)," ")))=0,0,LEN(TRIM(SUBSTITUTE(F19,CHAR(10)," ")))-LEN(SUBSTITUTE(TRIM(SUBSTITUTE(F19,CHAR(10)," "))," ",""))+1)+IF(LEN(TRIM(SUBSTITUTE(G19,CHAR(10)," ")))=0,0,LEN(TRIM(SUBSTITUTE(G19,CHAR(10)," ")))-LEN(SUBSTITUTE(TRIM(SUBSTITUTE(G19,CHAR(10)," "))," ",""))+1) -> 38 | I19: =IF(ISNUMBER(FIND("[CLIENT",D19&E19&F19&G19)),"CLIENT INPUT",IF(ISNUMBER(FIND("[CONFIRM",D19&E19&F19&G19)),"CONFIRM",IF(ISNUMBER(FIND("[DEV",D19&E19&F19&G19)),"DEV NOTE","Ready"))) -> Ready
A20: vijayawada | B20: Local demand | C20: 3 | D20: Capital city construction | E20: Amaravati Capital Phase-I: the World Bank and ADB have committed US$1.6 billion, and contractors are mobilised on arterial roads, housing and government buildings and city-wide systems | F20: Water mains and pumping stations, sewerage and drainage, fire-fighting and HVAC plant rooms in large buildings | G20: Slip-on, blind and large-bore flanges drilled to AWWA C207, EN 1092-1 PN10/PN16 or IS 6392 as the tender specifies; A105 Class 150 for fire mains | H20: =IF(LEN(TRIM(SUBSTITUTE(D20,CHAR(10)," ")))=0,0,LEN(TRIM(SUBSTITUTE(D20,CHAR(10)," ")))-LEN(SUBSTITUTE(TRIM(SUBSTITUTE(D20,CHAR(10)," "))," ",""))+1)+IF(LEN(TRIM(SUBSTITUTE(E20,CHAR(10)," ")))=0,0,LEN(TRIM(SUBSTITUTE(E20,CHAR(10)," ")))-LEN(SUBSTITUTE(TRIM(SUBSTITUTE(E20,CHAR(10)," "))," ",""))+1)+IF(LEN(TRIM(SUBSTITUTE(F20,CHAR(10)," ")))=0,0,LEN(TRIM(SUBSTITUTE(F20,CHAR(10)," ")))-LEN(SUBSTITUTE(TRIM(SUBSTITUTE(F20,CHAR(10)," "))," ",""))+1)+IF(LEN(TRIM(SUBSTITUTE(G20,CHAR(10)," ")))=0,0,LEN(TRIM(SUBSTITUTE(G20,CHAR(10)," ")))-LEN(SUBSTITUTE(TRIM(SUBSTITUTE(G20,CHAR(10)," "))," ",""))+1) -> 70 | I20: =IF(ISNUMBER(FIND("[CLIENT",D20&E20&F20&G20)),"CLIENT INPUT",IF(ISNUMBER(FIND("[CONFIRM",D20&E20&F20&G20)),"CONFIRM",IF(ISNUMBER(FIND("[DEV",D20&E20&F20&G20)),"DEV NOTE","Ready"))) -> Ready
A21: vijayawada | B21: Local demand | C21: 4 | D21: Water & irrigation | E21: Krishna river works around Prakasam Barrage, the delta canal system and municipal water supply | F21: Pump discharge headers, valve chambers, surge and air-release branches | G21: Large-diameter plate or slip-on flanges, PN10/PN16 or Class 150; blind flanges for future tap-offs | H21: =IF(LEN(TRIM(SUBSTITUTE(D21,CHAR(10)," ")))=0,0,LEN(TRIM(SUBSTITUTE(D21,CHAR(10)," ")))-LEN(SUBSTITUTE(TRIM(SUBSTITUTE(D21,CHAR(10)," "))," ",""))+1)+IF(LEN(TRIM(SUBSTITUTE(E21,CHAR(10)," ")))=0,0,LEN(TRIM(SUBSTITUTE(E21,CHAR(10)," ")))-LEN(SUBSTITUTE(TRIM(SUBSTITUTE(E21,CHAR(10)," "))," ",""))+1)+IF(LEN(TRIM(SUBSTITUTE(F21,CHAR(10)," ")))=0,0,LEN(TRIM(SUBSTITUTE(F21,CHAR(10)," ")))-LEN(SUBSTITUTE(TRIM(SUBSTITUTE(F21,CHAR(10)," "))," ",""))+1)+IF(LEN(TRIM(SUBSTITUTE(G21,CHAR(10)," ")))=0,0,LEN(TRIM(SUBSTITUTE(G21,CHAR(10)," ")))-LEN(SUBSTITUTE(TRIM(SUBSTITUTE(G21,CHAR(10)," "))," ",""))+1) -> 40 | I21: =IF(ISNUMBER(FIND("[CLIENT",D21&E21&F21&G21)),"CLIENT INPUT",IF(ISNUMBER(FIND("[CONFIRM",D21&E21&F21&G21)),"CONFIRM",IF(ISNUMBER(FIND("[DEV",D21&E21&F21&G21)),"DEV NOTE","Ready"))) -> Ready
